Workbook

Sheet MJ 5.0 - ND Task list
B1: Level | C1: Phân loại công việc | D1: Đầu việc | E1: PIC | F1: Quantity | G1: Capacity/unit | H1: Task capacity | I1: Start date | J1: End date | K1: Status | L1: Note | M1: Tháng 6 | Q1: Tháng 7 | U1: Tháng 8
A2: Luồng học chính
A3: =row()-2 -> 1 | B3: Level 0 | C3: Data | D3: Pair lại data 2 topics = 8 từ | E3: Duyên | G3: 1 | K3: Done
A4: =row()-2 -> 2 | B4: Level 0 | C4: Data | D4: Check data của Monkey Kindy, MS để match với data M.ABC -> sắp xếp lại thứ tự | E4: Duyên | K4: Done
A5: =row()-2 -> 3 | B5: Level 0 | C5: Data | D5: Config data 41 units | E5: Duyên | J5: 28/6 | K5: Done
A6: =row()-2 -> 4 | B6: Level 0 | C6: Game | D6: Nghiên cứu + chốt game dùng để thể hiện truyện MS/ video Kindy | E6: Duyên | K6: Done
A7: =row()-2 -> 5 | B7: Level 0 | C7: Game | D7: A Dũng đánh giá lại sửa file gaf truyện anim sang spine để đưa lên game | E7: Media | K7: Cancelled
A8: 6 | B8: Level 0 | D8: Dev 8 games | E8: KT | K8: Doing
A9: =row()-2 -> 7 | B9: Level 1-5 | C9: Data | D9: Tổng hợp data audio truyện + act MTC Story | E9: Thiên Anh | K9: Done
A10: =row()-2 -> 8 | B10: Level 1-5 | D10: Config data 3 unit test | E10: Thiên Anh | K10: Done
A11: =row()-2 -> 9 | B11: Level 1-5 | D11: Test data 3 unit test | E11: Thiên Anh | K11: Done
A12: =row()-2 -> 10 | B12: Level 1-5 | D12: Test 34 game done dev | E12: Thiên Anh | J12: 45467 | K12: Done
A13: =row()-2 -> 11 | B13: Level 1-5 | D13: Nghiệm thu các game có CR (sau TNNB) | E13: Thiên Anh | K13: NYS
A14: =row()-2 -> 12 | B14: Level 1-5 | D14: Test full luồng 3 unit | E14: Thiên Anh | J14: 45468 | K14: Done
A15: =row()-2 -> 13 | B15: Level 1-5 | D15: Hoàn thiện data full 60 unit | E15: Thiên Anh | K15: Done
A16: =row()-2 -> 14 | B16: Level 1-5 | C16: Game | D16: Config data full truyện + hội thoại | E16: KT | K16: Done
A17: =row()-2 -> 15 | B17: Level 1-5 | D17: Test + sửa lại full data truyện | E17: Thiên Anh | J17: 45471 | K17: Done
A18: =row()-2 -> 16 | B18: Level 1-5 | D18: Test + sửa lại full data hội thoại | E18: Thiên Anh | J18: 45471 | K18: Done
A19: =row()-2 -> 17 | B19: Level 1-5 | D19: Config full data 60 unit phase 1 | E19: KT | K19: Done
A20: =row()-2 -> 18 | B20: Level 1-5 | D20: Config full data 20 unit phase 1 | E20: KT | J20: 45478 | K20: Doing
A21: =row()-2 -> 19 | B21: Level 1-5 | D21: Config full data 20 unit phase 2 | E21: KT | K21: Delayed
A22: =row()-2 -> 20 | B22: Level 1-5 | D22: Test full bài học 80 unit phase 1 | E22: Team ND | K22: Doing
A23: =row()-2 -> 21 | B23: Level 1-5 | D23: Test full bài học 20 unit phase 2 | E23: Team ND | K23: Delayed
A24: =row()-2 -> 22 | B24: Level 1-5 | D24: Config 25 video interactive phase 1 | E24: Thiên Anh | K24: Done
A25: =row()-2 -> 23 | B25: Level 1-5 | D25: Config 3 video interactive phase 2 | E25: Thiên Anh | K25: NYS
A26: =row()-2 -> 24 | B26: Level 1-5 | D26: Test 26 video interactive phase 1 | E26: Thiên Anh | K26: Done
A27: =row()-2 -> 25 | B27: Level 1-5 | C27: Data | D27: Bổ sung video U61-70 | E27: Media | J27: 45467 | K27: Done
A28: =row()-2 -> 26 | B28: Level 1-5 | D28: Bổ sung video U81-90 | E28: Media | J28: 45495 | K28: NYS
A29: =row()-2 -> 27 | B29: Level 1-5 | D29: Bổ sung video U71-80 | E29: Media | K29: NYS
A30: =row()-2 -> 28 | B30: Level 1-5 | D30: Bổ sung video U91-100 | E30: Media | K30: NYS
A31: =row()-2 -> 29 | B31: Level 1-5 | D31: Duyệt video U61-70 | E31: Thiên Anh | J31: 45467 | K31: Done
A32: =row()-2 -> 30 | B32: Level 1-5 | D32: Duyệt video U81-90 | E32: Thiên Anh | J32: 45495 | K32: NYS
A33: =row()-2 -> 31 | B33: Level 1-5 | D33: Duyệt video U71-80 | E33: Thiên Anh | K33: NYS
A34: =row()-2 -> 32 | B34: Level 1-5 | D34: Duyệt video U91-100 | E34: Thiên Anh | K34: NYS
A35: =row()-2 -> 33 | B35: Level 1-5 | D35: Gắn link audio blending sounds | E35: Thiên Anh | K35: Done
A36: =row()-2 -> 34 | B36: Level 1-5 | D36: Gắn link audio letter name | E36: Thiên Anh | K36: Done
A37: =row()-2 -> 35 | B37: Level 1-5 | D37: Thu âm + gắn link audio speaking competition | E37: Thiên Anh | K37: Done
A38: =row()-2 -> 36 | B38: Level 1-5 | C38: Data | D38: Thiết kế ảnh game Điền thế sentence | E38: CTV | K38: Done
A39: =row()-2 -> 37 | B39: Level 1-5 | D39: Thiết kế ảnh game Jumbled pages | E39: CTV | K39: Done
A40: =row()-2 -> 38 | B40: Level 1-5 | C40: Data | D40: Bổ sung CHTT act Jumbled pages | E40: Nguyệt | K40: Done
A41: =row()-2 -> 39 | B41: Level 1-5 | D41: Bổ sung audio Jumbled pages U61-70 | E41: Thiên Anh | J41: 45462 | K41: Done
A42: =row()-2 -> 40 | B42: Level 1-5 | D42: Bổ sung audio Jumbled pages U81-90 | E42: Thiên Anh | J42: 45468 | K42: Done
A43: =row()-2 -> 41 | B43: Level 1-5 | D43: Bổ sung audio Jumbled pages U71-80 | E43: Thiên Anh | K43: Done
A44: =row()-2 -> 42 | B44: Level 1-5 | D44: Bổ sung audio Jumbled pages U91-100 | E44: Thiên Anh | K44: Done
A45: =row()-2 -> 43 | B45: Level 1-5 | D45: Bổ sung filter words U60-70 | E45: Thiên Anh | J45: 45462 | K45: Done
A46: =row()-2 -> 44 | B46: Level 1-5 | D46: Bổ sung filter words U81-90 | E46: Thiên Anh | J46: 45468 | K46: Done
A47: =row()-2 -> 45 | B47: Level 1-5 | D47: Bổ sung filter words U71-80 | E47: Thiên Anh | K47: Done
A48: =row()-2 -> 46 | B48: Level 1-5 | D48: Bổ sung filter words U91-100 | E48: Thiên Anh | K48: Done
A49: =row()-2 -> 47 | B49: Level 1-5 | C49: Data | D49: Bổ sung audio Chunking U61-70 | E49: Thiên Anh | J49: 45462 | K49: Done
A50: =row()-2 -> 48 | B50: Level 1-5 | D50: Bổ sung audio Chunking U81-90 | E50: Thiên Anh | J50: 45468 | K50: Done
A51: =row()-2 -> 49 | B51: Level 1-5 | D51: Bổ sung audio Chunking U71-80 | E51: Thiên Anh | K51: Done
A52: =row()-2 -> 50 | B52: Level 1-5 | D52: Bổ sung audio Chunking U91-100 | E52: Thiên Anh | K52: Done
A53: =row()-2 -> 51 | B53: Level 1-5 | D53: Bổ sung CHTT act MTC Story 1 U61-70 | E53: Thiên Anh | J53: 45462 | K53: Done
A54: =row()-2 -> 52 | B54: Level 1-5 | D54: Bổ sung CHTT act MTC Story 1 U81-90 | E54: Thiên Anh | J54: 45468 | K54: Done
A55: =row()-2 -> 53 | B55: Level 1-5 | D55: Bổ sung CHTT act MTC Story 1 U71-80 | E55: Thiên Anh | K55: Done
A56: =row()-2 -> 54 | B56: Level 1-5 | D56: Bổ sung CHTT act MTC Story 1 U91-100 | E56: Thiên Anh | K56: Done
A57: =row()-2 -> 55 | B57: Level 1-5 | D57: Sửa lại luồng học sau test | E57: Thiên Anh | K57: Done
A58: =row()-2 -> 56 | B58: Level 1-5 | D58: Tìm/thiết kế background game theo topic | E58: Thiên Anh | K58: Delayed
A59: =row()-2 -> 57 | B59: Level 1-5 | C59: Flow bài học | D59: Bài review 4-5 unit? | E59: Thiên Anh | K59: Delayed
A60: =row()-2 -> 58 | B60: Level 1-5 | C60: Flow bài học | D60: Thiết kế luồng bài học cho độ tuổi 6-8 | E60: Thiên Anh | K60: Delayed
A61: =row()-2 -> 59 | B61: Level 1-5 | D61: Ra list game mới bổ sung | E61: Thiên Anh | K61: Delayed
A62: Product
A63: 1 | B63: Level 1-5 | D63: Trải nghiệm nội bộ | E63: Product | J63: 45471 | K63: Done
A64: 2 | B64: All levels | D64: Vẽ UI/UX, vỏ app | E64: Media | K64: Done
A65: 3 | B65: All levels | D65: Chốt report sau unit + tổng khóa học (UI, logic) | E65: Product | K65: Done
A66: 4 | B66: All levels | D66: Chốt reward (Xu + sticker) | E66: Product | K66: Done
A67: 5 | B67: All levels | D67: F2P - Điều kiện mở khóa học cho user (free/ trial/ paid) | E67: Product | K67: NYS
A68: 6 | B68: All levels | D68: Điều kiện trong parent setting | E68: Product | K68: NYS
A69: 7 | B69: All levels | D69: Điều kiện suggest các khóa học vệ tinh | E69: Product | K69: NYS
A70: 8 | B70: All levels | D70: Đồng bộ | E70: Product | K70: NYS
A71: 9 | B71: All levels | D71: Offline | E71: Product | K71: NYS
A72: 10 | B72: All levels | D72: Event | E72: Product | K72: NYS
A73: 11 | B73: All levels | D73: Localize | E73: Product | K73: NYS
A74: 12 | B74: All levels | D74: Payment | E74: Product | K74: NYS
A75: Sản phẩm vận hành
A76: 1 | B76: All levels | D76: Product profile | E76: Thiên Anh + Duyên | G76: 40 | J76: 45469 | K76: Done | L76: chờ chị Hạnh duyệt
A77: 2 | B77: All levels | D77: Ebook TA + TV | E77: Thiên Anh + Duyên | G77: 40 | I77: 45474 | J77: 45476 | K77: Done | L77: chờ chị Hạnh duyệt

Sheet MC - Khung CT + checkpoints
A1: Mục tiêu | C1: 1 week challenge
A2: 1. Mục tiêu: - Cung cấp thêm giá trị > tăng tỉ lệ mua 01 - Kết nối với bố mẹ - Cross sale - Upsale 2. Cách triển khai: - Đưa giáo trình học + checkpoints - Học theo lộ trình + GV chấm điểm, comment - Testing nếu có (có thể làm in app) 3. Nền tảng: - Monkey Class 4. PH nhận được gì: - Thời khóa biểu - Hiểu về chương trình học - Report tuần - Report kì | C2: Nội dung | F2: Cách làm | I2: Các dạng challenge
C3: Học 3-4 bài | F3: Quay video cô giáo giới thiệu challenge (giao vào đầu tuần) | I3: - Học 3-4 bài/học 10 phút
C4: Học 1 bài cross course (chỉ mở cho các bạn tham gia MC + theo tuần) | F4: Push challenge board vào launch app, hoàn thành bài học (MJ5 hoặc cross course) | I4: - Học lesson M-ABC/MSP/MS
C5: 1 challenge activity | F5: Bài extra trên mj app/quay phim nộp lên MC | I5: - Đọc truyện MS + hoàn thành CHTT
I6: - Thu âm truyện MS
I7: - Quay video con học/chơi (hát theo video/thu âm/video call)
I8: - Quay video ba mẹ hỏi - con trả lời theo chủ đề
I9: - Quay video ba mẹ show từ - con nói/mô tả lại từ đó
I10: - Quay video con mô tả 1 bức tranh,...
I11: - Quay video con thuyết trình về 1 chủ đề
I12: - Giao worksheet -> bố mẹ in ra cho con làm, chụp lại nộp
I13: - Lồng tiếng truyện
I14: - Giao 1 bài & quay phim lại con đọc
C15: Lv 0: học 1 unit trong 1 tuần => 41 tuần xong | I15: - Làm poster/mind map/mô hình/project, chụp lại (có thể thêm mô tả)
C16: Lv 1-5: học 1 unit trong 2 tuần -> 40 tuần sẽ xong 1 level | I16: - Giao 1 chủ đề, con viết về chủ đề đó
C18: TKB chi tiết | D18: Tuần 1 | E18: Tuần 2 | F18: Tuần 3 | G18: Tuần 4 | H18: Tuần 5 | I18: Tuần 6 | J18: Tuần 7 | K18: Tuần 8 | L18: Tuần 9 | M18: Tuần 10 | N18: Tuần 11 | O18: Tuần 12 | P18: Tuần 13 | Q18: Tuần 14 | R18: Tuần 15 | S18: Tuần 16 | T18: Tuần 17 | U18: Tuần 18 | V18: Tuần 19 | W18: Tuần 20 | X18: Tuần 21 | Y18: Tuần 22 | Z18: Tuần 23 | AA18: Tuần 24 | AB18: Tuần 25 | AC18: Tuần 26 | AD18: Tuần 27 | AE18: Tuần 28 | AF18: Tuần 29 | AG18: Tuần 30 | AH18: Tuần 31 | AI18: Tuần 32 | AJ18: Tuần 33 | AK18: Tuần 34 | AL18: Tuần 35 | AM18: Tuần 36 | AN18: Tuần 37 | AO18: Tuần 38 | AP18: Tuần 39 | AQ18: Tuần 40
C19: Level 0 | D19: - Hoàn thiện 5 bài học (Unit 1) - Quay video con học/chơi/ hát theo video | E19: - Hoàn thiện 5 bài học (Unit 2) - Quay video ba mẹ hỏi - con trả lời theo chủ đề | F19: - Hoàn thiện 5 bài học (Unit 3) - Chụp ảnh/ quay con tô màu worksheet | G19: - Hoàn thiện 5 bài học (Unit 4) - | H19: - Hoàn thiện 5 bài học (Unit 5) - Quay video con học/chơi/ hát theo video | I19: - Hoàn thiện 5 bài học (Unit 6) - Quay video ba mẹ hỏi - con trả lời theo chủ đề | J19: - Hoàn thiện 5 bài học (Unit 7) - Chụp ảnh/ quay con tô màu worksheet | K19: - Hoàn thiện 5 bài học (Unit 8) -
C20: Level 1 | D20: - Hoàn thiện 3 bài học - Học 1 lesson M-ABC - Quay lại video con hát theo bài hát trong Lesson 3 | E20: - Hoàn thiện 4 bài học - Đọc đúng hết các từ trong act thu âm | F20: - Hoàn thiện 3 bài học - Học 1 lesson M-ABC - Quay lại video con giới thiệu bản thân | G20: - Hoàn thiện 4 bài học - Quay video con thu âm hội thoại cuối Lesson 14 | H20: - Hoàn thiện 3 bài học - Đọc 1 truyện MS và hoàn thành hết CHTT | I20: - Hoàn thiện 4 bài học - Quay video ba mẹ show từ - con nói/mô tả lại từ đó | J20: - Hoàn thiện 3 bài học - Đọc 1 truyện MS hoàn thành hết CHTT | K20: - Hoàn thiện 4 bài học - Quay video con thu âm hội thoại cuối Lesson 28
C21: Level 2 | D21: - Hoàn thiện 3 bài học - Đọc 1 truyện MS và hoàn thành hết CHTT | E21: - Hoàn thiện 4 bài học - Quay video con thu âm hội thoại cuối Lesson 7 | F21: - Hoàn thiện 3 bài học - Đọc 1 truyện MS - Quay video con thu âm 1 truyện MS | G21: - Hoàn thiện 4 bài học - Chụp ảnh con vẽ hình 1 chiếc áo đc dạy trong bài | H21: - Hoàn thiện 3 bài học - Quay lại video con đọc chữ cái "y" và viết chữ y ra giấy | I21: - Hoàn thiện 4 bài học - Quay video ba mẹ hỏi - con trả lời theo chủ đề | J21: - Hoàn thiện 3 bài học - Học 2 lesson MSP | K21: - Hoàn thiện 4 bài học - Quay video con chơi Lesson 28
C22: Level 3 | D22: - Hoàn thiện 3 bài học - Quay video con đánh vần các từ ở lesson 2 | E22: - Hoàn thiện 4 bài học - Quay video ba mẹ hỏi - con trả lời theo chủ đề | F22: - Hoàn thiện 3 bài học - Học 2 bài MSP | G22: - Hoàn thành 4 bài học - Quay video con chơi 1 video call MSP | H22: - Hoàn thiện 3 bài học - Đọc 1 truyện MS - Lồng tiếng 1 truyện MS | I22: - Hoàn thiện 4 bài học - Quay video con chơi Lesson 21 | J22: - Hoàn thiện 3 bài học - Quay video con viết chữ ff | K22: - Hoàn thiện 4 bài học - Quay video ba mẹ hỏi, con trả lời theo đoạn hội thoại trong bài
C23: Level 4 | D23: - Hoàn thiện 3 bài học - Ba mẹ hỏi con tìm các từ có âm fl -> quay video con nói | E23: - Hoàn thiện 4 bài học - Quay video con nói về chủ đề Camping | F23: - Hoàn thiện 3 bài học - Quay lại video con phát âm /sl/ và viết chữ "sl" ra giấy | G23: - Hoàn thiện 4 bài học - Quay video con thu âm hội thoại cuối Lesson 14 | H23: - Hoàn thiện 3 bài học - Học 2 bài MSP | I23: - Hoàn thiện 4 bài học - Quay video con nói về chủ đề Painting | J23: - Hoàn thiện 3 bài học - Đọc 1 truyện MS - Lồng tiếng 1 truyện MS | K23: - Hoàn thành 4 bài học - Quay video con chơi 1 video call MSP
C24: Level 5 | D24: - Hoàn thiện 3 bài học - Đọc 1 truyện MS và hoàn thành hết CHTT | E24: - Hoàn thiện 4 bài học - Quay video con mô tả 1 bức tranh | F24: - Hoàn thiện 3 bài học - Quay lại video con hát theo video ở cuối lesson 10 | G24: - Hoàn thiện 4 bài học - Quay video con chơi Lesson 14 | H24: - Hoàn thiện 3 bài học - Quay video con thuyết trình về môn thể thao con thích | I24: - Hoàn thiện 3 bài học - Đọc 1 truyện MS - Lồng tiếng 1 truyện MS | J24: - Hoàn thiện 3 bài học - Đọc 1 truyện MS - Quay video con lồng tiếng 1 truyện MS | K24: - Hoàn thành 4 bài học - Quay video con chơi 1 video call MSP

Sheet MJ 5.0_Level 0_ Tổng quan
A1: Tên sản phẩm | B1: MJ 5.0_Level 0
A2: Định nghĩa | B2: Khóa học dạy tiếng Anh với định hướng tập trung từ vựng, áp dụng các phương pháp Giáo dục sớm
A3: Đối tượng sử dụng | B3: Trẻ 0-3 tuổi
A4: Phương pháp | B4: 1. Chụp hình nguyên từ 2. Tráo thẻ nhanh - Glenn Doman 3. Học thông qua trò chơi
A5: Hệ thống nội dung | B5: Nội dung học: tập trung học từ vựng với 2 loại từ: - Từ vựng chủ đề - Từ sight word
A6: Cấp độ bài học | B6: 3 cấp độ: Cơ bản - Trung bình - Nâng cao
A7: Luồng bài học | B7: Luồng bài học
A8: Games | B8: List game
A9: Input - Output | B9: - Input: chưa biết gì về tiếng Anh, độ tuổi 0-3 - Output: Nhận biết các từ vựng ở các topic rất phổ biến (Animals, Shapes, Actions, Fruits, Food, Toys), là tiền đề để học khóa học M.Go

Sheet MJ 5.0_Level 1-5_Tổng quan
A1: Tên sản phẩm | B1: Monkey Go
A2: Tổng quan | B2: - Khóa học giúp trẻ phát triển 4 kỹ năng: Nghe - Nói - Đọc - Viết - Dành cho trẻ độ tuổi 3-8 (ideally là chưa biết nhiều về tiếng Anh/ ít tiếp xúc với tiếng Anh)
A3: 2. Nhu cầu của bố mẹ | B3: Mục đích khi ba mẹ cho con học apps: - Học từ vựng - Học phát âm - Học giao tiếp - Thi chứng chỉ Hướng nội dung + tính năng ba mẹ mong muốn trên app: - Kết hợp games + interactive learnings - Personalized learning (child's progress and performance) - Multimedia and Visual Learning - Speech Recognition and Pronunciation Improvement - Parental Involvement and Progress Tracking - AI-Powered Learning Assistants (chatbots and virtual assistants) - Customizable Learning Paths
A4: 3. Lỗ hổng của app MJ hiện tại | B4: - MABC: tập trung dạy từ vựng cho trẻ 0-6, focus chính vào độ tuổi 0-3, hình ảnh + phương pháp chủ yếu cho 0-3 nhiều hơn - Khóa Monkey Stories: tập trung dạy đọc hiểu thông qua truyện cho độ tuổi 3-11, phát triển từ app MS cũ, nhưng đã bỏ đi phần bài học phonics (gồm 243 bài cho tổng 3 level) - Khóa Monkey Speak: tập trung phát triển kỹ năng nói cho độ tuổi 3-11 - Chưa có khóa dạy 4 kỹ năng + bổ sung phần phonics bị bỏ đi khi chuyển từ app MS lên khóa MS - Chưa có khóa học dùng các nội dung xuất hiện trên Media để dạy
A5: Tâm lý học của trẻ 3-8 Reference | B5: - Thích dùng các phương tiện Media - Bị hấp dẫn bởi các nội dung như video, games - Thích học thông qua các học liệu đa dạng, có kèm theo các nội dung giải trí: truyện, video, songs - Học được từ vựng qua các ngữ cảnh thực tế Các act nên sử dụng: - <4t: phonics, tracing, coloring, videos, songs - 4-6t: videos, songs, stories, repeat - 7-8t: videos, songs, stories, word search,... | C5: Trẻ mẫu giáo bé (3-4 tuổi) - Tư duy trực quan hành động: trẻ tiếp xúc và khám phá thế giới chủ yếu qua các giác quan. Trẻ sẽ sử dụng tư duy trực quan để liên kết những thông tin con thu thập và cố gắng để hiểu thế giới xung quanh - Bắt chước và thử nghiệm: khả năng bắt chước hành vi từ người lớn. Dù có thể chưa đạt đến mức sáng tạo cao, trẻ vẫn thể hiện sự tò mò và ham học hỏi, thích thử nghiệm và tìm hiểu. - Phân loại thông tin: Trẻ bắt đầu có khả năng phân loại các đồ vật theo những đặc điểm cơ bản như màu sắc, kích thước và hình dạng, nhưng chỉ ở mức độ cơ bản. Trẻ mẫu giáo nhỏ (4-5 tuổi) - Tư duy trực quan hình ảnh phát triển mạnh: trẻ có khả năng tưởng tượng ra các sự vật, hiện tượng mà trước đây con chưa từng thấy hoặc trải qua. Trẻ có thể tạo ra những câu chuyện riêng biệt, tưởng tượng ra các trò chơi, và thậm chí là tạo ra những bức tranh phong phú từ trí tưởng tượng của mình. - Tư duy từ ngữ - logic bắt đầu xuất hiện: trẻ có thể sử dụng từ ngữ để diễn đạt suy nghĩ, cảm xúc và giải quyết các vấn đề một cách lôgic hơn. Trẻ cũng bắt đầu đặt ra các câu hỏi tò mò, phân tích nguyên nhân và kết quả - Khả năng giải quyết vấn đề phức tạp hơn: con có thể tham gia vào các trò chơi xếp hình, lắp ráp và thử thách tư duy khác mà trước đây không thể thực hiện được một cách chính xác. Trẻ mẫu giáo lớn (5-6 tuổi), bước ngoặt quan trọng trong sự mở rộng tư duy logic và từ ngữ của trẻ - Tư duy từ ngữ - lôgic phát triển mạnh: trẻ bắt đầu sử dụng từ ngữ như một công cụ mạnh mẽ để diễn đạt suy nghĩ và trải nghiệm của mình. Trong đó, con không chỉ diễn đạt được ý nghĩa bề nổi, mà còn có khả năng phân tích và đánh giá thông tin một cách lôgic hơn. - Khả năng phân loại và tổ chức thông tin: Trẻ ở giai đoạn này có khả năng phân loại, so sánh và tổ chức thông tin một cách chi tiết và có hệ thống. Trẻ có thể nhận diện mối liên hệ giữa các sự vật và hiện tượng, giúp con hiểu rõ hơn về thế giới xung quanh. - Khả năng tư duy trừu tượng và sáng tạo: Trẻ bắt đầu phát triển khả năng tư duy trừu tượng, điều này giúp con hiểu được ý nghĩa sâu xa từ các khái niệm như tình yêu, tình bạn hay công bằng. Hơn nữa, sự sáng tạo của trẻ cũng được nâng cao, và con thể hiện điều này qua các hoạt động nghệ thuật như vẽ, viết hay sáng tác. - Tư duy độc lập và phê phán: Trẻ mẫu giáo lớn có xu hướng hình thành quan điểm và ý kiến riêng, thể hiện sự độc lập trong tư duy. Lúc này, con cũng bắt đầu biểu lộ khả năng phê phán, đặt ra câu hỏi và thách thức những thông tin được truyền đạt. | D5: Average Attention Span 3 years old: 6-8 minutes 4 years old: 8-12 minutes 5-6 years old: 12-18 minutes 7–8 years old: 16-24 minutes | E5: 6 weeks vowels sounds 6 months consonants 1,5 years single words + meaning 2 years single words together + simple sentences 5 years rhyme words 5-6 years blending 6 years story 8 years write simple story
A6: Lý do cần khóa Monkey Go | B6: - Đáp ứng nhu cầu làm quen với tiếng Anh giao tiếp và học 4 kỹ năng ở trẻ nhỏ - Bổ sung vào hệ sinh thái sản phẩm của siêu app: + 0-3: M.ABC + 3-8: M.Go - Bổ sung phần Phonics bị thiếu khi KH chuyển từ app MS sang khóa MS trong siêu app, cũng bổ trợ cho phương pháp học phonics đang được áp dụng gần đây trong bộ sgk tiểu học) - Bổ sung phương pháp học mới cho siêu app: học thông qua media-based, material-based learning - Là cầu nối để hook bán các khóa offline: K5 (chương trình bổ trợ kiến thức trên lớp), Monkey Tutoring (5-10 tuổi, học giao tiếp)
A7: Hệ thống nội dung | B7: - Gồm 5 level (mỗi level 20 unit) với độ khó tăng dần. Flow bài học cố định, tuy nhiên có thể tự do chọn level - Dạy phonics, vocab, sentence, dialog, story Bảng data tổng
A8: Các phương pháp sẽ được ứng dụng trong Monkey Go | B8: Phương pháp
A9: Cách dạy các kỹ năng Nghe - Nói - Đọc - Viết
A10: 9. Selling points của khóa học | B10: - Hệ thống học liệu đa dạng, hiện đại: từ vựng (phonics, từ topics), câu, sight words, truyện tranh, video, games - Game hiện đại, có cốt truyện - Kho truyện được viết riêng, minh họa hiện đại, nội dung hấp dẫn - Nội dung đi theo phương pháp phonics được công nhận trên thế giới (Jolly Phonics + Wushka phonics) - Áp dụng Shadowing techniques + công nghệ M-Speak để phát triển khả năng phát âm và kỹ năng nói - Áp dụng Hand-writing technology để phát triển kỹ năng viết - Thời lượng mỗi bài học ngắn, phù hợp với khả năng tập trung của bé ở lứa tuổi 3-8 - Monkey Go bổ sung phần Phonics bị thiếu khi chuyển từ app MS sang khóa MS, bổ trợ cho phương pháp học phonics đang được áp dụng ở sgk tiểu học, đồng thời có thêm những hoạt động giúp các bé luyện viết
A11: Input & output của khóa học | B11: Input - Trẻ 3-8 tuổi, ideally là chưa biết nhiều về tiếng Anh/ ít tiếp xúc với tiếng Anh - Bé trong độ tuổi 3-8 - Thích chơi xem media - Thích đọc truyện tranh - Biết một số ít từ vựng tiếng Anh, chưa thành thạo sử dụng các mẫu câu - Phát âm tiếng Anh chưa chuẩn - Khả năng viết còn chưa tốt - Nhu cầu bổ trợ cả 4 kỹ năng/giao tiếp được bằng tiếng Anh Outcome
A12: 11. Road map | B12: Roadmap dự kiến Dự kiến launch vào tuần cuối Tháng 4/2024
A13: Flow games trong lesson | B13: Flow tổng Flow minimal
A14: Tổng hợp games | B14: List game chốt
A15: 14. Điều kiện suggest khóa học | B15: Điều kiện suggest
A16: 15. Report khóa học | B16: - Report sau mỗi unit + Show những từ, âm, mẫu câu & truyện con học trong unit + Show điểm (sao) phát âm của hội thoại - Report tổng + Số từ + Số mẫu câu + Số truyện Reference Figma | D16: Link 1 Link 2
A17: 16. Reward | B17: - Sau mỗi lesson +15 xu. Học lại không cộng xu. - Sau mỗi unit +1 sticker
A18: 17. UI | B18: gồm 3-5 level với độ khó tăng dần flow bài học cố định, tuy nhiên có thể tự do chọn level
A19: 18. Review | B19: Sẽ có bài review sau 4 units (hoặc 5) Ôn lại các từ dễ (con đã nhớ) trước, rồi dần dần tới các từ con chưa nhớ
A20: 19. Timeline | B20: Timeline tổng
A21: Đề bài cho luồng mới | B21: - 2 luồng chính, 3-6t và 6-8t - Dùng luồng mới (content-based) nhưng dùng lại các ND đã có sẵn, sau đó sẽ update & thay dần các act - Transition giữa khóa M-ABC và MGo ở độ tuổi 3.5 và có thể tham khảo thêm luồng 3-6t của M-ABC - List game gồm minimum 15 games

Sheet MG - Phương pháp luận
A1: STT | B1: Phương pháp | C1: Mô tả | D1: Ứng dụng trong M.Go
A2: 1 | B2: Multimedia-based learning | C2: Phương pháp sử dụng nhiều học liệu khác nhau để dạy kiến thức. | D2: - Sử dụng hình ảnh, video, truyện, hội thoại để dạy từ vựng, cấu trúc, kỹ năng cho trẻ
A3: 2 | B3: Phonics Method | C3: Phương pháp dạy học sinh mối liên hệ giữa chữ cái (mặt chữ) và âm (sound) để giúp trẻ đọc và viết tốt hơn | D3: - Dạy trẻ mối liên hệ giữa chữ cái (letters), và âm (sound), cách ghép các âm để tạo thành từ hoàn chỉnh. - Các unit của M.Go sẽ dạy các từ phonics từ cơ bản đến nâng cao: âm đơn lẻ - âm ghép - cách ghép vần để đọc được các từ trong tiếng Anh - Phương pháp phonics giúp con phát âm chuẩn hơn, dễ dàng nhận diện để đọc chữ cái
A4: 3 | B4: Communicative Language Teaching | C4: Phương pháp tập trung rèn luyện năng lực giao tiếp cho trẻ thông qua sự tương tác của trẻ với các nội dung hướng tới mục đích giao tiếp. | D4: - Cung cấp các hội thoại định hướng giao tiếp, được cấu thành từ các từ vựng, mẫu câu đã được giới thiệu trước đó để giúp trẻ luyện tập giao tiếp trong các tình huống cụ thể, gần với đời thật
A5: 6 | B5: Story-based learning | C5: Story-based learning (Học thông qua truyện tranh tương tác): Các từ vựng và mẫu câu được đưa vào truyện một cách tự nhiên kèm theo cốt truyện hấp dẫn, khiến trẻ dễ dàng ghi nhớ kiến thức.Truyện giúp trẻ rèn luyện khả năng nắm bắt nghĩa của từ thông qua ngữ cảnh. Ngay cả khi trẻ không biết định nghĩa chính xác của một từ, trẻ vẫn có thể suy ra nghĩa của nó từ ngữ cảnh của truyện. | D5: - M.Go có xây dựng và thiết kế riêng bộ truyện theo các unit, nhằm giúp trẻ học từ vựng, câu ngữ cảnh thông qua việc đọc truyện.
B8: Kỹ năng | C8: Cách áp dụng trong games/ bài
B9: Kỹ năng nghe | C9: - Nghe các audio chuẩn bản ngữ trong các audio từ vựng, hội thoại, truyện, video - Tương tác với các game nghe audio và chọn đáp án
B10: Kỹ năng đọc | C10: - Đọc từ vựng, câu - Đọc hội thoại, đọc truyện - Chơi game - Trả lời các câu hỏi tương tác về nội dung truyện
B11: Kỹ năng nói | C11: - Nói từ, câu trong các game Speaking - Luyện nói hội thoại - Luyện tập kể lại truyện
B12: Kỹ năng viết | C12: - Độ tuổi nhỏ: + viết chữ cái, viết từ + ghép cụm từ, ghép câu đơn giản - Độ tuổi lớn + Ghép 2 vế câu + Ghép câu nhỏ vào đoạn văn lớn

Sheet MJ 5.0 - Outcome
A1: Cấp độ | B1: Từ vựng/Ngữ pháp | C1: 4 kỹ năng Nghe - Nói - Đọc - Viết | D1: Giao tiếp | E1: Ngữ âm - Phonics | F1: Story
A2: Level 0 | B2: - Tập trung ngôn ngữ đầu vào, giúp trẻ nhận biết các từ vựng ở các topic phổ biến (Động vật, Hoa quả, Đồ ăn, Đồ chơi,...), là tiền đề để học các cấp độ sau | C2: - Nghe hiểu và nhận diện được hình ảnh/ text của các từ vựng thuộc chủ đề gần gũi với cuộc sống hàng ngày - Làm quen với từ vựng thông qua các video bài hát, bài vè, truyện | D2: x | E2: x
A3: Level 1 | B3: - Nói được đúng từ vựng ở các topic rất phổ biến (Động vật, Hoa quả, Đồ ăn, Đồ chơi,...) | C3: - Được tiếp xúc với nhiều loại hình học liệu mới và yêu thích việc học tiếng Anh - Tăng cường nghe, đọc truyện và hội thoại - Tập nói từ, câu đơn giản; giới thiệu được bản thân, nói về những sự vật quanh mình - Làm quen và viết các chữ cái trong bảng chữ cái tiếng Anh | D3: - Chào hỏi, trao đổi được thông tin cá nhân cơ bản - Hiểu và trả lời được các câu hỏi về các vật phổ biến - Trả lời câu hỏi bằng các từ hoặc cụm từ ngắn | E3: - Bắt đầu học các âm đơn - Ghép từ có 1 âm tiết, học cách ghép âm lẻ | F3: - Nghe app đọc truyện đơn giản (tương đương level A-C ở MS) - Làm được CHTT bằng hình ảnh + audio
A4: Level 2 | B4: - Nói được các cụm từ và cấu trúc câu đơn giản | C4: - Đa dạng các loại học liệu để trẻ nghe - Đọc các truyện đơn giản, bắt đầu có cốt truyện để trẻ phát triển tính logic - Tiếp xúc và tập viết các nguyên âm đôi, đánh vần từ vựng dạng C-V-C (Consonant - Vowel - Consonant words) - Quen thuộc với việc giao tiếp bằng tiếng Anh, dễ dàng bật ra câu trả lời khi được hỏi
A5: Level 3 | B5: - Nói + sử dụng được phần lớn từ vựng xuất hiện trong các tình huống hàng ngày (A1-A2). - Nói được câu đơn ở các thì đơn giản: Hiện tại đơn, Hiện tại tiếp diễn, tương lai đơn | C5: - Các video sử dụng nhiều tình tiết đa dạng trong cuộc sống - Đọc truyện và hình thành khả năng phân tích truyện - Được học về phụ âm đôi, đánh vần các từ phức tạp hơn, dạng C-V-C, C-C-V-C - Giao tiếp về mọi người, sự vật, sự việc xung quanh, dễ dàng mô tả về ngoại hình, vị trí, hành động của họ | D5: - Giao tiếp cơ bản: nghe hiểu các câu hỏi WH-questions đơn giản => trả lời được bằng câu hoàn chỉnh - Giới thiệu được bản thân bằng một đoạn 3-4 câu liên tiếp | E5: - Ôn lại âm đơn lẻ + học cách ghép âm đôi - Đánh vần được những từ 1-2 âm tiết, có thể có âm đôi | F5: - Nghe app đọc truyện có scripts là câu + cốt truyện hấp dẫn - Làm được CHTT bằng cả text và audio/ hình ảnh
A6: Level 4 | B6: - Nói được cụm từ/câu đơn + câu phủ định, cảm thán, câu hỏi + một số câu phức có liên từ đơn giản (and, but) | C6: - Nghe và đọc truyện, hội thoại với số lượng từ vựng nhiều và phức tạp hơn, ở nhiều chiều thời gian - Đa dạng các nguyên âm và phụ âm đôi, ở thời điểm này trẻ có thể vận dụng kĩ năng đánh vần để đọc được truyện thiếu nhi tiếng Anh - Trẻ có thể mô tả sự việc đã xảy ra trong quá khứ, trong tương lai gần khi giao tiếp
A7: Level 5 | B7: - Sử dụng thành thạo các từ vựng hàng ngày + các từ vựng khó hơn (A2-B1) - Nói được đa dạng loại câu đơn + phức. Có thể dễ dàng chia sẻ thông tin + cảm nghĩ, cảm xúc bản thân. - Sử dụng được các thì: Quá Khứ đơn, Hiện tại hoàn thành | C7: - Thời điểm này trẻ gần như hoàn thiện về khả năng giao tiếp so với nhu cầu thường ngày của trẻ - Được giới thiệu tổng 100 âm phonics, trẻ dễ dàng đánh vần một từ chưa gặp và có khả năng đọc tốt - Trẻ dễ dàng phân tích các truyện hình ngắn về từ vựng, tình tiết truyện, trả lời các câu hỏi đọc hiểu sau truyện - Viết: tô các chữ cái, luyện tập ghép câu, điền từ vào câu | D7: - Giao tiếp thực tế: nghe hiểu tốt các câu hỏi, câu tường thuật, câu cảm thán - Đưa ra được ý kiến cá nhân | E7: - Học tiếp các blended sounds (2-3 letters) - Đánh vần được các từ khó hơn, có thể bao gồm blended sound đến 3 chữ cái | F7: - Đọc được truyện có đến 4-5 câu mỗi trang + informational texts - Làm được CHTT bằng các loại data, mạnh về comprehension + details

Sheet MJ 5.0 - Landing page
A1: Level | B1: Độ tuổi | C1: Tagline | D1: Phương pháp | E1: Số bài học/ hoạt động | F1: Giới thiệu (biểu thị bằng chart ở từng level) | G1: Phân loại theo cấp độ | H1: Outcome | I1: Highlight
A2: 0 | B2: 0-3 | C2: Khóa học với định hướng tập trung từ vựng, áp dụng các phương pháp Giáo dục sớm | D2: 1. Phương pháp chụp hình nguyên từ - Học từ vựng thông qua ghi nhớ mặt chữ viết, hình ảnh và audio giọng đọc. - Hiệu quả đối với các bạn nhỏ khi bán cầu não phải đang trong quá trình phát triển mạnh và việc học thông qua hình ảnh, chụp hình được tiến hành một cách rất dễ dàng và tự nhiên. Khi đó, việc giới thiệu một từ vựng gốc, không phân tách từng chữ cái với trẻ sẽ giống với việc giới thiệu một hình ảnh. Trẻ không cần kiến thức về chữ viết cũng có thể nhớ được cách viết của từ vựng đó. 2. Phương pháp đa giác quan - Học từ vựng thông qua việc sử dụng nhiều giác quan cùng lúc - Trẻ được nghe giọng đọc, hiệu ứng âm thanh. Trẻ được nhìn chữ cùng hình ảnh, video mô tả sinh động, chính xác, trực tiếp ấn chạm thông qua các trò chơi tương tác. 3. Phương pháp tráo thẻ nhanh - Glenn Doman - Học từ vựng thông qua thẻ từ với các quy chuẩn nhất định. - Các từ vựng được giới thiệu 1 set từ vựng cùng nhau thông qua các hình hình ảnh rõ ràng, chân phương, không có các yếu tố gây nhiễu. Tốc độ tráo thẻ nhanh, từ 0.7-1s. 4. Phương pháp học thông qua trò chơi - Phương pháp đưa các nội dung tri thức và kỹ năng muốn truyền tải cho con trẻ lồng ghép vào các trò chơi có tính định hướng. - Mỗi bài học có từ 5-7 hoạt động là các hoạt động trò chơi tương tác khác nhau kích thích tư duy & hứng thú học của trẻ xuyên suốt quá trình học tập. | E2: 600+ hoạt động 600+ từ vựng | F2: - 700+ từ vựng phổ biến - 50+ bài hát, bài vè, truyện - Học từ vựng theo phương pháp Giáo dục sớm | G2: - 2 loại từ vựng : + Từ vựng chủ đề + Từ vựng phổ biến | H2: - Nghe hiểu và nhận diện được hình ảnh/ text của các từ vựng thuộc chủ đề gần gũi với cuộc sống hàng ngày | I2: - Thời lượng mỗi bài học ngắn, các hoạt động được thiết kế phù hợp với khả năng học và tương tác của trẻ 0-3 tuổi - Tích lũy kho từ vựng chủ đề và từ vựng phổ biến, là tiền đề để học lên các cấp độ tiếp theo.
A3: 1 | B3: 45359 | C3: Khóa học phát triển 4 kỹ năng Nghe - Nói - Đọc - Viết | D3: 1. Multimedia-based Learning - Học qua đa phương tiện - Phương pháp sử dụng nhiều học liệu khác nhau: hình ảnh, video, truyện, hội thoại,... để dạy kiến thức, kỹ năng cho trẻ. 2. Phonics Method - Phương pháp ngữ âm - Phương pháp dạy mối liên hệ giữa chữ cái (letter) và âm (sound), cách ghép các âm để tạo thành từ hoàn chỉnh, giúp trẻ nhận diện được mặt chữ, phát âm chuẩn hơn, đọc và viết tốt hơn. - Các phonics được lồng ghép theo cấp độ từ cơ bản đến nâng cao: âm đơn lẻ - âm ghép - cách ghép vần để đọc được các từ trong tiếng Anh. 3. Communicative Language Teaching - Dạy ngôn ngữ qua giao tiếp - Phương pháp tập trung rèn luyện năng lực giao tiếp cho trẻ thông qua sự tương tác của trẻ với các nội dung hướng tới mục đích giao tiếp. - Khóa học cung cấp các hội thoại theo định hướng giao tiếp, được cấu thành từ các từ vựng, mẫu câu đã được giới thiệu trước đó để giúp trẻ luyện tập giao tiếp trong các tình huống cụ thể, gần với đời thật. | E3: 640+ hoạt động | F3: - 20 âm đơn - 300+ từ vựng - 60+ video, bài hát, hội thoại, truyện - Làm quen với Cambridge Starters | G3: - 20 chủ đề quen thuộc: Con vật, Hoa quả, Đồ chơi,... * Kỹ năng nghe: - Nghe và hiểu được tên riêng, tên gọi đồ vật, sự vật rất đơn giản, quen thuộc. - Nghe, hiểu và làm theo những yêu cầu đơn giản, tương tác chọn đáp án. * Kỹ năng nói: - Biết nhắc lại, nói tên riêng, tên đồ vật, sự vật rất đơn giản, quen thuộc. - Phát âm tương đối rõ ràng các từ đơn lẻ của chủ đề được học. * Kỹ năng đọc: - Đọc từ vựng, câu đơn giản trong hội thoại, truyện. - Trả lời các câu hỏi rất đơn giản về truyện. * Kỹ năng viết: - Tập tô chữ cái đơn lẻ. * Ngữ âm: - Nhận biết và phát âm được 20 âm đơn lẻ. - Học cách ghép các âm vào từ. | H3: - Được tiếp xúc với nhiều loại hình học liệu mới và yêu thích việc học tiếng Anh - Tăng cường nghe, đọc truyện và hội thoại - Tập nói từ, câu đơn giản; giới thiệu được bản thân, nói về những sự vật quanh mình - Làm quen và viết các chữ cái trong bảng chữ cái tiếng Anh | I3: - Thời lượng mỗi bài học ngắn, phù hợp với khả năng tập trung của trẻ ở lứa tuổi 3-8. - Hệ thống học liệu đa dạng, hiện đại: từ vựng, câu, truyện tranh, video, bài hát, trò chơi tương tác,... với độ khó tăng dần theo từng cấp độ. - Sử dụng phương pháp Jolly Phonics + Wushka phonics được công nhận trên thế giới, giúp trẻ nhận diện được mặt chữ và ghép thành từ hoàn chỉnh. - Áp dụng phương pháp Shadowing và công nghệ M-Speak để phát triển khả năng phát âm và kỹ năng nói. - Kho truyện được thiết kế riêng, minh họa hiện đại, nội dung hấp dẫn, giúp phát triển khả năng đọc hiểu. - Áp dụng công nghệ Hand-writing để phát triển kỹ năng viết. | J3: Thiếu kĩ năng nghe
A4: 2 | E4: 640+ hoạt động | F4: - 20 âm đơn và âm đôi - 300+ từ vựng - 60+ video, bài hát, hội thoại, truyện - Luyện tập theo Cambridge Starters | G4: - 20 chủ đề quen thuộc: Đồ ăn, Quần áo, Nhà cửa,... * Kỹ năng nghe: - Nghe và hiểu được tên gọi đồ vật, sự vật đơn giản, quen thuộc. - Nghe, hiểu và làm theo những yêu cầu đơn giản, tương tác chọn đáp án. * Kỹ năng nói: - Phát âm rõ ràng các từ của chủ đề được học. - Nói được các cụm từ và cấu trúc câu đơn giản. * Kỹ năng đọc: - Đọc từ vựng, câu đơn giản trong hội thoại, truyện. - Trả lời các câu hỏi rất đơn giản về truyện. * Kỹ năng viết: - Bắt đầu tập tô tổ hợp 1 - 2 chữ cái. * Ngữ âm: - Bắt đầu nhận biết và phát âm được âm đôi. - Học cách ghép các âm vào từ. | H4: - Đa dạng các loại học liệu để trẻ nghe - Đọc các truyện đơn giản, bắt đầu có cốt truyện để trẻ phát triển tính logic - Tiếp xúc và tập viết các nguyên âm đôi, đánh vần từ vựng dạng C-V-C (Consonant - Vowel - Consonant words) - Quen thuộc với việc giao tiếp bằng tiếng Anh, dễ dàng bật ra câu trả lời khi được hỏi
A5: 3 | E5: 640+ hoạt động | F5: - 20 âm đôi - 400+ từ vựng - 60+ video, bài hát, hội thoại, truyện - Sẵn sàng thi chứng chỉ Cambridge Starters | G5: - 20 chủ đề quen thuộc: Thời tiết, Địa điểm, Phương tiện,... * Kỹ năng nghe: - Nghe và hiểu được tên gọi đồ vật, sự vật, hành động. - Nghe, hiểu và làm theo những yêu cầu để tương tác trong bài học. * Kỹ năng nói: - Phát âm rõ ràng các từ vựng và mẫu câu của chủ đề được học. - Nói được câu trong hội thoại và truyện. * Kỹ năng đọc: - Đọc hiểu từ vựng, câu đơn giản trong hội thoại, truyện. - Trả lời các câu hỏi về ý nghĩa truyện, sắp xếp tình tiết truyện. * Kỹ năng viết: - Tô các tổ hợp âm đôi. * Ngữ âm: - Nhận biết và phát âm được các âm đôi. - Ghép các âm vào từ. | H5: - Các video sử dụng nhiều tình tiết đa dạng trong cuộc sống - Đọc truyện và hình thành khả năng phân tích truyện - Được học về phụ âm đôi, đánh vần các từ phức tạp hơn, dạng C-V-C, C-C-V-C - Giao tiếp về mọi người, sự vật, sự việc xung quanh, dễ dàng mô tả về ngoại hình, vị trí, hành động của họ
A6: 4 | E6: 700+ hoạt động | F6: - 20 âm đôi - 600+ từ vựng - 60+ video, bài hát, hội thoại, truyện - Làm quen với Cambridge Movers | G6: - 20 chủ đề quen thuộc: Thể thao, Thiên nhiên, Nghề nghiệp,... * Kỹ năng nghe: - Nghe, hiểu, nắm rõ được tên gọi đồ vật, sự vật, hành động. - Nghe, hiểu và làm theo những yêu cầu để tương tác trong bài học. * Kỹ năng nói: - Phát âm rõ ràng các từ vựng và mẫu câu của chủ đề được học. - Nói được câu trong hội thoại và truyện. * Kỹ năng đọc: - Đọc hiểu, đoán được nghĩa từ vựng, câu trong ngữ cảnh. - Trả lời các câu hỏi về ý nghĩa truyện, sắp xếp tình tiết truyện. * Kỹ năng viết: - Tô các tổ hợp âm đôi. * Ngữ âm: - Nhận biết và phát âm được các âm đôi. - Ghép các âm vào từ. | H6: - Nghe và đọc truyện, hội thoại với số lượng từ vựng nhiều và phức tạp hơn, ở nhiều chiều thời gian - Đa dạng các nguyên âm và phụ âm đôi, ở thời điểm này trẻ có thể vận dụng kĩ năng đánh vần để đọc được truyện thiếu nhi tiếng Anh - Trẻ có thể mô tả sự việc đã xảy ra trong quá khứ, trong tương lai gần khi giao tiếp
A7: 5 | E7: 700+ hoạt động | F7: - 20 âm đôi và âm ba - 800+ từ vựng - 60+ video, bài hát, hội thoại, truyện - Luyện tập theo Cambridge Movers | G7: - 20 chủ đề quen thuộc: Sức khỏe, Công cụ, Công nghệ,... * Kỹ năng nghe: - Nghe, hiểu, nắm rõ được tên gọi đồ vật, sự vật, hành động. - Nghe, hiểu và làm theo những yêu cầu để tương tác trong bài học. * Kỹ năng nói: - Phát âm rõ ràng các từ vựng và mẫu câu của chủ đề được học. - Nói được câu trong hội thoại và truyện. * Kỹ năng đọc: - Đọc hiểu, đoán được nghĩa từ vựng, câu trong ngữ cảnh. - Trả lời các câu hỏi về ý nghĩa truyện, sắp xếp tình tiết truyện. * Kỹ năng viết: - Tô các tổ hợp phụ âm được cấu tạo bởi 2 - 3 chữ cái. * Ngữ âm: - Nhận biết và phát âm được các âm đôi và âm gồm 3 chữ cái. - Ghép các âm vào từ. | H7: - Thời điểm này trẻ gần như hoàn thiện về khả năng giao tiếp so với nhu cầu thường ngày của trẻ - Được giới thiệu tổng 100 âm phonics, trẻ dễ dàng đánh vần một từ chưa gặp và có khả năng đọc tốt - Trẻ dễ dàng phân tích các truyện hình ngắn về từ vựng, tình tiết truyện, trả lời các câu hỏi đọc hiểu sau truyện

Sheet MJ 5.0 - Logic tính sao Kĩ năng
A1: Nhóm game | B1: Level | C1: ID Game | D1: Tên game | E1: Kĩ năng | F1: Cách tính điểm
A2: Nhóm 1 | C2: BE.RST02 | D2: Multiple choice story (chọn ảnh) | E2: Listening | F2: 1. Tính kết quả của lần chơi đầu tiên 2. Cách tính điểm của 1 game: 2.1. Game có 2 lượt chơi: - Sai lần đầu chơi cả 2 lượt: 40 điểm - Sai lần đầu chơi 1 lượt: 60 điểm - Đúng lần đầu chơi cả 2 lượt: 100 điểm 2.2. Game có 3 lượt chơi: - Sai lần đầu chơi cả 3 lượt: 40 điểm - Sai lần đầu chơi 2 lượt: 60 điểm - Sai lần đầu chơi 1 lượt: 80 điểm - Đúng lần đầu chơi cả 3 lượt: 100 điểm 2.3. Game có 1 lượt chơi: - Không có lần drag sai (100 điểm) - 1 lần drag sai (80 điểm) - >=2 lần drag sai (60 điểm) 3. Tính sao hiển thị: - Count số lần chơi các game cùng 1 kĩ năng trong 7 ngày gần nhất - Tính trung bình số điểm/lần hoàn thành game - Quy đổi thành đơn vị SAO bằng cách chia cho 20: 1=>5 SAO, làm tròn đến đơn vị 0.5 SAO
C3: BE.RP05 | D3: Multiple choice (cho audio chọn ảnh) | E3: Listening | G3: Phân biệt các skills
C4: EE.RP01 | D4: Multiple choice - Audio | E4: Listening | G4: cho audio chọn text | H4: listening
C5: BE.RP04 | D5: Listen and choose picture | E5: Listening | G5: cho audio chọn ảnh | H5: listening
C6: MG.MC02 | D6: Multiple choice (ảnh) | E6: Listening | G6: cho ảnh chọn audio | H6: listening
C7: BE.RV03 | D7: Listen and choose (cho audio chọn text) | E7: Listening | G7: cho ảnh chọn text | H7: reading
C8: BE.RV06 | D8: Multiple choice (cho audio chọn text) | E8: Listening | G8: cho text chọn ảnh | H8: reading
C9: BE.PS01 | D9: Brick layer | E9: Reading | G9: cho text chọn audio | H9: reading
C10: BE.RS02 | D10: Word machine | E10: Reading
C11: EE.RV01 | D11: Multiple choice - Image | E11: Listening
C12: EE.RW08 | D12: Multi-bubble | E12: Listening
A13: Nhóm 2 | C13: EE.GS01 | D13: Letter Fishing | E13: Listening | F13: 1. Tính kết quả theo số lần tap (cá) của user 2. Cách tính điểm của 1 game: - User thao tác tap trên màn hình >12 lần: 40 điểm - User thao tác tap trên màn hình 9-12 lần: 60 điểm - User thao tác tap trên màn hình 5-8 lần: 80 điểm - User thao tác tap trên màn hình 4 lần: 100 điểm 3. Tính sao hiển thị: - Count số lần chơi các game cùng 1 kĩ năng trong 7 ngày gần nhất - Tính trung bình số điểm/lần hoàn thành game - Quy đổi thành đơn vị SAO bằng cách chia cho 20: 1=>5 SAO, làm tròn đến đơn vị 0.5 SAO
D14: Word Fishing | E14: Reading | F14: 1. Tính kết quả theo số lần tap (cá) của user 2. Cách tính điểm của 1 game: - User thao tác tap trên màn hình >16 lần: 40 điểm - User thao tác tap trên màn hình 13-16 lần: 60 điểm - User thao tác tap trên màn hình 9-12 lần: 80 điểm - User thao tác tap trên màn hình 8 lần: 100 điểm 3. Tính sao hiển thị: - Count số lần chơi các game cùng 1 kĩ năng trong 7 ngày gần nhất - Tính trung bình số điểm/lần hoàn thành game - Quy đổi thành đơn vị SAO bằng cách chia cho 20: 1=>5 SAO, làm tròn đến đơn vị 0.5 SAO
C15: BE.RVS02 | D15: Jumbled pages | E15: Reading | F15: 1. Tính kết quả theo số lần drag (ảnh) của user 2. Cách tính điểm của game: - User thao tác drag trên màn hình >8 lần: 40 điểm - User thao tác drag trên màn hình 7-8 lần: 60 điểm - User thao tác drag trên màn hình 5-6 lần: 80 điểm - User thao tác drag trên màn hình 4 lần: 100 điểm 3. Tính sao hiển thị: - Count số lần chơi các game cùng 1 kĩ năng trong 7 ngày gần nhất - Tính trung bình số điểm/lần hoàn thành game - Quy đổi thành đơn vị SAO bằng cách chia cho 20: 1=>5 SAO, làm tròn đến đơn vị 0.5 SAO
C16: BE.RV08 | D16: Catching fireflies | E16: Reading | F16: 1. Tính kết quả theo số lần drag (đom đóm) của user 2. Cách tính điểm của 1 game: - User thao tác drag trên màn hình >20 lần: 20 điểm - User thao tác drag trên màn hình 17-20 lần: 40 điểm - User thao tác drag trên màn hình 13-16 lần: 60 điểm - User thao tác drag trên màn hình 11-12 lần: 80 điểm - User thao tác drag trên màn hình 10 lần: 100 điểm 3. Tính sao hiển thị: - Count số lần chơi các game cùng 1 kĩ năng trong 7 ngày gần nhất - Tính trung bình số điểm/lần hoàn thành game - Quy đổi thành đơn vị SAO bằng cách chia cho 20: 1=>5 SAO, làm tròn đến đơn vị 0.5 SAO
A17: Nhóm 3 | C17: BE.GP05 | D17: Trace the letter (Tracing) | E17: Writing | F17: 1. Tính kết quả của lượt tô tự do (lượt cuối) Với những âm có 2-3 chữ cái: user cần tô cả 2-3 chữ cái thì mới tính là 1 lượt, không tính lẻ theo từng letter riêng 2. Cách tính điểm: * Với luồng < 3 tuổi: không áp dụng Hand-writing mà chỉ tô trên nét đứt - User tô đúng từ lần 1: 100 điểm - User tô đúng từ lần 2: 80 điểm - User tô đúng từ lần 3: 60 điểm - User tô đúng ở lần cuối (drag): 40 điểm * Với luồng >= 3 tuổi: áp dụng Hand-writing - Hệ thống nhận đúng chữ: 100 điểm - Hệ thống không nhận diện được chữ: 40 điểm 3. Tính sao hiển thị: - Count số lần chơi các game cùng 1 kĩ năng trong 7 ngày gần nhất - Tính trung bình số điểm/lần hoàn thành game - Quy đổi thành đơn vị SAO: 1=>5 SAO, làm tròn đến đơn vị 0.5 SAO
A18: Nhóm 4 | C18: BE.PV02 | D18: Cat teaching AI | E18: Speaking | F18: 1. Tính kết quả của lần thu âm cuối cùng 2. Cách tính điểm của 1 lượt: - TH1: match >=80% => 100 điểm - TH2: match >=60% => 80 điểm - TH3: 50% =< match <60% => 60 điểm - TH4: match < 50% => 40 điểm 3. Tính sao hiển thị: - Count số lần chơi các game cùng 1 kĩ năng trong 7 ngày gần nhất - Tính trung bình số điểm/lần hoàn thành game - Quy đổi thành đơn vị SAO: 1=>5 SAO, làm tròn đến đơn vị 0.5 SAO
C19: BE.PV03 | D19: Robot teaching AI | E19: Speaking
C20: EE.PS01 | D20: Speaking sentence (AI) | E20: Speaking
D21: Chunking speaking | E21: Speaking
C22: BE.PD01 | D22: Dialog 1 | E22: Speaking
C23: BE.PS04 | D23: Speaking competition | E23: Speaking

Sheet So sánh MJ 4.0 vs. MJ 5.0
A1: So sánh sản phẩm - MONKEY JUNIOR 4.0 và MONKEY JUNIOR 5.0
A3: Tiêu chí | B3: Phiên bản hiện tại | C3: Monkey Junior 5.0
A4: Tổng quan app | B4: Home course gồm nhiều khóa học, mỗi khóa học có mục tiêu học khác nhau để bộ trợ riêng cho từng kỹ năng | C4: Home course gồm 1 lộ trình chính giúp phát triển toàn diện 4 kỹ năng Nghe - Nói - Đọc - Viết cho trẻ từ 0-8 tuổi kèm theo mục Siêu Việt (hệ thống các khóa học bổ trợ của MJ 4.0)
A5: Đối tượng học | B5: Trẻ độ tuổi 0-11 | C5: Lộ trình chính dành cho trẻ độ tuổi 0-8
A6: Lộ trình học | B6: - MABC: 3 cấp độ, trẻ tự do chọn cấp độ, topic học - MS: đặc trưng của việc đọc truyện theo cấp độ >> có nhiều cấp độ đọc truyện - MSP: 4 cấp độ, trẻ được học unit đầu mỗi cấp độ | C6: Lộ trình chính gồm 6 cấp độ: - Cấp độ 0 (0-3 tuổi): nghe hiểu, nhận diện được hình ảnh và mặt chữ của các từ vựng thuộc chủ đề gần gũi với cuộc sống hàng ngày - Cấp độ 1-5 (3-8 tuổi): phát triển toàn diện 4 kỹ năng Nghe - Nói - Đọc - Viết Mỗi level mở 01 bài học đầu tiên. Users được phép học thử các levels để quyết định sẽ học level nào
A7: Nội dung học | B7: Chi tiết xem product profile từng khóa học - MABC: học từ vựng - MSP: luyện nói và giao tiếp - MS: đọc truyện theo cấp độ | C7: Các khóa học khác: giữ nguyên Lộ trình chính gồm: - Âm phonics: 100 âm - Từ vựng phonics: 400 từ - Từ vựng ghép vần: 200 từ - Từ vựng chủ đề: 400 từ (bao gồm 100 từ trùng với từ vựng phonics) - Câu: 100 câu - Hội thoại: 100 hội thoại - Truyện: 50 truyện - Video: 150 video Nội dung học được xây dựng hoàn toàn mới, không trùng lặp với các khóa khác Benchmark: - Từ vựng: CEFR - Tổng quan kiến thức, kĩ năng: theo Cambridge (Starters, Movers)
A8: Chương trình học | C8: Khối lượng kiến thức khổng lồ được chia thành nhiều level, nhiều unit, mỗi unit được chia ra 7 bài học giúp trẻ dễ dàng nắm bắt và thực hành nội dung học, sử dụng nhiều kĩ năng ngôn ngữ khác nhau
A9: Cấu trúc bài học | B9: Chi tiết xem product profile từng khóa học | C9: Lộ trình học chính chia theo 2 giai đoạn: * Level 0 (0-3 tuổi) Ở Cấp độ 0, một đơn vị bài học gồm hai chủ đề nhỏ với 16 từ vựng được học trong 5 bài học. 5 bài học này gồm 2 loại bài học tương ứng. Từ bài học 1 đến bài học 4, mỗi bài học trẻ được học 8 từ vựng trong 2 chủ đề, như vậy mỗi từ được lặp lại 2 lần. Trong bài học 5, trẻ được xem video bài hát/ bài vè/ truyện. * Level 1-5 (3-8 tuổi) Mỗi cấp độ từ 1-5 bao gồm 140 bài học, trong đó có 20 chủ đề, và mỗi chủ đề gồm 7 bài học. Tất cả các chủ đề đều có 7 từ vựng chính, 1 âm phonics và 2 từ phonics ghép âm, 1 mẫu câu, 1 hội thoại, 1 truyện/video chứa mẫu câu.
A10: Phương pháp học | B10: - MABC: các PP GDS - MSP: PP Giao tiếp, KT Nhại lại (Shadowing), PP Chunking - MS course: PP Học thông qua truyện tranh tương tác - MS app: thêm PP Phonics | C10: * Level 0 (0-3 tuổi): - Phương pháp Chụp hình nguyên từ - Phương pháp Tráo thẻ nhanh - Glenn Doman - Phương pháp Đa giác quan - Phương pháp Học thông qua trò chơi * Level 1-5 (3-8 tuổi): - Phương pháp Học qua đa phương tiện - Phương pháp Ngữ âm - Phương pháp Dạy ngôn ngữ qua giao tiếp
A11: Outcomes | B11: Chi tiết xem product profile từng khóa học | C11: Xem chi tiết ở đây
A12: Hoạt động trò chơi | B12: Mỗi khóa học có hệ thống trò chơi riêng phục vụ mục đích của từng khóa (chi tiết xem product profile từng khóa) | C12: - Các khóa học bổ trợ vẫn giữ nguyên hệ thống trò chơi - Lộ trình chính được bổ sung thêm các trò chơi mới được minh họa mới theo phong cách hiện đại, sinh động, hấp dẫn trẻ nhỏ - Các hoạt động được phân loại theo mục đích dạy kỹ năng: luyện nghe và phát âm, ghép câu, giao tiếp, đọc hiểu, viết chữ. - Các trò chơi được thiết kế với tính tương tác cao: video tương tác, game tô chữ áp dụng công nghệ nhận diện chữ viết,...
A13: Công nghệ | B13: Công nghệ MSpeak độc quyền chấm điểm phát âm bằng trí tuệ nhân tạo, dành riêng cho trẻ em giúp kiểm tra, chấm điểm phát âm dựa trên độ chính xác của các âm, trọng âm | C13: - Công nghệ MSpeak độc quyền chấm điểm phát âm dựa trên độ chính xác của các âm, trọng âm - Công nghệ nhận diện chữ viết Handwriting đánh giá độ chính xác khi viết chữ của trẻ - Video tương tác giúp tăng sự hứng thú của trẻ
A14: Phần thưởng | B14: - Monkey Shop - Xu sau bài học - Sticker sau unit | C14: Không thay đổi

Sheet So sánh list từ
A1: =COUNTA(A3:A1299) -> 1179 | B1: =COUNTA(B3:B1299) -> 919 | C1: 442 | D1: =C1/B1 -> 0.48095756 | F1: =COUNTA(F3:F1299) -> 1045 | G1: =COUNTA(G3:G1299) -> 427 | H1: 292 | I1: =H1/G1 -> 0.68384075 | K1: =COUNTA(K3:K1299) -> 320 | L1: =COUNTA(L3:L1299) -> 278 | M1: 63 | N1: =M1/L1 -> 0.22661871 | P1: =COUNTA(P3:P1299) -> 324 | Q1: =COUNTA(Q3:Q1299) -> 350 | R1: 90 | S1: =R1/Q1 -> 0.25714286
A2: Tổng từ MJ | B2: Tổng từ Cambridge | C2: Số từ trùng | D2: % trùng | F2: Level 0-1 | G2: A1 Starters | H2: Số từ trùng | I2: % trùng | K2: Level 2-3 | L2: A1 Movers | M2: Số từ trùng | N2: % trùng | P2: Level 4-5 | Q2: A2 Flyers | R2: Số từ trùng | S2: % trùng
A3: cat | B3: animal | F3: cat | G3: animal | K3: watermelon | L3: bat | P3: flashlight | Q3: beetle
A4: cow | B4: bear | F4: cow | G4: bear | K4: orange | L4: cage | P4: sleeping bag | Q4: butterfly
A5: dog | B5: bee | F5: dog | G5: bee | K5: cherry | L5: dolphin | P5: tent | Q5: camel
A6: pig | B6: bird | F6: pig | G6: bird | K6: papaya | L6: fly | P6: compass | Q6: creature
A7: eye | B7: cat | F7: eye | G7: cat | K7: jacket | L7: kangaroo | P7: sloth | Q7: dinosaur
A8: ear | B8: chicken | F8: ear | G8: chicken | K8: sweater | L8: kitten | P8: snail | Q8: eagle
A9: arm | B9: cow | F9: arm | G9: cow | K9: coat | L9: lion | P9: tortoise | Q9: extinct
A10: leg | B10: crocodile | F10: leg | G10: crocodile | K10: shirt | L10: panda | P10: koala | Q10: fur
A11: popcorn | B11: dog | F11: popcorn | G11: dog | K11: yacht | L11: parrot | P11: smock | Q11: insect
A12: candy | B12: donkey | F12: candy | G12: donkey | K12: ship | L12: penguin | P12: paintbrush | Q12: nest
A13: jello | B13: duck | F13: jello | G13: duck | K13: boat | L13: puppy | P13: palette | Q13: octopus
A14: ice cream | B14: elephant | F14: ice cream | G14: elephant | K14: ferry | L14: rabbit | P14: easel | Q14: swan
... A272: fireplace | B272: mouse | F272: fireplace | G272: English | K272: black | L272: hospital | P272: throw | Q272: December
A273: hammer | B273: music | F273: hammer | G273: eraser | L273: ill | P273: wrestle | Q273: ambulance
A274: broom | B274: number | F274: broom | G274: example | K274: sweater | L274: matter | P274: wrap | Q274: bicycle
A275: towel | B275: open | F275: towel | G275: find | K275: watermelon | L275: nurse | P275: wrinkle | Q275: fire engine
A276: elderly man | B276: page | F276: elderly man | G276: floor | K276: jacket | L276: sick | P276: knee | Q276: fire truck
A277: elderly woman | B277: painting | F277: elderly woman | G277: keyboard | K277: yacht | L277: stomach-ache | P277: knock | Q277: journey
A278: teenager | B278: part | F278: teenager | G278: computer | K278: yo-yo | L278: temperature | Q278: lift
A279: kid | B279: pen | F279: kid | G279: learn | K279: fox | L279: tired | P279: engineer | Q279: motorway
A280: worm | B280: pencil | F280: worm | G280: lesson | K280: zoo | L280: toothache | P280: flashlight | Q280: passenger
A281: moth | B281: poster | F281: moth | G281: letter | K281: queen | P281: sloth | Q281: platform
A282: slug | B282: question | F282: slug | G282: line | K282: cheese | P282: smock | Q282: racing
A283: mantis | B283: read | F283: mantis | G283: listen | K283: peach | P283: cave | Q283: ride
A284: slide (v) | B284: right | F284: slide | G284: look | K284: scooter | P284: rose | Q284: railway
A285: carry | B285: ruler | F285: carry | G285: mouse | K285: cooker | P285: throne | Q285: rocket
A286: dip | B286: school | F286: dip | G286: music | K286: bowling | P286: ice skates | Q286: spaceship
A287: drop | B287: sentence | F287: drop | G287: number | K287: goat | P287: amusement park | Q287: taxi
A288: juice | B288: sit | F288: juice | G288: open | K288: aloe | P288: athlete | Q288: tour
A289: water | B289: spell | F289: water | G289: page | K289: soup | P289: garden | Q289: traffic
A290: coffee | B290: stand | F290: coffee | G290: painting | K290: cloudy | P290: claw | Q290: wheel
A291: hot chocolate | B291: story | F291: hot chocolate | G291: paper | K291: boil | P291: hawk | Q291: fog
A292: baker | B292: teacher | F292: baker | G292: part | K292: soy | P292: reindeer | Q292: foggy
... A323: pot | B323: photo | F323: pot | G323: boat | K323: blazer | P323: stream | Q323: taxi
A324: rainbow | B324: piano | F324: rainbow | G324: book | P324: throne | Q324: waiter
A325: sea | B325: play | F325: sea | G325: bounce | P325: wrist | Q325: air
A326: Earth | B326: ride | F326: Earth | G326: camera | P326: knit | Q326: bridge
A327: cloud | B327: run | F327: cloud | G327: catch | P327: knight | Q327: castle
A328: cicada | B328: sing | F328: cicada | G328: doll | Q328: cave
A329: caterpillar | B329: skateboard | F329: caterpillar | G329: draw | Q329: desert
A330: dragonfly | B330: skateboarding | F330: dragonfly | G330: drawing | Q330: Earth
A331: butterfly | B331: song | F331: butterfly | G331: drive | Q331: entrance
A332: tricycle | B332: sport | F332: tricycle | G332: enjoy | Q332: environment
A333: tractor | B333: swim | F333: tractor | G333: favorite | Q333: exit
A334: carriage | B334: table tennis | F334: carriage | G334: fishing | Q334: fire
A335: forklift | B335: take a photo | F335: forklift | G335: fly | Q335: future
A336: basketball | B336: tennis | F336: basketball | G336: football | Q336: hill
A337: volleyball | B337: tennis racket | F337: volleyball | G337: soccer | Q337: land
A338: table tennis | B338: throw | F338: table tennis | G338: game | Q338: ocean
A339: baseball | B339: walk | F339: baseball | G339: guitar | Q339: planet
... A352: shirt | B352: helicopter | F352: shirt | G352: read | Q352: x-ray
A353: T-shirt | B353: monster | F353: T-shirt | G353: ride
A354: dress | B354: motorbike | F354: dress | G354: run
A355: hat | B355: plane | F355: hat | G355: sing
A356: salt | B356: robot | F356: salt | G356: skateboard
A357: sugar | B357: teddy bear | F357: sugar | G357: skateboarding
A358: ginger | B358: train | F358: ginger | G358: song
A359: garlic | B359: truck | F359: garlic | G359: sport
A360: farm | B360: bus | F360: farm | G360: story
A361: park | B361: go | F361: park | G361: swim
A362: beach | B362: ship | F362: beach | G362: table tennis
A363: school | B363: sun | F363: school | G363: take a photo
A364: board | B364: sand | F364: board | G364: television
... A429: flower pot | B429: basement | F429: door handle | G429: water
A430: door handle | B430: blanket | F430: television
A431: television | B431: downstairs | F431: firefighter
A432: firefighter | B432: dream | F432: police officer
A433: police officer | B433: elevator | F433: construction worker
A434: construction worker | B434: internet | F434: photographer
A435: photographer | B435: lift | F435: wild boar
A436: wild boar | B436: message | F436: skunk
A437: skunk | B437: roof | F437: lemur
A438: lemur | B438: seat | F438: beaver
A439: beaver | B439: shower | F439: fingernail
A440: fingernail | B440: stair | F440: elbow
A441: elbow | B441: stairs | F441: ankle
... A921: tiptoe | B921: one hundred | F921: read
A922: hoe | F922: man
A923: doe | F923: play
A924: coupon | F924: carry
A925: wound | F925: wash
A926: mousse | F926: under
A927: south | F927: apple
A928: house | F928: mango
A929: soil | F929: banana
A930: coin | F930: pear
A931: toilet | F931: tiger
A932: cowboy | F932: bear
A933: toys | F933: lion
... A1047: can | F1047: pineapple
A1048: he
A1049: for
A1050: on
A1051: are
A1052: with
A1053: they
A1054: at
A1055: be
...

Sheet Sheet14
A2: Cấp độ | B2: Chủ đề | C2: Ngữ âm | D2: Nghe | E2: Nói | F2: Đọc | G2: Viết
A3: 1 | B3: 20 chủ đề quen thuộc: Con vật, Hoa quả, Đồ chơi,... | C3: - Nhận biết và phát âm được 20 âm đơn lẻ. - Học cách ghép các âm vào từ. | D3: - Nghe và hiểu được tên riêng, tên gọi đồ vật, sự vật rất đơn giản, quen thuộc. - Nghe, hiểu và làm theo những yêu cầu đơn giản, tương tác chọn đáp án. | E3: - Biết nhắc lại, nói tên riêng, tên đồ vật, sự vật rất đơn giản, quen thuộc. - Phát âm tương đối rõ ràng các từ đơn lẻ của chủ đề được học. | F3: - Đọc từ vựng, câu trong hội thoại, truyện. - Trả lời các câu hỏi rất đơn giản về truyện. | G3: - Tập tô chữ cái đơn lẻ.
A4: 2 | B4: 20 chủ đề quen thuộc: Đồ ăn, Quần áo, Nhà cửa,... | C4: - Bắt đầu nhận biết và phát âm được âm đôi. - Học cách ghép các âm vào từ. | D4: - Nghe và hiểu được tên gọi đồ vật, sự vật đơn giản, quen thuộc. - Nghe, hiểu và làm theo những yêu cầu đơn giản, tương tác chọn đáp án. | E4: - Phát âm rõ ràng các từ của chủ đề được học. - Nói được các cụm từ và cấu trúc câu đơn giản. | F4: - Đọc từ vựng, câu trong hội thoại, truyện. - Trả lời các câu hỏi rất đơn giản về truyện. | G4: - Bắt đầu tập tô tổ hợp 1 - 2 chữ cái.
A5: 3 | B5: 20 chủ đề quen thuộc: Thời tiết, Địa điểm, Phương tiện,... | C5: - Nhận biết và phát âm được các âm đôi. - Ghép các âm vào từ. | D5: - Nghe và hiểu được tên gọi đồ vật, sự vật, hành động. - Nghe, hiểu và làm theo những yêu cầu để tương tác trong bài học. | E5: - Phát âm rõ ràng các từ vựng và mẫu câu của chủ đề được học. - Nói được câu trong hội thoại và truyện. | F5: - Đọc hiểu từ vựng, câu đơn giản trong hội thoại, truyện. - Trả lời các câu hỏi về ý nghĩa truyện, sắp xếp tình tiết truyện. | G5: - Tô các chữ cái trong tổ hợp âm đôi.
A6: 4 | B6: 20 chủ đề quen thuộc: Thể thao, Thiên nhiên, Nghề nghiệp,... | C6: - Nhận biết và phát âm được các âm đôi. - Ghép các âm vào từ. | D6: - Nghe, hiểu, nắm rõ được tên gọi đồ vật, sự vật, hành động. Nghe, hiểu và làm theo những yêu cầu để tương tác trong bài học. | E6: - Phát âm rõ ràng các từ vựng và mẫu câu của chủ đề được học. - Nói được câu trong hội thoại và truyện. | F6: - Đọc hiểu, đoán được nghĩa từ vựng, câu trong ngữ cảnh. - Trả lời các câu hỏi về ý nghĩa truyện, sắp xếp tình tiết truyện. | G6: - Tô các chữ cái trong tổ hợp âm đôi.
A7: 5 | B7: 20 chủ đề: Sức khỏe, Công cụ, Công nghệ,... | C7: - Nhận biết và phát âm được các âm đôi và âm gồm 3 chữ cái. - Ghép các âm vào từ. | D7: - Nghe, hiểu, nắm rõ được tên gọi đồ vật, sự vật, hành động. - Nghe, hiểu và làm theo những yêu cầu để tương tác trong bài học. | E7: - Phát âm rõ ràng các từ vựng và mẫu câu của chủ đề được học. - Nói được câu trong hội thoại và truyện. | F7: - Đọc hiểu, đoán được nghĩa từ vựng, câu trong ngữ cảnh. - Trả lời các câu hỏi về ý nghĩa truyện, sắp xếp tình tiết truyện. | G7: - Tô các tổ hợp phụ âm được cấu tạo bởi 2 - 3 chữ cái.

Sheet MJ 5.0_Level 0_ Game list 07052
G1: Round 0 - GD + PO chuẩn bị tài liệu | Q1: Round 1.1 - Dev (Unity) | Z1: Round 1.1 - BE config data | AG1: Round 1.1 QA test | AQ1: R1.2 - PO + GD + Artist nghiệm thu | AV1: Round 2.1 - Done fix bug | AY1: Round 2.2 Product Team nghiệm thu
I2: Dự kiến | J2: Thực tế | U2: Timeline dự kiến | W2: Timeline thực tế | AD2: Dự kiến | AE2: Thực tế | AJ2: Dự kiến | AM2: Thực tế | AS2: Dự kiến | AT2: Thực tế | AV2: Dự kiến | AW2: Thực tế | AY2: Dự kiến | AZ2: Thực tế
A3: Content type | B3: Activity type | C3: Focus | D3: Course | E3: Game name | F3: Hình thức | G3: Loại data | H3: Video tham khảo | I3: Ngày trả docs | J3: Ngày trả docs | K3: Doc2 cũ | L3: Doc2 mới | M3: Trạng thái doc | N3: Thời gian chuyển dev | O3: Thời gian cần done data | Q3: huongbt_note CR game | R3: PIC dev | S3: STT dev | T3: ETA (days) | U3: Start dev | V3: End dev | W3: Start dev | X3: End dev | Z3: BE Config (1h/ 1 game) | AA3: BE 2 Activity Test | AB3: PO full data | AC3: BE Full Data | AD3: UN Ghép data | AE3: UN Ghép data | AG3: PIC QA | AH3: Start Testcase | AI3: ETA test game (giờ) | AJ3: Start QA | AK3: Done QA | AL3: Ngày chuyển PO nghiệm thu - R1 | AM3: Start QA | AN3: Done QA | AO3: Ngày chuyển PO nghiệm thu - R1 | AQ3: PO_Nghiệm thu game play | AR3: PO_Nghiệm thu game 1 - 2 unit | AS3: PO chuyển Dev | AT3: PO chuyển Dev | AV3: Dev chuyển PO | AW3: Dev chuyển PO | AY3: Product Team nghiệm thu | AZ3: Product Team nghiệm thu
A4: Vocab | B4: Intro | C4: 4 từ | D4: EE.IW01 | E4: Multisensory | F4: Nghe audio + nhìn ảnh/ video | G4: Ảnh/ Video + Audio + Text | H4: Link | K4: Link | L4: Link | M4: Done doc 2 | R4: Tài | S4: Done dev | X4: 21/6 | AG4: Linh Phạm
C5: 4 từ | D5: EE.IV01 | E5: Flashcard | F5: Nghe audio + nhìn ảnh | G5: Ảnh + Audio | H5: Link | K5: Link | L5: Link | M5: Done doc 2 | R5: Thuận | S5: Done dev | X5: 21/6 | AG5: Linh Phạm
A6: Vocab | B6: Guided | C6: 2 từ | D6: EE.IW04 | E6: Tap the balloon | F6: Tap bóng + nghe audio + nhìn ảnh | G6: Ảnh + Audio | H6: Link | K6: Link | L6: Link | M6: Done doc 2 | R6: Thuận | S6: Done dev | U6: 21/6 | V6: 24/6 - chiều | W6: 21/6 | X6: 24/6 - chiều | AG6: Linh Phạm
A7: Vocab | B7: Review | C7: 2 từ | D7: EE.RW08 | E7: Multi-bubble | F7: Nghe audio - chọn ảnh | G7: Ảnh + Audio | H7: Link | K7: Link | L7: Link | M7: Done doc 2 | R7: Nam | S7: Doing | T7: 3 | U7: 24/6 | V7: 26/6 | AG7: Linh Phạm
C8: 2 từ | D8: EE.RV01 | E8: Multiple choice - Image | F8: Cho text - chọn ảnh | G8: Ảnh + Text | H8: Link | K8: Link | L8: Link | M8: Done doc 2 | R8: Thuận | S8: Doing | U8: 24/6 - chiều | V8: 27/6 - sáng | AG8: Linh Phạm
C9: 2 từ | D9: EE.RW02 | E9: Listen and Choose 3 | F9: Nghe audio - chọn ảnh | G9: Ảnh + Audio | H9: Link | K9: Link | AG9: Linh Phạm
A10: SW | B10: Intro | C10: 6 từ | D10: EE.IV04 | E10: Tap 3 options + Flashcard | F10: Tap 3 từ + Flashcard 3 từ | G10: Audio + Text | H10: Link | L10: Link | M10: Done doc 2 | R10: Nam | U10: 27S | AG10: Linh Phạm
A11: SW | B11: Review | C11: 2 từ | D11: BE.RP04 | E11: Listen and Choose 2 | F11: Nghe audio - chọn text | G11: Audio + Text | H11: Link | K11: Link | L11: Link | M11: Done doc 2 | R11: Thuận/ Nam | U11: 27C | AG11: Linh Phạm
A12: Truyện | B12: Input | D12: MJ.ST01 | F12: Đọc truyện | G12: Ảnh/ Video + Audio + Text | L12: Link | M12: Done doc 2 | R12: Tài | U12: 24/6 - chiều | AG12: Linh Phạm
A13: Video | D13: MJ.VD03 | F13: Xem video | G13: Ảnh/ Video | L13: Link | M13: Done doc 2 | AG13: Linh Phạm

Sheet MJ 5.0_Level 0_Flow 070524
A1: Luồng bài học Level 0 - MJ 5.0
A2: Từ vựng chủ đề: 16
A3: Từ SW: 6
A5: Flow 1 | B5: Intro Vocab (4 từ đầu) | C5: Review Vocab (2 từ) | D5: Review Vocab (2 từ) | E5: Intro Vocab (4 từ sau) | F5: Review Vocab (2 từ) | G5: Review Vocab (2 từ) | H5: Intro Vocab (4 từ đầu) | I5: Intro Vocab (4 từ sau) | J5: Intro SW (6 từ) | K5: Review SW (2 đầu)
B6: EE.IW01 - Multisensory | C6: EE.IW04 - Tap the balloon | D6: EE.IW04 - Tap the balloon | E6: EE.IW01 - Multisensory | F6: EE.IW04 - Tap the balloon | G6: EE.IW04 - Tap the balloon | H6: EE.IV01 - Flashcard | I6: EE.IV01 - Flashcard | J6: Tap 3 options + Flashcard | K6: EE.RW09 - Listen and Choose 2
C7: EE.RW08 - Multi-bubble | D7: EE.RW08 - Multi-bubble | F7: EE.RW08 - Multi-bubble | G7: EE.RW08 - Multi-bubble
C8: EE.RV01 - Multiple choice - Image | D8: EE.RV01 - Multiple choice - Image | F8: EE.RV01 - Multiple choice - Image | G8: EE.RV01 - Multiple choice - Image
D9: Anim | G9: Anim | J9: Anim
B12: Intro Vocab (4 từ đầu) | C12: Review Vocab (2 từ) | D12: Review Vocab (2 từ) | E12: Intro Vocab (4 từ sau) | F12: Review Vocab (2 từ) | G12: Review Vocab (2 từ) | H12: Intro Vocab (4 từ đầu) | I12: Intro Vocab (4 từ sau) | J12: Intro SW (6 từ) | K12: Review SW (2 đầu)
B13: Multisensory | C13: Tap bóng + nghe audio + nhìn ảnh | D13: Tap bóng + nghe audio + nhìn ảnh | E13: Multisensory | F13: Tap bóng + nghe audio + nhìn ảnh | G13: Tap bóng + nghe audio + nhìn ảnh | H13: Flashcard | I13: Flashcard | J13: Tap 3 options + Flashcard | K13: Nghe audio - chọn text
C14: Nghe audio - chọn ảnh | D14: Nghe audio - chọn ảnh | F14: Nghe audio - chọn ảnh | G14: Nghe audio - chọn ảnh
C15: Cho text - chọn ảnh | D15: Cho text - chọn ảnh | F15: Cho text - chọn ảnh | G15: Cho text - chọn ảnh
D16: Anim | G16: Anim | J16: Anim
A18: Flow 2 | B18: Play video/ truyện

Sheet MJ 5.0_Level 0_Data 130524
A1: Unit | B1: Level | C1: Topic | D1: Word | E1: Audio từ 1 | F1: Audio từ 2 | G1: Ảnh vẽ (từ) | H1: Ảnh thật 1 (từ) | I1: Ảnh thật 2 (từ) | J1: Video 3s1 | K1: Video 3s2 | L1: Câu 5s1 | M1: Audio 5s1 | N1: Video 5s1 | O1: Ảnh 5s1 | P1: Câu 5s2 | Q1: Audio 5s2 | R1: Video 5s2 | S1: Ảnh 5s2 | T1: Sound effect | U1: Color
A2: 1 | B2: 1 | C2: Animals 1 | D2: cat | E2: https://drive.google.com/file/d/1ob-7ubp1x27Kd3-OzJUxxOQD-Uwg_sB9/view?usp=sharing | F2: https://drive.google.com/file/d/1NEr2tCNWwGxIBqS2qXK47Le3CxHTuuwV/view?usp=sharing | G2: https://drive.google.com/file/d/1AYHmUWaPlG78JSqpkLKQ8iEoKYHI55ta/view?usp=drive_link | H2: https://drive.google.com/file/d/1tVq2TAhw5nLsW3LwWfGT_tVsrBT-FEG3/view?usp=sharing | I2: https://drive.google.com/file/d/1c0wPyk2Ma8NWydrR80N-MopM6ItPeTW9/view?usp=sharing | J2: https://drive.google.com/file/d/1pRbTzxtAn1AqJzrODal1YzlAm8XskFaM/view?usp=sharing | K2: https://drive.google.com/file/d/1FaXjVPHIA-5drGyz3ZOp3MDPD3VLIqNY/view?usp=sharing | L2: That cat is so cute! | M2: https://drive.google.com/file/d/1Yc36I4IJ0TTpunOVvL8PUfSscVgbwS90/view?usp=sharing | O2: https://drive.google.com/file/d/1i4v95OwsFwTjp1Lc17_preFGZFFpOo_5/view?usp=sharing | P2: The cat is jumping. | Q2: https://drive.google.com/file/d/1wiZVwsXmzoGSVu_FGsWlGDw1WBXMo_Qw/view?usp=sharing | S2: https://drive.google.com/file/d/1i7xFlEY_W-pMeJ3iuAqt1KLKfxTz80nn/view?usp=sharing | T2: https://vnmedia2.monkeyuni.net/upload/cms_platform/audio/1f798884bb67c1552f4a6e609e9730ba.mp3
A3: 1 | B3: 1 | C3: Animals 1 | D3: cow | E3: https://drive.google.com/file/d/1_tCnv5E3cNM1Qc1ugF3FesRyhbWGGkIC/view?usp=sharing | F3: https://drive.google.com/file/d/1s9nXdYmVVRftkk_25ECDdNmbjXBJYmuL/view?usp=sharing | G3: https://drive.google.com/file/d/1qtVaJHs2jIeKUVHUmHv8dTFH-uEu9YOh/view?usp=sharing | H3: https://drive.google.com/file/d/1AF-QwJmB3Z5eugqiLervhPwk_HvtmfYh/view?usp=sharing | I3: https://drive.google.com/file/d/14hdeZDUmHOEk5xWI6kUX_QyhX5YuNhhu/view?usp=sharing | J3: https://drive.google.com/file/d/1G79-RjX-oMthENlwqMeqhYqLmfekdJc8/view?usp=sharing | K3: https://drive.google.com/file/d/1UQzBw7QhWrd_wRebrdDxZo6wetM3VKrp/view?usp=sharing | L3: The cows are eating grass. | M3: https://drive.google.com/file/d/1uZoU6txearxHyVx99dhVihSzA7ToY8BH/view?usp=sharing | O3: https://drive.google.com/file/d/1t1JLYWKGO0Ubzeg620s3Wl6f49BvMFcl/view?usp=sharing | P3: The man is feeding the cows. | Q3: https://drive.google.com/file/d/1-VA35z3vKZhW0OlU7J_DdqTamBdDX6mm/view?usp=sharing | S3: https://drive.google.com/file/d/1m6ihLEkFb8bzJty-HV3h8I6tbBHIbDX_/view?usp=sharing | T3: https://vnmedia2.monkeyuni.net/upload/cms_platform/audio/b61bfdf8556d097b67e720893fdd0992.mp3
A4: 1 | B4: 1 | C4: Animals 1 | D4: dog | E4: https://drive.google.com/file/d/1EQ19HHJ_NPCVtme4HWeDBgZcG59PpQ_R/view?usp=sharing | F4: https://drive.google.com/file/d/1CSx_s4Z02QaLfVPwfS7_iX5AqxgT22LE/view?usp=sharing | G4: https://drive.google.com/file/d/1hpWaA629M4ihUQ0kwi8lnceElinT_vbB/view?usp=sharing | H4: https://drive.google.com/file/d/1khf23JrhY5WLF1ntyXAleeBkV_9It2aL/view?usp=sharing | I4: https://drive.google.com/file/d/12VKazQA9GsXQ2OWbO5h3kM2LWJBganHa/view?usp=sharing | J4: https://drive.google.com/file/d/18clfgmuQtc-tKrUvE0TceqFJca4h6YuK/view?usp=sharing | K4: https://drive.google.com/file/d/1cB9DYGy3BVhf6xzqcezBmun6sBUYcxrK/view?usp=sharing | L4: Wow, this is a beautiful dog! | M4: https://drive.google.com/file/d/1uTnKvrOrVFmlbeK2ZOLBIVtFClCpoiil/view?usp=sharing | O4: https://drive.google.com/file/d/1y7nniRnUgShgKO_BBeZZcP1DTYrae5Sr/view?usp=sharing | P4: Dogs can be good friends. | Q4: https://drive.google.com/file/d/1wb27dw68kz2Yn2R1vgT0KbYt0RBJg0Ty/view?usp=sharing | S4: https://drive.google.com/file/d/1djwHb9mECCqGAYo0Xs1ChprRi28x0g4Y/view?usp=sharing | T4: https://vnmedia2.monkeyuni.net/upload/cms_platform/audio/a562b4096ece55b8f6496dd73499e028.mp3
A5: 1 | B5: 1 | C5: Animals 1 | D5: pig | E5: https://drive.google.com/file/d/1LQqbyZXfnUMfs1AZo9e_dqLqAL9uEAuK/view?usp=sharing | F5: https://drive.google.com/file/d/14Nx3hFqMxbMQM4CqMGJtNGRSjqD3QSjA/view?usp=sharing | G5: https://drive.google.com/file/d/1xOOBKpr4Bo7VJuQXutoTlaxAx-lInktA/view?usp=sharing | H5: https://drive.google.com/file/d/12R6RBKN8-4xIxQK3MPAAwUi6ygSIJL2g/view?usp=sharing | I5: https://drive.google.com/file/d/16WvIBE6RoykAJdfREIiCmaK1qvyf1ect/view?usp=sharing | J5: https://drive.google.com/file/d/1-1HoxSCfWKnNFvxLhcg-ot6Xg6BDo00G/view?usp=sharing | K5: https://drive.google.com/file/d/1k3NFkluIq_T0sul4XBbAyqr8vd6Mw7W1/view?usp=sharing | L5: Pigs love playing in the mud. | M5: https://drive.google.com/file/d/1P_ZVJats8A51DGqK9HjjC7ibpun4_gDz/view?usp=sharing | O5: https://drive.google.com/file/d/1VNaGkLbPxw5cAfqytu8hEHscpoqFKtoO/view?usp=sharing | P5: Look! The baby pigs are lying with their mom. | Q5: https://drive.google.com/file/d/1thryEUZWSvgPSlNJ_YvG7u1Mja3W-i7y/view?usp=sharing | S5: https://drive.google.com/file/d/1i0Eq8FHrzGE9pmJ_UVcgzrdVo7zOeDFk/view?usp=sharing | T5: https://vnmedia2.monkeyuni.net/upload/cms_platform/audio/899658152eefc8ec0628b964ff472833.mp3
A6: 1 | B6: 1 | C6: Animals 3 | D6: bird | E6: https://drive.google.com/file/d/1EmqztjZxUYJet5pUE76Mgjzf6L37sJZs/view?usp=sharing | F6: https://drive.google.com/file/d/1-GDVjww8vbyGLsBrl5oK_bW-UD1MkeWD/view?usp=sharing | G6: https://drive.google.com/file/d/1kJbQovERklMBTIw8SZALYuojwwchlnL_/view?usp=sharing | H6: https://drive.google.com/file/d/18b2dVmzJmD6jKc5Ohbayz_ok0YNO5XiQ/view?usp=sharing | I6: https://drive.google.com/file/d/1j7JORmSr0BHHMYUtk9fHdnLltnirHSYK/view?usp=sharing | J6: https://drive.google.com/file/d/1cabBHN_v38eAg1G-B2abTwvYpqL91h5Q/view?usp=sharing | K6: https://drive.google.com/file/d/1JSpTzKSCqaQZO2FcSC8Zn-UPy-kk4dMs/view?usp=sharing | L6: The bird is eating seeds. | M6: https://drive.google.com/file/d/1mH4b3V4X5syRaV4vWhmbPrYABsfWBr4m/view?usp=sharing | O6: https://drive.google.com/file/d/1Y328gUNS2T9uEmo2wJAoH5f1IbIJr2Qk/view?usp=sharing | P6: Look! That is such a beautiful bird! | Q6: https://drive.google.com/file/d/1UUe0ZrZEw5cIaEkw4ZjnrZqPGBHXOoq3/view?usp=sharing | S6: https://drive.google.com/file/d/1uhHD0aoKg2XALa_v5ILAMtAOa4pvX59C/view?usp=sharing | T6: https://vnmedia2.monkeyuni.net/upload/cms_platform/audio/1d8d983899b8999c837ecb16d7a71bca.mp3
A7: 1 | B7: 1 | C7: Animals 3 | D7: duck | E7: https://drive.google.com/file/d/1HIzNBQ8Bnfb5EfDt26omDMl2AjXVo47a/view?usp=sharing | F7: https://drive.google.com/file/d/1y9wxSslZWQ6049TcoI7_pDou3hXXX_M-/view?usp=sharing | G7: https://drive.google.com/file/d/1UkX4-otqwrpSJMEchmTN1BT0ClyUjy9h/view?usp=sharing | H7: https://drive.google.com/file/d/1xHUzhYE7Z_CpWQsHQp_fQIbkWsH0lrcO/view?usp=sharing | I7: https://drive.google.com/file/d/1XzlSRQ3T3mgMCiNS8I_liJlutgF0AL62/view?usp=sharing | J7: https://drive.google.com/file/d/11alhEtuVqCRhjrgJIj-nFfmyEAcEBEYu/view?usp=sharing | K7: https://drive.google.com/file/d/1D6c4p3_7YT3pR639ZIMMMVVtm1CPgy6v/view?usp=sharing | L7: The baby ducks are following their mother. | M7: https://drive.google.com/file/d/1D5rDf_NRHUMZ2YQCFJwBEamZmhUqleXH/view?usp=sharing | O7: https://drive.google.com/file/d/1if7pECDvCi5edlWtD-S-vDb1lDvVQgPP/view?usp=sharing | P7: The ducks are flying away. | Q7: https://drive.google.com/file/d/1AokOGPlMBILKfXlWFamgE4YATumlr2Px/view?usp=sharing | S7: https://drive.google.com/file/d/1wnslBAw9mw10NBrpqUM3fIJbl0XcT3CI/view?usp=sharing | T7: https://vnmedia2.monkeyuni.net/upload/cms_platform/audio/9dfac0c99e662a02abed90d90d63e641.mp3
A8: 1 | B8: 1 | C8: Animals 3 | D8: bat | E8: https://drive.google.com/file/d/1QxnuwbCKlh21QuwabDnUi5fl3Y_7ScP8/view?usp=sharing | F8: https://drive.google.com/file/d/11wXCwi1wZD_XVPRnqaCPW9FeVc_qdPD5/view?usp=sharing | G8: https://drive.google.com/file/d/1hUrdmfstVLOi971Q3zU44vKYiMLMTytm/view?usp=sharing | H8: https://drive.google.com/file/d/1lwtMvPvD8bzma6ieWyQFC644OZ8A25mY/view?usp=sharing | I8: https://drive.google.com/file/d/1tGMGHHp2f-GV1opzrQNWECl7cfCyACyF/view?usp=sharing | J8: https://drive.google.com/file/d/1OMbqgmlxSSPXsk8L9i8buIYnskeTImv0/view?usp=sharing | K8: https://drive.google.com/file/d/15ye77bCpFidcUPVTTyDa_m658KqaeXtS/view?usp=sharing | L8: Bats can fly like birds. | M8: https://drive.google.com/file/d/10Ubm0T9mxcYhstkM1-ihkNjy0kcp3xXy/view?usp=sharing | O8: https://drive.google.com/file/d/1Zo_wrI8Daj5GdDQc4cpHzsGGJf3ZwkV5/view?usp=sharing | P8: The bats are hanging. | Q8: https://drive.google.com/file/d/1jXqaHewG2XBaCenHXmdjw8IGcbDVLTHb/view?usp=sharing | S8: https://drive.google.com/file/d/1N6HCfixQA9_vwe9ZASBtw1ufxMhUyY0-/view?usp=sharing
A9: 1 | B9: 1 | C9: Animals 3 | D9: frog | E9: https://drive.google.com/file/d/1bPRiDLeOaIRTjTW_t6NjQaZ3DoKnj7pB/view?usp=sharing | F9: https://drive.google.com/file/d/1z6QuOm-YbY4v4QteKOfyo_Fe58rvBpMn/view?usp=sharing | G9: https://drive.google.com/file/d/1zX9HWTCyr4xRX6IJKUSIgF4vW5JDb5KC/view?usp=sharing | H9: https://drive.google.com/file/d/1AdQuLj5PLe6FeRxiznUtMctrnvAhDDed/view?usp=sharing | I9: https://drive.google.com/file/d/1JC3hvFTzflwq7Lc9iadD4CRxKPZDTfRl/view?usp=sharing | J9: https://drive.google.com/file/d/1IrYDUtq0ziFVNKwE8NSTS-vksh1bZ97C/view?usp=sharing | K9: https://drive.google.com/file/d/1dsilPqawTkDc7_PKv5DJ38bhVLfjL78b/view?usp=sharing | L9: Look, the frog is jumping! | M9: https://drive.google.com/file/d/1IQNUNKzvx3srfS66JGy4XuuVRH7d6KkZ/view?usp=sharing | O9: https://drive.google.com/file/d/1wfQeRloI5upqG2-rVV8tXNt6E4I5XE0k/view?usp=sharing | P9: The frog is floating in the water. | Q9: https://drive.google.com/file/d/15GC6RkpNh6jb9DQnwAurwthX3um882JV/view?usp=sharing | S9: https://drive.google.com/file/d/18iflqfAjcIB9pXL9rHwB2qKVO-JE0YMk/view?usp=sharing | T9: https://vnmedia2.monkeyuni.net/upload/cms_platform/audio/f9416eaf1ec03dc8eea7104954117352.mp3
A10: 1 | B10: 1 | C10: Actions 3 | D10: hug | E10: https://drive.google.com/file/d/1TraXz3S9herCKV-r219Ti6EaLO6Alg_y/view?usp=sharing | F10: https://drive.google.com/file/d/1LiaHO7HRUZUUobcz0rrQUNApLZ6uW5Ag/view?usp=sharing | G10: https://drive.google.com/file/d/1krDM7tL1Iq2bvVewcWJijKj1NBgs6RRf/view?usp=sharing | H10: https://drive.google.com/file/d/1UYQtrawUv_N6cvlEmfHggfgqOOJiM--N/view?usp=sharing | I10: https://drive.google.com/file/d/1cvbqMnMXVkaYcSsAqCbT9DpJ-VRZfAco/view?usp=sharing | J10: https://drive.google.com/file/d/1KLtWJ0RV1rHTO-7bBw-iFZVGXNEbkRqQ/view?usp=sharing | K10: https://drive.google.com/file/d/1Hk7FbiH1TXic_ljkmMz5uM5GN9UrEZwU/view?usp=sharing | L10: Do you often hug your pet? | M10: https://drive.google.com/file/d/1wAy3SbzQe5KojVXDmghUYd-sKpnwjMp_/view?usp=sharing | O10: https://drive.google.com/file/d/15yIQCBcQA9hqmjkjcnNFtsqF-EMBAB5Y/view?usp=sharing | P10: Darling, please give Mommy a big hug! | Q10: https://drive.google.com/file/d/1hX2eSmQZ-CXvQrco2tg0mVLiLTB3MfHv/view?usp=sharing | S10: https://drive.google.com/file/d/1pTE6t3j7M32RTdAjoEzcs7PccdPPb5z7/view?usp=sharing
A11: 1 | B11: 1 | C11: Actions 3 | D11: kiss | E11: https://drive.google.com/file/d/1oT1Be8REpl8kduw1Y_gi4slPzceKO5dP/view?usp=sharing | F11: https://drive.google.com/file/d/1n66mRUblonqvhUmasSEhpPnLxSgV1H2t/view?usp=sharing | G11: https://drive.google.com/file/d/1eXP3Oxa9GbiLc0GKgX5LYFCohWPIxwF0/view?usp=sharing | H11: https://drive.google.com/file/d/1CAofo6jLswc8I6hbFGoZe0xrpqgq6OPo/view?usp=sharing | I11: https://drive.google.com/file/d/1Jp8bLEiVuELSZAuIPDXHncXjOtbd92Oi/view?usp=sharing | J11: https://drive.google.com/file/d/1rS-KJKR1dGwkP32kKn04aqZ2tS0jGJUw/view?usp=sharing | K11: https://drive.google.com/file/d/1k9sQhfOb1dzsFGgcqR2vK-FobhopbI8Q/view?usp=sharing | L11: Is the little boy kissing his teddy bear? | M11: https://drive.google.com/file/d/1rd5qT6Oa_akqfClcNNJbF-iqM5Wuu7Mc/view?usp=sharing | O11: https://drive.google.com/file/d/14t43Kk9Cf7ZZXIokv579ZRPlI9x5mr3W/view?usp=sharing | P11: My daddy and mommy are kissing me. How sweet! | Q11: https://drive.google.com/file/d/1h0qc1ITtr5awVhylnxUBOwGrYZm7C7BQ/view?usp=sharing | S11: https://drive.google.com/file/d/1p2cgaMDK5TAcBPgQmsWLqN74gCtiVDLg/view?usp=sharing
A12: 1 | B12: 1 | C12: Actions 3 | D12: give | E12: https://drive.google.com/file/d/1N46epO5UDpoPsm7A0YFxHc96nwp-XVD8/view?usp=sharing | F12: https://drive.google.com/file/d/1viv93YLm9El9_qTqvXQz5u5GD5vubivM/view?usp=sharing | G12: https://drive.google.com/file/d/1wBXzytWoP22AobJUiql6BVt_RMAwDXtp/view?usp=sharing | H12: https://drive.google.com/file/d/1sGqnAiRjA0UIqduEbaHkE5DxeUCkPdIN/view?usp=sharing | I12: https://drive.google.com/file/d/1gZvc2RjCUpdjX7OdXYhhlOy8l4HcgJVH/view?usp=sharing | J12: https://drive.google.com/file/d/1Bys03pXXta8r06ZrjIaK_LRnYds5NmbU/view?usp=sharing | K12: https://drive.google.com/file/d/1aAqnyne7ZBPK5V19WDWxwej0ijXnV_VZ/view?usp=sharing | L12: The Girl gives the flowers to her grandmother. | M12: https://drive.google.com/file/d/16a_eRctYtWRcBG3G9W0idpzo-18k8dEF/view?usp=sharing | O12: https://drive.google.com/file/d/1_hlIm5yeAhKRLIvM5hJ4OSmlYrnX1Vw-/view?usp=sharing | P12: Wow! He is giving me a really big present! | Q12: https://drive.google.com/file/d/18mBDBoB_Pz0WY30Fnyq8LmGJGbU4q2yN/view?usp=sharing | S12: https://drive.google.com/file/d/17CPrVPVFy9e__myXEkrwz4qdDDQY54go/view?usp=sharing
A13: 1 | B13: 1 | C13: Actions 3 | D13: put | E13: https://drive.google.com/file/d/1sm-GdlKB0vJGLaLdNbQEjCUCAYL03jYk/view?usp=sharing | F13: https://drive.google.com/file/d/1Vo4bcX0O8LkO2J1BaMFpXtEpRX_23hkI/view?usp=sharing | G13: https://drive.google.com/file/d/1s64cktVXMcGpWmMJRx_c45HrrCZVlOkV/view?usp=sharing | H13: https://drive.google.com/file/d/1-SfERAP39aQMt9qmSUrzdUCAUSLZ8W6N/view?usp=sharing | I13: https://drive.google.com/file/d/1MjqysMQf9c6kRkzKuWGogCs1GJVGiUB1/view?usp=sharing | J13: https://drive.google.com/file/d/1CnM9fL9RupdLN7Y1OhMc4gnqBZ5QJJhU/view?usp=sharing | K13: https://drive.google.com/file/d/1sp2VEe2D_mOXebVcJv3JsvHpDVaX7_cE/view?usp=sharing | L13: The baby is putting toys into a white box. | M13: https://drive.google.com/file/d/1yzj4ius9meFK7fPS-gSNi35T4p2bI98r/view?usp=sharing | O13: https://drive.google.com/file/d/1ha3OUtwttQlCmZzezhW74aW_uApEFiI_/view?usp=sharing | P13: The man is putting the baby in a crib. | Q13: https://drive.google.com/file/d/11rRUCryucUygvQqUl-439fADWxCz3Gka/view?usp=sharing | S13: https://drive.google.com/file/d/1OU0qc5ax5T9xtLEEwT_fB_9HpTjCTCEO/view?usp=sharing
A14: 1 | B14: 1 | C14: Actions 5 | D14: smile | E14: https://drive.google.com/file/d/19RJNvzdDQOc-XZSwSonJVX0NmSOUtI8E/view?usp=sharing | F14: https://drive.google.com/file/d/1azRhSzAPv3sj94RurKt7MTaj9atVCCNc/view?usp=sharing | G14: https://drive.google.com/file/d/1UFW4sh_BV9QVi37MMUJW38dU7tEl7mqh/view?usp=drive_link | H14: https://drive.google.com/file/d/1zbvMa55T3QAFZB_O52Zv_CIIhUq8NaSl/view?usp=sharing | I14: https://drive.google.com/file/d/1D0wgNJb1jQdqGUTj1h2WElZb_d4979nn/view?usp=sharing | J14: https://drive.google.com/file/d/1bmBMXHehYau1Cg_1X4Al0SiND1fmtMID/view?usp=sharing | K14: https://drive.google.com/file/d/1SCoTrHqc1ZOduLYIdQrk5QnJEQoG56kE/view?usp=sharing | L14: They are smiling. | M14: https://drive.google.com/file/d/1d8Zvdz4rrSrt4VW3fOu8ITO80-Z0VZKK/view?usp=sharing | O14: https://drive.google.com/file/d/1QcAk6hKSdgpYDCRJlspgp8qudJgr0MQ1/view?usp=sharing | P14: Let's all smile and I will take a picture! | Q14: https://drive.google.com/file/d/1WrlbHuXPbeNfFQsgJ0INN3EJBnG_5RgP/view?usp=sharing | S14: https://drive.google.com/file/d/1v2iXFNMmLehLISVfgJWNqI0DUN9n3u7V/view?usp=sharing
A15: 1 | B15: 1 | C15: Actions 5 | D15: cry | E15: https://drive.google.com/file/d/1NBAErn4UFjGfIML5yHn8RIR6XpwHUNN0/view?usp=sharing | F15: https://drive.google.com/file/d/15h-5YtVJhG8RhmgBBVC84LROdWi0tOC7/view?usp=sharing | G15: https://drive.google.com/file/d/1rcWkypwX5TJZJEqBCquHBcriLyNWaDcS/view?usp=sharing | H15: https://drive.google.com/file/d/1rWfvOb0OfmAMFRhZY9Wb4iYn2gpTtmiz/view?usp=sharing | I15: https://drive.google.com/file/d/1NlHDexMq4j7UTMg2vF1kvqdqXv_ej_IC/view | J15: https://drive.google.com/file/d/1f0elEtPQrNA64mYztdT_-8ASSfVzhLqU/view?usp=sharing | K15: https://drive.google.com/file/d/1Xv7FXnwNZAEwDMu-gRFFIj30gQIyeFuK/view?usp=sharing | L15: Oh, the little baby is crying. | M15: https://drive.google.com/file/d/1wQ18xNXKpol3J3oRf1FHgBHHsBpITwdh/view?usp=sharing | O15: https://drive.google.com/file/d/1O0wz-GoKVM0al2gW66oSXIeb8Y36Z4TS/view?usp=sharing | P15: Oh baby Girl! Don't cry, please. | Q15: https://drive.google.com/file/d/1p0_vr4Lvxq0-Gde_3-NglRappKHiihhO/view?usp=sharing | S15: https://drive.google.com/file/d/11R8Qryoh4BxKFsiR1smG-Jh0ikZnJDOU/view?usp=sharing
A16: 1 | B16: 1 | C16: Actions 5 | D16: sleep | E16: https://drive.google.com/file/d/1UK0PaJ7iBnZ9gCmx9bNlU74k5Bgt9FwR/view?usp=sharing | F16: https://drive.google.com/file/d/1LcTsS9BTAVkveaEcVixkKfLVf13XKZmB/view?usp=sharing | G16: https://drive.google.com/file/d/178m4seavW-c4c_CSxOgvvtk4QZLqs1Tq/view?usp=sharing | H16: https://drive.google.com/file/d/1oeJ96sio848QkjLjzwHxD6RH1Qp29Q0P/view?usp=sharing | I16: https://drive.google.com/file/d/1Vldqu9SBnsk8jsWGR1IyiYx202qA7vHj/view?usp=sharing | J16: https://drive.google.com/file/d/1BhLilCnLSkRZA-mX46O4FYhxE8-20nXt/view?usp=sharing | K16: https://drive.google.com/file/d/1rdKBJbOxXY9jSeO_u057UXRtOKG9BSid/view?usp=sharing | L16: The baby sleeps in the crib. | M16: https://drive.google.com/file/d/1Kebb5Qwt0pjJB0ksBBNA-uYhQqzVKBIz/view?usp=sharing | O16: https://drive.google.com/file/d/1hjeQLoLKeIJepQNQVuvLROFB-UTKqqU8/view?usp=sharing | P16: The boy likes to sleep in his grandparents' arms. | Q16: https://drive.google.com/file/d/1CP7LoOIVAPLF4UQ_41uYUk9zTaOHoSzv/view?usp=sharing | S16: https://drive.google.com/file/d/17y05AraXul8Z7Z55kejFNotP-BLScmGr/view?usp=sharing
A17: 1 | B17: 1 | C17: Actions 5 | D17: take | E17: https://drive.google.com/file/d/12flbQO1PoTmHfhRVbmtSiN1BuzROoWAW/view?usp=sharing | F17: https://drive.google.com/file/d/1t30DI_8Q3l8yA0-Cznst3LGT_P7UHB_8/view?usp=sharing | G17: https://drive.google.com/file/d/1DjhYjCeczI4pSc8da_6Re422PpkQD5l2/view?usp=sharing | H17: https://drive.google.com/file/d/1k3OOw6gMBz_pYkqHR4snInYgN8R6TbL5/view?usp=sharing | I17: https://drive.google.com/file/d/1SuD5BtjpCMm2VsDEaRhc_EjU7xBzdoyM/view?usp=sharing | J17: https://drive.google.com/file/d/1NbFOkFuyJ7WhcrTvDGnLzpXyjz8I0u-Z/view?usp=sharing | K17: https://drive.google.com/file/d/1PBGXj54zl4uXddx8wUWcsVLdZS_FXluE/view?usp=sharing | L17: The boy takes a cookie. | M17: https://drive.google.com/file/d/1GeJLPe43F6EMopoBT-TRX88_xZ-JEOvd/view?usp=sharing | O17: https://drive.google.com/file/d/10sF8E-koEikPYZ7sQ-zeHGIF7dOjb8f3/view?usp=sharing | P17: Please take your order! | Q17: https://drive.google.com/file/d/1KjKNXvP2g4mOsH9Ld2084Cm9h58oDEvz/view?usp=sharing | S17: https://drive.google.com/file/d/1OluYVWkOUnZouEz4Z6F-OWox6r-dG-cZ/view?usp=sharing
A18: 1 | B18: 1 | C18: SW 1 | D18: the | E18: https://drive.google.com/file/d/1CYGOKeZCyQkCYyPe6w1-cSYPWsZDx90D/view?usp=sharing | F18: https://drive.google.com/file/d/1dFeFp8cYbRuL_qRmSrl6erBPIIsZqKeH/view?usp=sharing
A19: 1 | B19: 1 | C19: SW 2 | D19: of | E19: https://drive.google.com/file/d/1QiyORrmC4WNyVwld1qDcoLxbq9ON6YCs/view?usp=sharing | F19: https://drive.google.com/file/d/1Ug_Hi2cBT1PgBt-Q-ffrUmafburYPGRf/view?usp=sharing
A20: 1 | B20: 1 | C20: SW 3 | D20: and | E20: https://drive.google.com/file/d/1wb5uoUBlqjro9y1CIDaNS74AwYMa9Feo/view?usp=sharing | F20: https://drive.google.com/file/d/14PvUo1_m0qH71v8gXbt21pRp7lMASiWh/view?usp=sharing
A21: 1 | B21: 1 | C21: SW 4 | D21: a | E21: https://drive.google.com/file/d/1-za6PmuKSS1QBPgU6gN-n29CT9-tHfBr/view?usp=sharing | F21: https://drive.google.com/file/d/1iFLASAGlA0yx464yuT0r5cycBkwf8btP/view?usp=sharing
A22: 1 | B22: 1 | C22: SW 5 | D22: to | E22: https://drive.google.com/file/d/1LfgEaBnnE8XRCV02mmEAvoY_-4ZjzpHR/view?usp=sharing | F22: https://drive.google.com/file/d/1iLzMm09BHHpNFpwULSVz-IUPTcoxZ6Ds/view?usp=sharing
A23: 1 | B23: 1 | C23: SW 6 | D23: in | E23: https://drive.google.com/file/d/1bLV_goSnCjG214E3P2z8D4ZIAFRWmuVE/view?usp=drive_link | F23: https://drive.google.com/file/d/1Myjg3kViXwvI24MVpAGHLkLtIlP0gysl/view?usp=sharing
A24: 1 | B24: 1 | C24: SW 7 | D24: you | E24: https://drive.google.com/file/d/15aG1kXIYQa0_fMO8qCyuBQCQYEjao5Pn/view?usp=sharing | F24: https://drive.google.com/file/d/1euI_WGyeAv7c5hdiUw9F_vRm4W2b_Uo-/view?usp=sharing
A25: 1 | B25: 1 | C25: SW 8 | D25: this | E25: https://drive.google.com/file/d/1h0P_A7yEKswT8niY0N-xbDnIpBnoMweG/view?usp=sharing | F25: https://drive.google.com/file/d/1Dk-8bBkPlfvW3ujvNhHZNngrqt43v7XR/view?usp=sharing
A26: 1 | B26: 1 | C26: SW 9 | D26: it | E26: https://drive.google.com/file/d/17wblMFDcQudjFGxG906zYzWycFXmOSOT/view?usp=sharing | F26: https://drive.google.com/file/d/1xdBeVfI651MMCQhGeBzQL8e-f97YPBSg/view?usp=sharing
A27: 1 | B27: 1 | C27: SW 10 | D27: can | E27: https://drive.google.com/file/d/1X97JefUelxPt6cVXf9u4Y0J2RVCxQfEy/view?usp=sharing | F27: https://drive.google.com/file/d/1t6FlvWYYkB2vWdE8lH80eBVPwtY5LDrt/view?usp=sharing
A28: 1 | B28: 1 | C28: SW 11 | D28: he | E28: https://drive.google.com/file/d/1v8bsXxJ83cKF_aP90gBUh6QVkun9GAjh/view?usp=sharing | F28: https://drive.google.com/file/d/1fxgXC_3kSbATvT9MeycRNG68aLOlrYju/view?usp=sharing
A29: 1 | B29: 1 | C29: SW 12 | D29: one | E29: https://drive.google.com/file/d/1_NA8wxVj_-Y_F0EhUwkUgGl6NDR8LZQg/view?usp=sharing | F29: https://drive.google.com/file/d/1G_fEkh_cDSFcV6LQ8GAwrf7eSFVQM6Zs/view?usp=sharing
A30: 2 | B30: 1 | C30: Transportation 1 | D30: bus | E30: https://drive.google.com/file/d/1JMYMKfcUS5Bypa8u7MnmMct86STzfOWH/view?usp=sharing | F30: https://drive.google.com/file/d/1YPD3cE9VCA3p10UKDNxxMHvtJ7GUnIUo/view?usp=sharing | G30: https://drive.google.com/file/d/16SOHCQwghO0uYQDKE3mCW-YCn6n8VsIl/view?usp=sharing | H30: https://drive.google.com/file/d/1U7HAiP1z0UodrT9uzpSM98FlNkMidD-3/view?usp=sharing | I30: https://drive.google.com/file/d/1LivxffnkGFwZRAVfMHb2TmTERahZ-yLx/view?usp=sharing | J30: https://drive.google.com/file/d/14JGTcFbZVljG-KOTJxTw3eezM8-VTbPF/view?usp=sharing | K30: https://drive.google.com/file/d/1IWFpVf0HQ8dF2sq05Rpe57Cj4D45tIjL/view?usp=sharing | L30: Look at that! A blue bus. | M30: https://drive.google.com/file/d/1XzZFc6IV80hfbhIQQERL7OqBaLGvUe-G/view?usp=sharing | O30: https://drive.google.com/file/d/1OIOKbqTrnsPJD02WcDTBCmDXxqd0pEGe/view?usp=sharing | P30: Here we go! Let's get on the bus. | Q30: https://drive.google.com/file/d/1QLqcvTuxdy5FMKi5oCY71JN7Hw-MJuYY/view?usp=sharing | S30: https://drive.google.com/file/d/1By6kBB0MjySn8nx-Po4mlQGPTrC7XUxo/view?usp=sharing | T30: https://vnmedia2.monkeyuni.net/upload/cms_platform/audio/76040ad3d753a2187c216538efc82461.mp3
A31: 2 | B31: 1 | C31: Transportation 1 | D31: car | E31: https://drive.google.com/file/d/1HHZZ4od-wUQrEDMPhrqPaUW05myGZoKR/view?usp=sharing | F31: https://drive.google.com/file/d/12I4ghv06zuQ5bwdzMwy2r3zHzMbL2_Et/view?usp=sharing | G31: https://drive.google.com/file/d/1eue3QM8gToJGC0EJAlz4x4g2Ld-2Zw6m/view?usp=sharing | H31: https://drive.google.com/file/d/15meZ3Id8RY6ZUHubqrOrpoO18Cxb0vb2/view?usp=sharing | I31: https://drive.google.com/file/d/1bfVdVdOwAIzZVKE-3h8hpzly-WTbYeoR/view?usp=sharing | J31: https://drive.google.com/file/d/1vjssI3fMg4okWjp74U06OTZWlWr5La2j/view?usp=sharing | K31: https://drive.google.com/file/d/1NwzjRSOHGoA0klI3_QmCRzmapipVs8QG/view?usp=sharing | L31: Oh! So many cars. | M31: https://drive.google.com/file/d/1Un-7aNAlgPx6gkDZjhaXhcoDQhLQ-0dg/view?usp=sharing | O31: https://drive.google.com/file/d/15dpGwsQgrOXcswLmjxMG_uffqWrZ_BZF/view?usp=sharing | P31: The man is cleaning the black car. | Q31: https://drive.google.com/file/d/1TONhXr_KkBYu9sGnuQ4_s3QZpqcNp4mO/view?usp=sharing | S31: https://drive.google.com/file/d/1QDRLEKNcWw08gca9W0RQRndt90d2WdJW/view?usp=sharing | T31: https://vnmedia2.monkeyuni.net/upload/cms_platform/audio/c60db4ed8ef63e162ddc06c935167bfe.mp3
A32: 2 | B32: 1 | C32: Transportation 1 | D32: truck | E32: https://drive.google.com/file/d/15JZBsKfBZ7OAkasZF3eQbm_toWsxlR86/view?usp=sharing | F32: https://drive.google.com/file/d/1VqewG28DFP9y4OzbTQ3PpuCHYlJgQeII/view?usp=sharing | G32: https://drive.google.com/file/d/1vUlMqJXTex98v3iETU-vplQmTd7Ff_rK/view?usp=sharing | H32: https://drive.google.com/file/d/13HPALXNymk8a9_4rxNcoGTUje8SNAMGZ/view?usp=sharing | I32: https://drive.google.com/file/d/1tMHrWb5tEqKbhtpnS1wpfSq9jTFnz_Rn/view?usp=sharing | J32: https://drive.google.com/file/d/1G0vGacJfZglFYQDd3Ocfdu13PLKVO-b3/view?usp=sharing | K32: https://drive.google.com/file/d/1BZ5HP9r3HggvbKX3CnEUElA181C5lExe/view?usp=sharing | L32: There are many trucks on the road. | M32: https://drive.google.com/file/d/13BVNVReS3xMyBdw6vn_aiTnv72KCldBc/view?usp=sharing | O32: https://drive.google.com/file/d/1QZ-7Sog4uNuJxQ6NhsE5eWnqJcxXNI-A/view?usp=sharing | P32: What a long red truck! | Q32: https://drive.google.com/file/d/1ZQG388Ei_9aPZEBk7b1UqP1LhV2pWT7w/view?usp=sharing | S32: https://drive.google.com/file/d/1u2iJ9oAdnXwiLSvX6IkpsoPYkEVUXfOv/view?usp=sharing | T32: https://vnmedia2.monkeyuni.net/upload/cms_platform/audio/3a5c93f0d1326a6286c969c2b89903f4.mp3
A33: 2 | B33: 1 | C33: Transportation 1 | D33: van | E33: https://drive.google.com/file/d/1ZzWW1QhTGuJuFrlCwdSDNuDEnVZEXwZD/view?usp=sharing | F33: https://drive.google.com/file/d/1-omAvrUkYMRxvDHUP2dnOEy972zbML39/view?usp=sharing | G33: https://drive.google.com/file/d/1REVmXi0l5n7nkiI5xSlui70oTQbQUn3T/view?usp=sharing | H33: https://drive.google.com/file/d/16oj3oAKNEZwNv9hqwGaEtaIJ71IQh6fA/view?usp=sharing | I33: https://drive.google.com/file/d/13AZG5uF7s-7vFCCO_mcRyoY4Sl9fvNQn/view?usp=sharing | J33: https://drive.google.com/file/d/1_1h3V5Sg9seR5VtjeorGXRCk7nxQmmfO/view?usp=sharing | K33: https://drive.google.com/file/d/1d95tGrMbtXyDDHa7I7zeJc4_giDHP-4s/view?usp=sharing | L33: The van is driving through the city. | M33: https://drive.google.com/file/d/1lkRlGs8HPQAY2udwEIPf_Qe3YM6ut2B6/view?usp=sharing | O33: https://drive.google.com/file/d/1DHBwupfGf3OVoYqwdY9pq7b68PUp4upY/view?usp=sharing | P33: There are many vans here! | Q33: https://drive.google.com/file/d/1iLfBz6U4awNNZGnNAkpsHK3siESnu91F/view?usp=sharing | S33: https://drive.google.com/file/d/1w-p2iM2RSsfYfrntJU1JIyYiF70xNhgl/view?usp=sharing | T33: https://vnmedia2.monkeyuni.net/upload/cms_platform/audio/6e48a9d614f00717aaf3a4bd19d3d825.mp3
A34: 2 | B34: 1 | C34: Transportation 2 | D34: train | E34: https://drive.google.com/file/d/1gFlkOtIgDthbYf_OeiG2WPhiY-JL1zbq/view?usp=sharing | F34: https://drive.google.com/file/d/1p0BFU8yswmom7eClLR_vcXEd3wY3osWG/view?usp=sharing | G34: https://drive.google.com/file/d/1fO6WH3Qx2CFo_1AyKEPrFfuJqaxne2gJ/view?usp=sharing | H34: https://drive.google.com/file/d/10_N9-nUUULoglOkcZuxm3Ikckd9qkcI4/view?usp=sharing | I34: https://drive.google.com/file/d/1WdeW8jGDb5MNygvBggpmnSW6ehe6vNgo/view?usp=sharing | J34: https://drive.google.com/file/d/1xDIPqlUxoBa6yS8zDGoRkdAh0LB19SKL/view?usp=sharing | K34: https://drive.google.com/file/d/16IoNdu8u82d_1yVHO5pO3v7EbSZAUEor/view?usp=sharing | L34: Have you ever traveled by train? | M34: https://drive.google.com/file/d/1hIEvtAxtcq2vVBGeuas9nQhnmBilW5Ya/view?usp=sharing | O34: https://drive.google.com/file/d/1Q_Aogec17gwChkzxi7iK4Wjq4hS2fanq/view?usp=sharing | P34: Can you guess where the red train is going? | Q34: https://drive.google.com/file/d/1zbCSEQ_69wlC70mxNywl1sPazC4YZAJL/view?usp=sharing | S34: https://drive.google.com/file/d/1ur1U_dXArIrYnrAoDYWHw_fzhL00rf16/view?usp=sharing | T34: https://vnmedia2.monkeyuni.net/upload/cms_platform/audio/7e48ffafe52e39ae602152ff19c10e9e.mp3
A35: 2 | B35: 1 | C35: Transportation 2 | D35: plane | E35: https://drive.google.com/file/d/1mXeM_PHtPBF9QBmN7k_Ia3v-72dNOUHk/view?usp=sharing | F35: https://drive.google.com/file/d/1XIGw94kp9sUbBNjRVw-T6KUCJq0JC2zs/view?usp=sharing | G35: https://drive.google.com/file/d/1v1VFs_YhSzFTD2wQICxN6fvYlx1WNIwj/view?usp=sharing | H35: https://drive.google.com/file/d/1STpLqBKVwJ5Nkbcc3IpPOcHsNBIF7BVM/view?usp=sharing | I35: https://drive.google.com/file/d/19WHdn9nV6MFJDXEeu-4QluQ_gUtL9wfl/view?usp=sharing | J35: https://drive.google.com/file/d/1Nn5hbbulrEiD_snAuxxaZgFdQJp43wxJ/view?usp=sharing | K35: https://drive.google.com/file/d/1QHml8lRDDev8qxg97Vul96Iq--6mrm3a/view?usp=sharing | L35: The plane is at the airport. | M35: https://drive.google.com/file/d/1MYQhsBL7Ft55BPiyYw3OJCgznEPwu7kU/view?usp=sharing | O35: https://drive.google.com/file/d/1XiJWB2Fg-KKjEOU9_VCZVtRiZm90Iizp/view?usp=sharing | P35: The plane is flying over the tall buildings. | Q35: https://drive.google.com/file/d/1JfHwqUCmr61i48myLVL-dfpkWFpA7bZe/view?usp=sharing | S35: https://drive.google.com/file/d/17cYGvo4UcyMHpg3N_Dal12DCVHBfpmhu/view?usp=sharing | T35: https://vnmedia2.monkeyuni.net/upload/cms_platform/audio/a77964aeb433ce8781048f5901b4dc7d.mp3
A36: 2 | B36: 1 | C36: Transportation 2 | D36: boat | E36: https://drive.google.com/file/d/1eObnUD16WkMqoIeOJIMgHEVdX0rBOGDg/view?usp=sharing | F36: https://drive.google.com/file/d/18qOyolIVfnn4ztF7ewAG_FHTk-K-sFUQ/view?usp=sharing | G36: https://drive.google.com/file/d/1-symrGiEOjyHhykuXigh9dwVeV5lbSS8/view?usp=sharing | H36: https://drive.google.com/file/d/1Mh6BS8oWU1DA5n3sbUvnTaA12J5lrk5r/view?usp=sharing | I36: https://drive.google.com/file/d/1yC--BIo-198uxY58iSqJPFNv7B8Bd0ga/view?usp=sharing | J36: https://drive.google.com/file/d/18IDFMjYkMAHJn2GUL_yYu8DxUL2OGA8W/view?usp=sharing | K36: https://drive.google.com/file/d/11Nfq0fyHGm46-58Umt2hHzdkqfCMywEy/view?usp=sharing | L36: What color is the boat? | M36: https://drive.google.com/file/d/1_qw6QH2j0ikULY1UkoVLhRh7gF38A53I/view?usp=sharing | O36: https://drive.google.com/file/d/1LtMxm-fWoT_0J7qsVMuj6Db8wvFcQl4N/view?usp=sharing | P36: Do you want to row the boat on the lake? | Q36: https://drive.google.com/file/d/1QHUPthqjOBYn-mmkIo-CDPBVNBSB3rp3/view?usp=sharing | S36: https://drive.google.com/file/d/1qvf6S8vG2z1eR6xkwysJbpc3r0U1GBhS/view?usp=sharing
A37: 2 | B37: 1 | C37: Transportation 2 | D37: ship | E37: https://drive.google.com/file/d/1aObuLx7YAtfpEo1QIdRzZO1heynnMubF/view?usp=sharing | F37: https://drive.google.com/file/d/1_nHrn40-ht7cwubJnFVSSTdurlUsik9W/view?usp=sharing | G37: https://drive.google.com/file/d/1f7bbVhXowVXXHx_Le9yKnKXWnxs3GA9r/view?usp=sharing | H37: https://drive.google.com/file/d/1T7afumfnBc6BMuChU1hYbZrXcsudXH9w/view?usp=sharing | I37: https://drive.google.com/file/d/10ZZFkYYOplId2NzKpKFRE8X0iH1cjYUk/view?usp=sharing | J37: https://drive.google.com/file/d/1vWzqyX943yC6fbwCRc2RhHl7W9wa79o4/view?usp=sharing | K37: https://drive.google.com/file/d/1Xc0U3Kcwo9xnqgdG53wxPD0WGmeZ4lV0/view?usp=sharing | L37: Oh, wow! That ship is so big! | M37: https://drive.google.com/file/d/1eViA-V1vIYoXhGT4G20SuqRXPlxmI_yI/view?usp=sharing | O37: https://drive.google.com/file/d/14C_MYrOBNiijRftB8kF_ZknO6PJWPwQT/view?usp=sharing | P37: Is this ship big? | Q37: https://drive.google.com/file/d/1DJDPktIs9YSWs_jEHJAO2I3EXr1jeaSl/view?usp=sharing | S37: https://drive.google.com/file/d/1-7AveppQukyKIeGduyOZfXQNDeUUrQON/view?usp=sharing | T37: https://vnmedia2.monkeyuni.net/upload/cms_platform/audio/c81e11638b81a69a0c70692230e25414.mp3
A38: 2 | B38: 1 | C38: Toys 1 | D38: dice | E38: https://drive.google.com/file/d/1mUHx_m8oxHWyVUuqj5c6IZfuK5ionwtl/view?usp=drive_link | F38: https://drive.google.com/file/d/1QUMs_lJMaIAV6QsgS_rbxAv-W1Xuxd5j/view?usp=sharing | G38: https://drive.google.com/file/d/1uuIVFZgMk2E6Du8xq4a_AKkA2rxhmXml/view?usp=sharing | H38: https://drive.google.com/file/d/1YgxEuLDVIC5bsiaNu4KiRplLwrXGn1m2/view?usp=sharing | I38: https://drive.google.com/file/d/16_bUDUwnFQmLR3E194amB6UKbInmRWki/view?usp=sharing | L38: Let's throw the dice. | M38: https://drive.google.com/file/d/1GtAlq7y-HZQljWaIguwQs91UyUQT7QMI/view?usp=sharing | N38: https://drive.google.com/file/d/1Qftq_y-r9GlwapjMywAgM912QdvY0wg-/view?usp=sharing | P38: Do you want to roll the dice? | Q38: https://drive.google.com/file/d/1jgVeBmoMZfHpwaS_OtI4_Cik3fn8hPyI/view?usp=sharing | R38: https://drive.google.com/file/d/1htM6QATEvUqQlKpbFJ-MXK4d35TFvuSG/view?usp=sharing
A39: 2 | B39: 1 | C39: Toys 1 | D39: crayon | E39: https://drive.google.com/file/d/1vCqXSvSDZhaSvwtsQ__cQ_7nikueuhRc/view?usp=sharing | F39: https://drive.google.com/file/d/12pxNFra42qeEx_nmfqLSLr9bOZ96OMpV/view?usp=drive_link | G39: https://drive.google.com/file/d/1iQuvg6PECyJUN2U_Mttoi1YkYViEpUS8/view?usp=sharing | H39: https://drive.google.com/file/d/1mUgwpBJvyzRZGgk2oA2U8MWgZxqwrtD2/view?usp=sharing | I39: https://drive.google.com/file/d/18epUpk7m_rPO5xH_ObHrbRPZwqJCJsI_/view?usp=sharing | L39: I can draw the sun with my crayon! | M39: https://drive.google.com/file/d/1A0Xjrqmen7N1GDIypwcQVm7PKMtfv78O/view?usp=sharing | N39: https://drive.google.com/file/d/1jSDGTuWAQm3yrcozXzIwexLvAjQBWT-7/view?usp=sharing | P39: The Girls have many colorful crayons. | Q39: https://drive.google.com/file/d/1_JSec_-Ejo24J0erLhvbaSK_29728FtV/view?usp=sharing | R39: https://drive.google.com/file/d/1w6yycK5LIc8f8ocTaUgQnvHymTR7Gsku/view?usp=sharing
A40: 2 | B40: 1 | C40: Toys 1 | D40: puzzle | E40: https://drive.google.com/file/d/1j5s-IH-9ZpGjcsyvP9GoHdZzsf5_CW-o/view?usp=sharing | F40: https://drive.google.com/file/d/1o9O_AiCD-OSOmJeMLIh0gL3mIaMGEdq6/view?usp=sharing | G40: https://drive.google.com/file/d/1-0ot7KF1x1Be9N03RUuwTxBxdU1m4eO-/view?usp=sharing | H40: https://drive.google.com/file/d/1oPWNITpr8U8e_gfI26ulZEUYt0O8Kfrh/view?usp=sharing | I40: https://drive.google.com/file/d/1FLbBOPh_7CMrYTV7XYuyCgtwcR-AXGbN/view?usp=sharing | L40: Can you do the puzzle? | M40: https://drive.google.com/file/d/1pkeU24bDRRLK7f4CP5CkEvIno-UnAsHJ/view?usp=sharing | N40: https://drive.google.com/file/d/1IKoFpfkPTY5v8dwSLUtpBVkHGj7RWxkD/view?usp=sharing | P40: Mark solved the puzzle. | Q40: https://drive.google.com/file/d/1k_VWqxMWWhuz57rGWfcpZqQ4rHVMQEtt/view?usp=sharing | R40: https://drive.google.com/file/d/1zSmtQ-BWTNQhx124bNzjqKyUoaMiU1dX/view?usp=sharing
A41: 2 | B41: 1 | C41: Toys 1 | D41: puppet | E41: https://drive.google.com/file/d/1y_y4DEelbQTUXWkpA5d4ve39w5i3Rcjk/view?usp=sharing | F41: https://drive.google.com/file/d/1bo6apGU3SoiTYGMAtr-F14UPd0enWh0z/view?usp=sharing | G41: https://drive.google.com/file/d/1TpXR2QtrZfDnr4HVpHZFVrDH54mQnGqV/view?usp=sharing | H41: https://drive.google.com/file/d/1IlhPIUu6DNbLZTDLpxmxoZ2jLqHa60WR/view?usp=sharing | I41: https://drive.google.com/file/d/14CqhcetqeuLxdAXijxKeGkevuj8cCp0M/view?usp=sharing | L41: Hello! I'm playing with puppets. | M41: https://drive.google.com/file/d/12vT-uI38qNxLKsbRxc7ivz5_hJifcaEo/view?usp=sharing | N41: https://drive.google.com/file/d/1PNI1NJnscIOQQwBbOgtJsbnbNsEOi0hd/view?usp=sharing | P41: Do you know how to play with puppets? Watch me! | Q41: https://drive.google.com/file/d/1DWQ2DQueRAxhRDtOnlSl3_mkkSsY-JgT/view?usp=sharing | R41: https://drive.google.com/file/d/190HsHLguDP_8HmSq0EvepmpJF0ov1q3c/view?usp=sharing
A42: 2 | B42: 1 | C42: Toys 2 | D42: doll | E42: https://drive.google.com/file/d/1LO2g9CTUO1sljUW6sloFfc-dfVKgykkG/view?usp=sharing | F42: https://drive.google.com/file/d/1jmbcKuJbhjBu2eS-sStO_bX1MN_Qt9zQ/view?usp=sharing | G42: https://drive.google.com/file/d/1poJXyhUv20xg8FWjWhU2eq2yUKJEhNvY/view?usp=drive_link | H42: https://drive.google.com/file/d/1361FKiAqOpGLFnjXnYt56EYagh6AVg80/view?usp=sharing | I42: https://drive.google.com/file/d/1NNrGBhrBqWGWwEIoWbP-hG0w12ZIWeC9/view?usp=sharing | L42: Yay! I got a new doll and I'm so happy. | M42: https://drive.google.com/file/d/1bPbDW6VGp7nkA8gAdi41u4LxtMLn40hv/view?usp=sharing | N42: https://drive.google.com/file/d/1omOyVncEzwxr0RahKZEpXLxzqpRAVeK7/view?usp=sharing | P42: Do you like playing with dolls? | Q42: https://drive.google.com/file/d/1d68A6NBgu5MaIY2jmSE_E1YhJ29h9QAj/view?usp=sharing | R42: https://drive.google.com/file/d/1_IisOdJrTfc-iLB5KZrM4i-_R6o48Wzg/view?usp=sharing
A43: 2 | B43: 1 | C43: Toys 2 | D43: ball | E43: https://drive.google.com/file/d/1muqgMeaH5uC7RS-gwW-ElFTtZYwiocJf/view?usp=sharing | F43: https://drive.google.com/file/d/1FRdVaBWssyS-cFnOBsTZAHcmNUTauTUx/view?usp=sharing | G43: https://drive.google.com/file/d/1JCH68ZSR8vJmifOz0MwBcstk-4a3Zh3w/view?usp=sharing | H43: https://drive.google.com/file/d/1CRpMTZKMQnOHvvqsp3qQdwbzIRHE7fOr/view?usp=sharing | I43: https://drive.google.com/file/d/11saVuF1z9ypuGlHdrt_qZq0VZR_-dtfO/view?usp=sharing | L43: The boy is kicking the ball in the field. | M43: https://drive.google.com/file/d/1bm4ycMs_ZMmCu2q72UMyLyf4rFQ-5Z3G/view?usp=sharing | N43: https://drive.google.com/file/d/1FR17pfzya8yEcbW7TAM4EPcPDkcz_ovS/view?usp=sharing | P43: Can she catch the ball? | Q43: https://drive.google.com/file/d/1ec_QDi4Tz-59hSXw1sjibbrOFptpO2Lm/view?usp=sharing | R43: https://drive.google.com/file/d/1wYt5w2pVcnaSz4RyZKzqur2WaKd4HRrc/view?usp=sharing
A44: 2 | B44: 1 | C44: Toys 2 | D44: bubbles | E44: https://drive.google.com/file/d/1nQTTaqpCDwM6ON994f6YtUiai_Ya881P/view?usp=drive_link | F44: https://drive.google.com/file/d/1DIdNlIBF74EMmoN42qSf0_PFOrL5Ssre/view?usp=drive_link | G44: https://drive.google.com/file/d/1dG6XQceoCHHZhaj-kMWRewGLG9MVwdir/view?usp=sharing | H44: https://drive.google.com/file/d/1zvfMTpmGfl6Wcez6CE6FcynvBc7uWkfE/view?usp=sharing | I44: https://drive.google.com/file/d/1Ik5ULMWZlFIvzLt0OOE4AI6HW6kcbk4k/view?usp=sharing | L44: Oh! There are many bubbles! | M44: https://drive.google.com/file/d/1Kx6R6AZXKMkQpK33f5OrK9lvIuy6C8KC/view?usp=sharing | N44: https://drive.google.com/file/d/16qxAszaDCN-CYSgBIFnKmetmxahuzWEL/view?usp=sharing | P44: I love bubbles! | Q44: https://drive.google.com/file/d/1cUZqQzOS4K3f7J11ZtSAMx8Fk0j_0nxw/view?usp=sharing | R44: https://drive.google.com/file/d/1F5csFFAKIpS1_eWlHNbzxZaruRs9aCBw/view?usp=sharing
A45: 2 | B45: 1 | C45: Toys 2 | D45: toy blocks | E45: https://drive.google.com/file/d/1_zavwvMGwyZfuYh7WJWbKa2nWoNTjhbx/view?usp=sharing | F45: https://drive.google.com/file/d/18C7SGVwHt-esETBNMqP7G_m72lZjr61o/view?usp=sharing | G45: https://drive.google.com/file/d/1n1AtuPYe-PYGyh6_o3Q21PKFLlRA1Itg/view?usp=sharing | H45: https://drive.google.com/file/d/1xvYl61Cou-WWxdH8wyxyUgDRAjeN-d21/view?usp=sharing | I45: https://drive.google.com/file/d/1y7kFU83P1NaHjWCZGA2PTiavjKF9VxWW/view?usp=sharing | L45: Come here and play toy blocks with us! | M45: https://drive.google.com/file/d/1q7t2k6kdb8EU86yvlQTOIVBIzql9ESzK/view?usp=sharing | N45: https://drive.google.com/file/d/1qP_YqSSqiGjSdvUueQbqMnmVZ_TNROeO/view?usp=sharing | P45: Do you want to build toy blocks with us? | Q45: https://drive.google.com/file/d/1CdrEWpt07VLg7hnBGdQamqAl3_p5_Nds/view?usp=sharing | R45: https://drive.google.com/file/d/13xgGh4vHKGlWHqKTH5sTmgCuY3SEyQSN/view?usp=sharing
A46: 2 | B46: 1 | C46: SW 13 | D46: for | E46: https://drive.google.com/file/d/1lON-N6gho8w85EW_2Qxj3aZ6kHEdsLQy/view?usp=sharing | F46: https://drive.google.com/file/d/1-DYatwv152MmeRVVs6itTwtfpwGWuKBr/view?usp=sharing
A47: 2 | B47: 1 | C47: SW 14 | D47: on | E47: https://drive.google.com/file/d/1nEj88x1DdWmScZZ7orM87ko5k8qevUPv/view?usp=sharing | F47: https://drive.google.com/file/d/1DspH-3LFMfVD22F02gp7nxEKIyvaXYT9/view?usp=sharing
A48: 2 | B48: 1 | C48: SW 15 | D48: are | E48: https://drive.google.com/file/d/1IFyyK0mgJWy-g70cQIHDd-3Twq7hdDuN/view?usp=sharing | F48: https://drive.google.com/file/d/1oU0bPGHH3O8GF5bksi7y_k_kZ7zrTBHZ/view?usp=sharing
A49: 2 | B49: 1 | C49: SW 16 | D49: with | E49: https://drive.google.com/file/d/1vbkEYZeV0pd9YrCDNTd8_Hhx9y9Q-LC5/view?usp=sharing | F49: https://drive.google.com/file/d/1GKhDMQFFFk9iV8no4dpif3EfnopsGqFh/view?usp=sharing
A50: 2 | B50: 1 | C50: SW 17 | D50: they | E50: https://drive.google.com/file/d/1e_OGpkkRkDf60n2lutnxv2_Asxi6_Spi/view?usp=sharing | F50: https://drive.google.com/file/d/1Zbh55gNMKNreim2qiShPEAGYCRtikPnP/view?usp=sharing
A51: 2 | B51: 1 | C51: SW 18 | D51: three | E51: https://drive.google.com/file/d/1WPQbZ2NuhmsBJbzp6MtCW0t0wyc3RJnQ/view?usp=sharing | F51: https://drive.google.com/file/d/17177dXBl4SS2nyTL4fqESRfQv3TgBgLn/view?usp=sharing
A52: 2 | B52: 1 | C52: SW 19 | D52: at | E52: https://drive.google.com/file/d/1fRZm725HzXSjL8eY-nyBMrKT7hsBXCsh/view?usp=sharing | F52: https://drive.google.com/file/d/1RTimdgFNjsLbsemXTTBBefR6a_sXI6VM/view?usp=sharing
A53: 2 | B53: 1 | C53: SW 20 | D53: be | E53: https://drive.google.com/file/d/1nKBnrj1dk7K_kql_m4jJJxF_EPC0L-vO/view?usp=sharing | F53: https://drive.google.com/file/d/1kNP5nvB0_heZcTDTJCq3Whb2dbpwETTy/view?usp=sharing
A54: 2 | B54: 1 | C54: SW 21 | D54: that | E54: https://drive.google.com/file/d/1guFYVxnPHWmTy84P5yyGbJGoqq4xiIcB/view?usp=sharing | F54: https://drive.google.com/file/d/1PmeM71DyJPNrUOJI4aH4-WDJdMR17GW9/view?usp=sharing
A55: 2 | B55: 1 | C55: SW 22 | D55: have | E55: https://drive.google.com/file/d/1LqZdGvZM-pSG4uKPTeUzrHTIqIdKLw51/view?usp=sharing | F55: https://drive.google.com/file/d/1EDQDWgkTelR_sjzqK0saT7K5CzM2NeHU/view?usp=sharing
A56: 2 | B56: 1 | C56: SW 23 | D56: from | E56: https://drive.google.com/file/d/103EG8W4ORrd5qWfWwcAWr54-j04uRrb3/view?usp=sharing | F56: https://drive.google.com/file/d/12rPFQXOL1LPXgweQPVGfhs8Q36qVztD3/view?usp=sharing
A57: 2 | B57: 1 | C57: SW 24 | D57: or | E57: https://drive.google.com/file/d/1iNsK_Nt2z1kpB5PjAjZ3QYIjbOOdvnts/view?usp=sharing | F57: https://drive.google.com/file/d/1IcRH5iJioXUSYXpbx0nkWqkyi01L1IAn/view?usp=sharing
A58: 3 | B58: 1 | C58: Actions 1 | D58: stand | E58: https://drive.google.com/file/d/1Ld0xqi0XByzvPLLYlJ5KaWjsucGR6fCD/view?usp=sharing | F58: https://drive.google.com/file/d/1Ct9YYHpTHvtg3TJLjtRch5tUeRVZo0Be/view?usp=sharing | G58: https://drive.google.com/file/d/1i42-uOjo6a2V0fgSNgaprsIz3MIomOQh/view?usp=sharing | H58: https://drive.google.com/file/d/1pnzik9gwThPpEYd9BzXjoKLq5ktOEdPI/view?usp=sharing | I58: https://drive.google.com/file/d/1z7IJTzCMvzlIpPX7FkgkXQPr_IB9bF4v/view?usp=sharing | J58: https://drive.google.com/file/d/15Dje50v91kTHPy5W6miYTBAc6tWyuGMk/view?usp=sharing | K58: https://drive.google.com/file/d/1d61VHHgXbERCPyijO2wDPSLd5NGwwPbm/view?usp=sharing | L58: The little Girl stands next to an umbrella. | M58: https://drive.google.com/file/d/1LvYpL_nUlwaY3WM7_s5gs1Oyoz4Pk9T0/view?usp=sharing | O58: https://drive.google.com/file/d/1bAGyq0uvyzcxeaIllP1FfxNLGyRUly2p/view?usp=sharing | P58: It is so relaxing to stand there. | Q58: https://drive.google.com/file/d/1Y0kzkTmAtj12qaiGGxGpnsotYolNy63y/view?usp=sharing | S58: https://drive.google.com/file/d/1Slq1XVeq8HfXECM35okmB_JrNBkWbMAW/view?usp=sharing
A59: 3 | B59: 1 | C59: Actions 1 | D59: sit | E59: https://drive.google.com/file/d/1N18-yMcZEG3WCS-kiRPi3QsM2GMQCcEO/view?usp=sharing | F59: https://drive.google.com/file/d/1gW73rO60bpPCmr_r4BYCxUjHf0gsGr46/view?usp=sharing | G59: https://drive.google.com/file/d/1WsSWIoa-8bfEhFXKKoNOiJLUHrAUa659/view?usp=sharing | H59: https://drive.google.com/file/d/110lLpeYQ7FCqddKloL4HjCpuBSbzKFmr/view?usp=sharing | I59: https://drive.google.com/file/d/1pvL6ck9MVvM-DCe4tdh3qIhgNhnQz6wi/view?usp=sharing | J59: https://drive.google.com/file/d/1nIWcN9ZwChYLg2r9lGfeUlTGeUShheDZ/view?usp=sharing | K59: https://drive.google.com/file/d/1HC-tSTHDHRzmlOwSXQqmU_ABmryNmy-T/view?usp=sharing | L59: The whole family sits at the park. | M59: https://drive.google.com/file/d/17R_mLiHTMeCCUhto-Z2VRXoi4zhxxbvU/view?usp=sharing | O59: https://drive.google.com/file/d/1uefJ8FIDK0T9KmfuGZoZbhykige2NMJK/view?usp=sharing | P59: He is sitting on a rock. | Q59: https://drive.google.com/file/d/1y2uvB9lpdcKjmgYQOmXGYNegXionvVq5/view?usp=sharing | S59: https://drive.google.com/file/d/1NiHJg4dRGvzz137BotOHYHSp7NhMDUY0/view?usp=sharing
A60: 3 | B60: 1 | C60: Actions 1 | D60: eat | E60: https://drive.google.com/file/d/11s5t_0C5ISrY01Isau3t1ankZemuE2Hm/view?usp=sharing | F60: https://drive.google.com/file/d/1W6kFfbZ0PcM_DJ9YjXeD4FJ-d3yp85hX/view?usp=sharing | G60: https://drive.google.com/file/d/1KLeUiQ7FCF8rQEDfzsDeSo_fW9FzNWRE/view?usp=sharing | H60: https://drive.google.com/file/d/1YSLwBpQTJjm0Wbhau3nNhDv6ZoHq04if/view?usp=sharing | I60: https://drive.google.com/file/d/12r8jz_A96BdIybeLeDVyhQHNEkDbNr5C/view?usp=sharing | J60: https://drive.google.com/file/d/1ifaf0oEonztRlZVXdJb2AZEJCGX0v_2r/view?usp=sharing | K60: https://drive.google.com/file/d/1X_ghgGU5tNk4BOrLqUKpQvf-Z0eWw9Nt/view?usp=sharing | L60: The little Girl enjoys eating bread. | M60: https://drive.google.com/file/d/1wmGewjHtMBc7Y_ZDHZmgjMubvyuuY1Lt/view?usp=sharing | O60: https://drive.google.com/file/d/1mlFfDNDBDdbQm1HKK3RbUQLZk_3RhNnd/view?usp=sharing | P60: Come here and eat ice cream with me! | Q60: https://drive.google.com/file/d/1Xfv2IvqpET2vGEVRf6tocJoif8dbyQVl/view?usp=sharing | S60: https://drive.google.com/file/d/1h-sZtymGMmqg-WJQUdDD47oD97AXovSx/view?usp=sharing
A61: 3 | B61: 1 | C61: Actions 1 | D61: drink | E61: https://drive.google.com/file/d/1n3WLQGPkI5PzeSOB-C_FabF44aO_VwYF/view?usp=sharing | F61: https://drive.google.com/file/d/1kVl4ic1MPgVn9fl-QOvizFhQwf5Jyjvz/view?usp=sharing | G61: https://drive.google.com/file/d/1h4fPW8Vyzi1lZG5GHV6Lc2gWSTy_xfxF/view?usp=sharing | H61: https://drive.google.com/file/d/1bS4-yepIsuveid2xx5ndrAqMqzkjgg7x/view?usp=sharing | I61: https://drive.google.com/file/d/1TXrJXLPCaqTWMFSGkJ8gp5pKTZoULVjI/view?usp=sharing | J61: https://drive.google.com/file/d/16yuBDSwUy-4u6kO7YaZJhJi76OvjPREG/view?usp=sharing | K61: https://drive.google.com/file/d/1YzlmVWBzIDaeSFNfdCerZLTDK6koJPdt/view?usp=sharing | L61: Mmm! I love to drink milk! | M61: https://drive.google.com/file/d/1L5QYUU_xk8dwVpqjnI2JQSpKi9wrXAYy/view?usp=sharing | O61: https://drive.google.com/file/d/1_RYXcK8J75m1Csq-TkLrZ-hxhCNkCyMR/view?usp=sharing | P61: I love to drink orange juice! | Q61: https://drive.google.com/file/d/1I8Gx45PqluojOvkN6A3dlLJG7JB0COvT/view?usp=sharing | S61: https://drive.google.com/file/d/1JqvvwDuy_S4SfF9izRjz2tOPd_YNhD0W/view?usp=sharing
A62: 3 | B62: 1 | C62: Actions 2 | D62: walk | E62: https://drive.google.com/file/d/1QT05PL1MX7bwV9fDvz3vPvzAr-TR0VgE/view?usp=sharing | F62: https://drive.google.com/file/d/1T3iyfXWjWUUyL194QMztUo-mNFpFVO-c/view?usp=sharing | G62: https://drive.google.com/file/d/1VHRXWqPvdJ99kTbjt6eaKg6yA9470_KO/view?usp=sharing | H62: https://drive.google.com/file/d/1x0BHfg0JWQUU4HmQVSTpv19S-1m_uMhB/view?usp=sharing | I62: https://drive.google.com/file/d/1j2PvqqBHt7kvtHKkqUQ_eeyRtNtcYXZx/view?usp=sharing | J62: https://drive.google.com/file/d/11BYSe0vZmMT6t9cvFVT2Ip3EtK8sW5e4/view?usp=sharing | K62: https://drive.google.com/file/d/1d1B9wJcbst3jmim97JwQG1AzwLlhLfqK/view?usp=sharing | L62: The little boy walks on the beach. | M62: https://drive.google.com/file/d/1jkhMf70ZHAS0aLIRs_BABWsbA0Oyf_hx/view?usp=sharing | O62: https://drive.google.com/file/d/1P63lUYBPvWho84FentI2fvWy8UOdcstG/view?usp=sharing | P62: The baby boy likes to walk in the park with his mother. | Q62: https://drive.google.com/file/d/1nAxkhm4Nys14odeSk9WobXHd_hB1-zR0/view?usp=sharing | S62: https://drive.google.com/file/d/1hvuDr8WLdGSAqYRHbiw5WBKm8HcX7ylk/view?usp=sharing
A63: 3 | B63: 1 | C63: Actions 2 | D63: run | E63: https://drive.google.com/file/d/18a7Ml_Hwpd8YMjbKATLzTpLcS_cwBZqV/view?usp=sharing | F63: https://drive.google.com/file/d/1l23UxRrUHJ9Y_lHf4splc6h4Vrw172LB/view?usp=sharing | G63: https://drive.google.com/file/d/1pssvjEHSy-2JS0dgDapcWzLey70aDqw0/view?usp=sharing | H63: https://drive.google.com/file/d/1ZAx9ZAEYQiOaVxmkUlWvzS_NWBoKmLPp/view?usp=sharing | I63: https://drive.google.com/file/d/1_HmexwxzunuNHdjyPOcGa8_bmIpCFlHY/view?usp=sharing | J63: https://drive.google.com/file/d/1BZWmH2SK9i3GmQdkHNKZTLZ9X8ec167v/view?usp=sharing | K63: https://drive.google.com/file/d/16qT8Q4sKYWJD59zgMSIbEzblKZTTaUaR/view?usp=sharing | L63: They are running. | M63: https://drive.google.com/file/d/1TzZpOM0oIUH5I3fBctblGoVfFXt9XkKi/view?usp=sharing | O63: https://drive.google.com/file/d/1IuO-d2Y7y-1OisqJXVTElnpRF3J5UYF7/view?usp=sharing | P63: Let's run in the park! | Q63: https://drive.google.com/file/d/1KVpsRc7k4lPnf16qLDVX8nYZL-lHMqND/view?usp=sharing | S63: https://drive.google.com/file/d/1uFRXVrlfEVFZm6xzU75VcF9A-RLmPB-_/view?usp=sharing
A64: 3 | B64: 1 | C64: Actions 2 | D64: play | E64: https://drive.google.com/file/d/1e_l5ZzOGKVd8XKFDQlm56xGSVdIpZHRL/view?usp=sharing | F64: https://drive.google.com/file/d/17qq4GZfoP9el2H6SL9A_fzscKH5D8QN1/view?usp=sharing | G64: https://drive.google.com/file/d/1pqdQVp_ArTRNO8uoo6c5XIU2-xQblVer/view?usp=sharing | H64: https://drive.google.com/file/d/1eKpHBwDEto9kMFkej4Z_-l1bjhrJqm7F/view?usp=sharing | I64: https://drive.google.com/file/d/1XG5Zy_mwVwkIXw2USXRQArH5mYKwlJLm/view?usp=sharing | J64: https://drive.google.com/file/d/1oz78QgGQpKM-jvhOyY5qTHoXEKvuJGra/view?usp=sharing | K64: https://drive.google.com/file/d/1XMHlq8GWZtbQ3CdaC0OS_is3PSC0EoRz/view?usp=sharing | L64: Do you often play with your friends? | M64: https://drive.google.com/file/d/1om-u2FbAgNDxxe8SwZ7zaEx3x2nc-Z2y/view?usp=sharing | O64: https://drive.google.com/file/d/18BxwEkS-O7SOxdc9iArRa8bE42YJcQ3i/view?usp=sharing | P64: Let's play football with my family! | Q64: https://drive.google.com/file/d/1DhJqn1tQ5uy-xoww2wMmYyA3hXIswdaN/view?usp=sharing | S64: https://drive.google.com/file/d/1OpYrYuJ5mAt1cd1czfTBeH3O_cmahxIA/view?usp=sharing
A65: 3 | B65: 1 | C65: Actions 2 | D65: clap | E65: https://drive.google.com/file/d/1e0LiQ7onuTU-jKds6qXFpUU-GQQKp0xV/view?usp=sharing | F65: https://drive.google.com/file/d/1ODMK1COHjqVBA1prNInTFx_YqrezJVwt/view?usp=sharing | G65: https://drive.google.com/file/d/1ghlDEj9CTObI4TPjfy-I6soxoMVVPMlJ/view?usp=sharing | H65: https://drive.google.com/file/d/1u_tl3uJVPR15iccio_Km9njH99pPS3jV/view?usp=sharing | I65: https://drive.google.com/file/d/1Qffh7mF7BIj-Wf6zSesNSG1xRmlrR2hS/view?usp=sharing | J65: https://drive.google.com/file/d/1cpxZcYFJ4vB1xLVDxeFLo06J-IuSVBiy/view?usp=sharing | K65: https://drive.google.com/file/d/15Oq3FM2inrdQk9KMZEIxad7nKizMuNiU/view?usp=sharing | L65: Clap, clap! Clap your hands. | M65: https://drive.google.com/file/d/1bgs1gGYCjSoLQUmSlddDahVQ2fc8Bahi/view?usp=sharing | O65: https://drive.google.com/file/d/1fRQLsJCGBNH0mvPTL9BZFumVABWe8aXa/view?usp=sharing | P65: Let's clap our hands. | Q65: https://drive.google.com/file/d/1LR73w2S6zx4x2bHWpC9oV0qmHKW0hpyT/view?usp=sharing | S65: https://drive.google.com/file/d/1GAHUrA3qHMqVJ4bC5mDR0dsnzbjH_xvh/view?usp=sharing
A66: 3 | B66: 1 | C66: Colors 1 | D66: red | E66: https://drive.google.com/file/d/1x5Zd-yeyF8Ga65BYRgi3_GvUQA6cRGHb/view?usp=sharing | F66: https://drive.google.com/file/d/1CbPFVutzl4cUhLgkWbaQrl1skjpSWfVU/view?usp=sharing | G66: https://drive.google.com/file/d/10dgf9FICk6KQLMca5C4pQO88TTbw5ICo/view?usp=sharing | H66: https://drive.google.com/file/d/17XUQzADy0GSUHlZxTf4LvXtctm1HDuu_/view?usp=sharing | I66: https://drive.google.com/file/d/1Pvqr9oaYWzok0i-a9dlPazXdehEwxMvs/view?usp=sharing | L66: Wow, red roses! They are so beautiful. | M66: https://drive.google.com/file/d/1Dw3g5Kqc4sR0_VIJiBdRkf5PYpabUcAI/view?usp=sharing | N66: https://drive.google.com/file/d/1002xL8KlKsJXBk4uM7o5O9u8WZrDi3-r/view?usp=sharing | P66: The red strawberries look so fresh! | Q66: https://drive.google.com/file/d/1yhgXxjtHJrDADaf9zZ57etYmqi6xBBUg/view?usp=sharing | R66: https://drive.google.com/file/d/1VDKv1vRNIDdxGl3f3UjfVkExT-uAZ4aI/view?usp=sharing | U66: { "text": "242,7,7", "highlight": "20,4,246" }
A67: 3 | B67: 1 | C67: Colors 1 | D67: pink | E67: https://drive.google.com/file/d/1FpAo8jdwFMDeR77WdGSsHg-d_UMTcq_I/view?usp=sharing | F67: https://drive.google.com/file/d/1RGU36pO9uZWK4JGXwc_4GsP1tjKexkDF/view?usp=sharing | G67: https://drive.google.com/file/d/1daE7vCXyD-UjwOkWQh3C-8hAWFtzO-4G/view?usp=sharing | H67: https://drive.google.com/file/d/1VWamPV827LTflOjz1qY-yYSWI-200KnG/view?usp=sharing | I67: https://drive.google.com/file/d/1Ssaf2KuakaamxrmkZS_1kh8fu_eO3wRh/view?usp=sharing | L67: Red and white make pink. | M67: https://drive.google.com/file/d/110dK5MVEDWzI0P--Dk7_dgstXOiAx3j6/view?usp=sharing | N67: https://drive.google.com/file/d/1gzDOOjW_4rOiAsNIun4y_b58tC1g3sOV/view?usp=sharing | P67: I love pink flowers. | Q67: https://drive.google.com/file/d/1YpbJFfftY9DzvyWjQZb3OcUe5FR4OVlN/view?usp=sharing | R67: https://drive.google.com/file/d/1Jru6rBuK2W6RJQ91wf77ZvP7rkhoVmRI/view?usp=sharing | U67: { "text": "255,20,127", "highlight": "0,0,238" }
A68: 3 | B68: 1 | C68: Colors 1 | D68: blue | E68: https://drive.google.com/file/d/1EgvOi8bXE0InFSIzocB4I9doAeZzs4nn/view?usp=sharing | F68: https://drive.google.com/file/d/185lSFcaGQy5T0Z7ttSYPM8gjpsb81BPT/view?usp=sharing | G68: https://drive.google.com/file/d/1mRSuyhWgYphk4TANCLJePIx4L8yWsy7Z/view?usp=sharing | H68: https://drive.google.com/file/d/1OSJgT1rF0_P8Y6_jBx_qxBV6zA1nGSoR/view?usp=sharing | I68: https://drive.google.com/file/d/1rk9uo3s-peS1BGyQhwkbHfHpwJprDZ_Q/view?usp=sharing | L68: See? I have a blue bike! | M68: https://drive.google.com/file/d/19vTRCVMVp06anVuIQmbht_wcutxcger-/view?usp=sharing | N68: https://drive.google.com/file/d/1XP-mMas2bJfdqdS6Ermpzo3vWu_Bk7Ny/view?usp=sharing | P68: The blue fish are swimming. | Q68: https://drive.google.com/file/d/1olU5JT0bQohRBTsybDpQUoBAGG14kNTl/view?usp=sharing | R68: https://drive.google.com/file/d/18JPzEYMU40mB-IJl53Vf6tASSAJErad1/view?usp=sharing | U68: { "text": "0,0,238", "highlight": "255,0,0" }
A69: 3 | B69: 1 | C69: Colors 1 | D69: black | E69: https://drive.google.com/file/d/1Nds0YKSVTEEavh9--Dl9O1kaqL1wZcxU/view?usp=sharing | F69: https://drive.google.com/file/d/1yNcrDJuGcs0JcEOLLgOrU7XV8MuujM8G/view?usp=sharing | G69: https://drive.google.com/file/d/10KcB5I_JcfTqWsSCiE_UcMz-q9vt49jV/view?usp=sharing | H69: https://drive.google.com/file/d/1asQ_fL0uJ7ggqu9uZaeXxAn9h8dQ4Hmv/view?usp=sharing | I69: https://drive.google.com/file/d/1LiEC3LbN1dMce13EcFx84TmFiz1WLp4z/view?usp=sharing | L69: The man is wearing black clothes. | M69: https://drive.google.com/file/d/10IY2MDa3ECAEYn3R0fZiiusVczDS6FYZ/view?usp=sharing | N69: https://drive.google.com/file/d/1KFk4JnUEs6I2kdoCZ4n4kwPLldqOzvCJ/view?usp=sharing | P69: Do you like the color black? | Q69: https://drive.google.com/file/d/1Az-xK5s8-xNAl4dRrtNyU-wAC_nUSebY/view?usp=sharing | R69: https://drive.google.com/file/d/1uSjzpkoOgddRUHxKIoDzr_4sshuimiCI/view?usp=sharing | U69: { "text": "18,17,17", "highlight": "255,0,0" }
A70: 3 | B70: 1 | C70: Colors 2 | D70: green | E70: https://drive.google.com/file/d/1WD_r8LNzVdF81KX2EqvMFAIis1ymGsd5/view?usp=sharing | F70: https://drive.google.com/file/d/1sMufipq4pSd9yQvK2BuND10dgzOznQj7/view?usp=sharing | G70: https://drive.google.com/file/d/19iBHuRu5Tj8-MKakuQAWKdeGzwtiGQAz/view?usp=sharing | H70: https://drive.google.com/file/d/1tMhloLqgxfEGX0RaB3FHGw7l1QFCekcw/view?usp=sharing | I70: https://drive.google.com/file/d/1Pf3p64yvaPm4LzqyhpenhaqAUPlnTi0L/view?usp=sharing | L70: Leaves are green. | M70: https://drive.google.com/file/d/1bfvJraf2GpbaeTPfuQCn1XbT2dsCgojc/view?usp=sharing | N70: https://drive.google.com/file/d/1VLez2u7qC7HWTYPVW-UN6w_0OmgjpQ-C/view?usp=sharing | P70: Wow! A green car is on a green road. | Q70: https://drive.google.com/file/d/1e6Cfq17Ke1SaE9q5diQlZaGWA7EAmO06/view?usp=sharing | R70: https://drive.google.com/file/d/1Wdpddcbm_iOIzoxXN1PaQVVZj9BdXXCf/view?usp=sharing | U70: { "text": "0,205,0", "highlight": "255,0,0" }
A71: 3 | B71: 1 | C71: Colors 2 | D71: white | E71: https://drive.google.com/file/d/1wFK-cXkXRQg3RobUEjhiwbONgy2ykLFZ/view?usp=drive_link | F71: https://drive.google.com/file/d/121Krzi1gj-RnZJ3Gjf1srcuC3ELv93PX/view?usp=sharing | G71: https://drive.google.com/file/d/1og8gSuNLSfYsqXfDmqqIXByzwIF0WhrB/view?usp=sharing | H71: https://drive.google.com/file/d/1ZHv5c8EvM2qDNA0EYl_TJIRc_CnCEK82/view?usp=sharing | I71: https://drive.google.com/file/d/16ADu71hLWMUmJR4d6tra8gm2QNWWCTkb/view?usp=sharing | L71: The white bird is flying. | M71: https://drive.google.com/file/d/1WOEY8nq8bIjYwCQzrLIrNa46gy2QTcpR/view?usp=sharing | N71: https://drive.google.com/file/d/1uMmJUo_gT860Q6eEhAXEqTA5uWjblUq8/view?usp=sharing | P71: A white bunny is on green grass. | Q71: https://drive.google.com/file/d/1GD0cxgSJUdmXzQlBLH7wAdyn0_w2GEEH/view?usp=sharing | R71: https://drive.google.com/file/d/1usI66FNYBE9lsGW5ZKYAydyXpjCFZn7W/view?usp=sharing | U71: { "text": "0,0,0", "highlight": "255,36,36" }
A72: 3 | B72: 1 | C72: Colors 2 | D72: orange | E72: https://drive.google.com/file/d/1-1PjtXjSBN6GR5uThbGm3LVIlRyy4Cu2/view?usp=sharing | F72: https://drive.google.com/file/d/1_b3Ze3JU8bTFEiLRB8CsKDY4xejlt-uY/view?usp=sharing | G72: https://drive.google.com/file/d/1nbvolf8cYbRT7xWnowt7kGXblcO4ZpjC/view?usp=sharing | H72: https://drive.google.com/file/d/1aHD1Fsv4eJDB7BJ_S95CClgIXMV_dDoM/view?usp=sharing | I72: https://drive.google.com/file/d/1x8dpCXrDUSGXW4dzkB-JPQ6jO19O4aSB/view?usp=sharing | L72: His helmet is orange. | M72: https://drive.google.com/file/d/1ME9Ms0wZpFyF3b7GxHJPTqxgvYJRqS0n/view?usp=sharing | N72: https://drive.google.com/file/d/1ACXE7xC239Q1z6qo5RgTb1uNfD5zu0x-/view?usp=sharing | P72: He is sitting on an orange chair. | Q72: https://drive.google.com/file/d/1d_LrqNIMoPNbLFnP6YvaSsYKze2laBY2/view?usp=sharing | R72: https://drive.google.com/file/d/18epUzkF6OI5mppDUrrFoUxOSc1ds4UBr/view?usp=sharing | U72: { "text": "255,118,0", "highlight": "0,0,238" }
A73: 3 | B73: 1 | C73: Colors 2 | D73: purple | E73: https://drive.google.com/file/d/11Xgf-LV6sKLe524wWq0L95H-sKv4w6Mr/view?usp=drive_link | F73: https://drive.google.com/file/d/1BI-QtSk0IA8zyWcqLRfrvugDs-hsXWio/view?usp=sharing | G73: https://drive.google.com/file/d/1s_BuOegoS2vXWgIMEaSygCkwmEo4NQB5/view?usp=sharing | H73: https://drive.google.com/file/d/1X6WE-lj9gYzpvMuhVFyo-sc-2fYLmP0Q/view?usp=sharing | I73: https://drive.google.com/file/d/1E67jJh24wkypZuY73X5x_ht1hy1r3EwX/view?usp=sharing | L73: Look! Red and blue make purple! | M73: https://drive.google.com/file/d/1ORy1FIFVHbj8FaKRgFC7cqNKWW0atqBU/view?usp=sharing | N73: https://drive.google.com/file/d/1T7tnG9UrJyyFzkrNMNW7r-Va3WfNV8dI/view?usp=sharing | P73: There are many purple flowers! | Q73: https://drive.google.com/file/d/1hYIj-Tz3wd4lVX0N1f8sYIVQ-4fJ1eaV/view?usp=sharing | R73: https://drive.google.com/file/d/1OrHubaFPE-3XtEyKCXo7w4cbs971LW2s/view?usp=sharing | U73: { "text": "128,0,128", "highlight": "255,0,0" }
A74: 3 | B74: 1 | C74: SW 25 | D74: way | E74: https://drive.google.com/file/d/1JaoIgIalMwhn3tOoskWP1L37x2DaTkvZ/view?usp=sharing | F74: https://drive.google.com/file/d/1c6-gIMj5-V5HnWPJNEgLtP2Ls0wXjaR0/view?usp=sharing
A75: 3 | B75: 1 | C75: SW 26 | D75: by | E75: https://drive.google.com/file/d/1TFlHQxTfVU6PKVixHvdppTzgNOoh6-rB/view?usp=sharing | F75: https://drive.google.com/file/d/1Mul26U23Uy7Mafe06MKoOH8CO8DRs2Je/view?usp=sharing
A76: 3 | B76: 1 | C76: SW 27 | D76: but | E76: https://drive.google.com/file/d/11WKz5Izz6cq6xvzrFP8S2SV41LMOgYrO/view?usp=sharing | F76: https://drive.google.com/file/d/1doponkWXKMPn1cXUsPDi-MiKvovLeqaJ/view?usp=sharing
A77: 3 | B77: 1 | C77: SW 28 | D77: not | E77: https://drive.google.com/file/d/1kJJvrQVBY2KeFJaileGgEcj2UIovH6Fc/view?usp=sharing | F77: https://drive.google.com/file/d/19lOmerslPvSHBJZMcwtj8cxWoj9Realq/view?usp=sharing
A78: 3 | B78: 1 | C78: SW 29 | D78: what | E78: https://drive.google.com/file/d/1C_7_vkyF9UvW3cmxRGLtgP3WcxP2Tnhr/view?usp=sharing | F78: https://drive.google.com/file/d/1l5uTNdkK1ZLu9ZQLEXKNa6fO5bw_PWFW/view?usp=sharing
A79: 3 | B79: 1 | C79: SW 30 | D79: all | E79: https://drive.google.com/file/d/14Lczq2Cwa7ko_LZeZgzH3GbiGDo6JC8M/view?usp=sharing | F79: https://drive.google.com/file/d/1LYH1FaSEow1oURKmQDWEAw_e_Ts-F-Z_/view?usp=sharing
A80: 3 | B80: 1 | C80: SW 31 | D80: I | E80: https://drive.google.com/file/d/1T9KFGfapNt4ivXOIjQDLwqvh34g6O1XO/view?usp=sharing | F80: https://drive.google.com/file/d/1ttqV0Ej4v8Yf1N3Rrt8Hl8sTzb_YlMwz/view?usp=sharing
A81: 3 | B81: 1 | C81: SW 32 | D81: his | E81: https://drive.google.com/file/d/1iTXkUH2EKLX-MB8xGkybCFMwlH0x53bg/view?usp=sharing | F81: https://drive.google.com/file/d/1m6o-XQLUD7O_ChjXgEg9oI9I5IHrEuCB/view?usp=sharing
A82: 3 | B82: 1 | C82: SW 33 | D82: we | E82: https://drive.google.com/file/d/1xsFwxy3-axGWAWZhF0PG6M5Cor0Yf3gp/view?usp=sharing | F82: https://drive.google.com/file/d/15kI6-3mM69JFrmngYAnhy9DQxpitchJA/view?usp=sharing
A83: 3 | B83: 1 | C83: SW 34 | D83: when | E83: https://drive.google.com/file/d/1QGp0sGFtdwnJ88iThSxAb4BOb8O4v5KC/view?usp=sharing | F83: https://drive.google.com/file/d/1eoh8meg4BFvGDsHJiChIabg4_OO4jhTu/view?usp=sharing
A84: 3 | B84: 1 | C84: SW 35 | D84: your | E84: https://drive.google.com/file/d/13AX4FF33X_1oj6nyIGABu9QXlqnayZkC/view?usp=sharing | F84: https://drive.google.com/file/d/1E9FVTR7JCQT2SEnyDfgc4y2M1SK3Zhrb/view?usp=sharing
A85: 3 | B85: 1 | C85: SW 36 | D85: there | E85: https://drive.google.com/file/d/1qMqOa_dLCRaBLu44_rAdleTyw3i1qp7J/view?usp=sharing | F85: https://drive.google.com/file/d/1i1j3YVYgp3ccq8Los5oE3c_sagTqWLAh/view?usp=sharing
A86: 4 | B86: 1 | C86: My house 1 | D86: fan | E86: https://drive.google.com/file/d/1zNYHgOC45QwMNmtlNCutCZRoIsk_y4Q5/view?usp=sharing | F86: https://drive.google.com/file/d/1itDtGhHgeMpi4v-Ro9o4N4drT4VHFqCu/view?usp=sharing | G86: https://drive.google.com/file/d/1gAbA7jGcROq_6VinRMci-rCsUR-GogH-/view?usp=sharing | H86: https://drive.google.com/file/d/1ioMUqr5Mgj8Up0-y--4c72LweEfyLsh-/view?usp=sharing | I86: https://drive.google.com/file/d/1Ho3X6XK9YlIgKhKoFPGoPYizKpL0qtb1/view?usp=sharing | L86: The fan cools me down. | M86: https://drive.google.com/file/d/1iClL5qI7kw8_CH7lH-m_qZ6tzndua5jA/view?usp=sharing | N86: https://drive.google.com/file/d/14G0q9bblm5R_MorLLBNcaE1EY2VF9CuM/view?usp=sharing | P86: Do you have a fan at home? | Q86: https://drive.google.com/file/d/1KKWgYPBM7e7s1lUM9a_KoR0BXZ5CXC-3/view?usp=sharing | R86: https://drive.google.com/file/d/1dz22mDzNT9qUzSipaLg19ID4aV9A5eMT/view?usp=sharing
A87: 4 | B87: 1 | C87: My house 1 | D87: key | E87: https://drive.google.com/file/d/1uPKnrPeWisggf6DLMv4nLTuLni0vbPMy/view?usp=sharing | F87: https://drive.google.com/file/d/15Ze0EQxcvKpabN1PbIaNJ9z1ZeK0aPC2/view?usp=sharing | G87: https://drive.google.com/file/d/19BDoiJPQTNveNgOfjPpsS3FcpjDwmuer/view?usp=sharing | H87: https://drive.google.com/file/d/1FHgwaZ-adXi_lXxQZnlYIG1v5Jw-QW07/view?usp=sharing | I87: https://drive.google.com/file/d/1xk-ddB04PsTRVgFvaL78fXjuYn6i2EG4/view?usp=sharing | L87: This is a gray key. | M87: https://drive.google.com/file/d/1OI82MxFy_wPfnxuq4_exbOVk0DbCObRY/view?usp=sharing | N87: https://drive.google.com/file/d/1I7qENd2MlsEYMJIA4FsLSlkJbgnzGMIw/view?usp=sharing | P87: Yes! This key is the right one! | Q87: https://drive.google.com/file/d/1iK9-vx8m3IJ-ZNs8Cx6XCeHP1NRnOL6E/view?usp=sharing | R87: https://drive.google.com/file/d/1Ie8P4KiAsjHRf8WcgYTIJ4iQu8HEfRmz/view?usp=sharing
A88: 4 | B88: 1 | C88: My house 1 | D88: bed | E88: https://drive.google.com/file/d/1XFpLIp6MQRGU1sQbDqGCmmvtj8TVaYu9/view?usp=sharing | F88: https://drive.google.com/file/d/1pNWV3mvVpkCjm43lCwIep42g6Ni12gPu/view?usp=drive_link | G88: https://drive.google.com/file/d/1RJy5GqqB2WiPC58n-ycudrmuOP0X-2_Y/view?usp=sharing | H88: https://drive.google.com/file/d/1MnIjlifXwmreF1eDRn2MNAp2EzczcjM2/view?usp=sharing | I88: https://drive.google.com/file/d/1AwKJBaLvRhoHxaUZHwQYJ06A4J8ThpWI/view?usp=sharing | L88: The kids are having fun with dad on the bed! | M88: https://drive.google.com/file/d/1rxuVPCZmnyEgGwR87XzIoD4mo_6n9ibm/view?usp=sharing | N88: https://drive.google.com/file/d/1kZMmIPKKmimo7GuAgv8tRxER9288J_e7/view?usp=sharing | P88: The Girl loves to jump on the bed! | Q88: https://drive.google.com/file/d/1wZj9PloeEu0QItnkM7zmo2QnmBMAaT-m/view?usp=sharing | R88: https://drive.google.com/file/d/1vrSh8kXogqsor5cg22ZOysqLbU-fSbr8/view?usp=sharing
A89: 4 | B89: 1 | C89: My house 1 | D89: fork | E89: https://drive.google.com/file/d/1ATf2yXTVqxQEhdHZ9Uwe03vTYNi4FHi4/view?usp=sharing | F89: https://drive.google.com/file/d/1baKDiYfFYAKLu1ZGxi-soppJ41UnX-p1/view?usp=sharing | G89: https://drive.google.com/file/d/1fZ5s8qXR2-18Bqv46KY0QPKjgRv5dAa4/view?usp=sharing | H89: https://drive.google.com/file/d/1jTBdI9WRbppwyrvbOPUGfHSro5iUpX2P/view?usp=sharing | I89: https://drive.google.com/file/d/1HyNDJIrHdUScbBCuN6pLqKHb_F_3ldHy/view?usp=sharing | L89: The Girl is eating with a fork. | M89: https://drive.google.com/file/d/1HjGK2HYCaDhi5a7M5on3JcmIxoUbifl0/view?usp=sharing | N89: https://drive.google.com/file/d/1C-eMGj01nlUtZlUB_S2mugVIPzbuUOaK/view?usp=sharing | P89: Do you have a fork at home? | Q89: https://drive.google.com/file/d/17TLS5JMTcHgQXGOvDuhaw0pR2k8wp08k/view?usp=sharing | R89: https://drive.google.com/file/d/13zE_XfmITA8UmuonMFVgMPruvybCZBwM/view?usp=sharing
A90: 4 | B90: 1 | C90: My House 2 | D90: wall | E90: https://drive.google.com/file/d/1vYOmFTTMIi7sQJd2-2ItFheDTqwEJFDF/view?usp=sharing | F90: https://drive.google.com/file/d/1Zgt8kx_Eq6Lk0ymRt2J3TvaQflZe1aMC/view?usp=sharing | G90: https://drive.google.com/file/d/1RxESHBowbGU6r8GQjtzc2Yzu3_x04IJ8/view?usp=sharing | H90: https://drive.google.com/file/d/1uPgHBKoRir61unS56MonxWUMrQgCLD9V/view?usp=sharing | I90: https://drive.google.com/file/d/1qZaOhaXWErVz6U7kB22jCLaAOaitxKBW/view?usp=sharing | L90: Brick walls are a deep reddish-brown color. | M90: https://drive.google.com/file/d/1DiZX8X3PYlJF3AwD18u48RbpD0PVcyMX/view?usp=sharing | N90: https://drive.google.com/file/d/1sZZfry9L7GC_6wbfq8nOGNduHmVDMvSp/view?usp=sharing | P90: Look! The wall is red. | Q90: https://drive.google.com/file/d/18bmwT3lTsm8xvd47OS9d0lGIOiQ6RnU_/view?usp=sharing | R90: https://drive.google.com/file/d/12iWkysRY0Q556ucRomKVVnHE-YqzH4E3/view?usp=sharing
A91: 4 | B91: 1 | C91: My House 2 | D91: door | E91: https://drive.google.com/file/d/1bAEwt5eV7q0cDVHjafpwqfMlll7z7jAi/view?usp=sharing | F91: https://drive.google.com/file/d/1Z8LOS33fmHmS_yiLJ0FBk7zRhAykRNi-/view?usp=sharing | G91: https://drive.google.com/file/d/1P3p_VBcRvaCb-aMWdpwSwRdclMQyCeTM/view?usp=drive_link | H91: https://drive.google.com/file/d/176V9rya7x9YNBastQc6keX8qJKPNeS6J/view?usp=sharing | I91: https://drive.google.com/file/d/1zrjIituKbgjFx6aM2hvioPatsO3qOHxm/view?usp=sharing | L91: The woman is opening the door. | M91: https://drive.google.com/file/d/1wzhwR33qty8YrO3My76sD70Vfqfp0ayt/view?usp=sharing | N91: https://drive.google.com/file/d/174bfj3vlnNorVNn-pS5s--k9D1Q1nTQg/view?usp=sharing | P91: The kids are opening the door and running into the room. | Q91: https://drive.google.com/file/d/1_WJzbVOBf3W3TIu1h-onGIP6TOkCa7uY/view?usp=sharing | R91: https://drive.google.com/file/d/1nSEN2gDt-hGdL6WOIxvqLu-twJmOOIhn/view?usp=sharing
A92: 4 | B92: 1 | C92: My House 2 | D92: sink | E92: https://drive.google.com/file/d/1xHqyICZa2GK0LktuDOQpe9ux-tk7XAq-/view?usp=sharing | F92: https://drive.google.com/file/d/1IMpIi_cgB54M2Gx-gULIQrSPCuqS2PST/view?usp=sharing | G92: https://drive.google.com/file/d/1qNTBRebizY3Kuzo24WSt9Gzzi62wBK5c/view?usp=sharing | H92: https://drive.google.com/file/d/1f-ibN9jKvj6u2Gn6aG1xgKe_AkjQMz1H/view?usp=sharing | I92: https://drive.google.com/file/d/1xN22256hHLOgUApKHIg2FCeypbWrW8je/view?usp=sharing | L92: The boy is washing his hands in the sink. | M92: https://drive.google.com/file/d/1a0lKs5Zvi_X4gfVKIoE7IQhmczn2SoHu/view?usp=sharing | N92: https://drive.google.com/file/d/1fDcnpFjvREZjzMe7oHao4-nC6_9DPwon/view?usp=sharing | P92: Do you often wash your hands in the sink? | Q92: https://drive.google.com/file/d/1ce2cP0id3ZhiOxzNFZGsTiAK_0cmyKUt/view?usp=sharing | R92: https://drive.google.com/file/d/17xYXlyobt9UzUCvGU4S-IaYiQdXTwSMm/view?usp=sharing
A93: 4 | B93: 1 | C93: My House 2 | D93: bowl | E93: https://drive.google.com/file/d/1EEUlyhsXBsZd780hhwxspTCJ-20Bpk_p/view?usp=sharing | F93: https://drive.google.com/file/d/1sHVq91MhWL46J8PNhKAxfYIyxjJFMoje/view?usp=sharing | G93: https://drive.google.com/file/d/1F3m8OBI0qqK4Okjo2_xaIMpfNzu-PvCF/view?usp=sharing | H93: https://drive.google.com/file/d/1JJwqgDDuX3KBcfNAuODcl0DVOY-AtzZy/view?usp=sharing | I93: https://drive.google.com/file/d/1KWDDbmPoViVhEbSmkhwY5aBULq7zCd1t/view?usp=sharing | L93: I want that bowl of soup! It smells so good. | M93: https://drive.google.com/file/d/15XylsjqSWvpBi7twXjJVqInMrzjoQTkS/view?usp=sharing | N93: https://drive.google.com/file/d/1OEUF4jnkRCvr-AoimqP0SRjiRYecFR2-/view?usp=sharing | P93: Wow! Such a big bowl of soup! | Q93: https://drive.google.com/file/d/1HobXmjR2MNiMnvHrPZ6VqvpkV1jWP4P4/view?usp=sharing | R93: https://drive.google.com/file/d/1HthTYRk_tUcBWACSiKyqv5xqFU6mccJp/view?usp=sharing
A94: 4 | B94: 1 | C94: Body Parts 1 | D94: eye | E94: https://drive.google.com/file/d/18OuY9qcLlkiS2naFCZhbCheweZ1mtSf5/view?usp=sharing | F94: https://drive.google.com/file/d/1ca6XFlnSkRVNrdw8aIbAPwWYllEbjuvd/view?usp=sharing | G94: https://drive.google.com/file/d/1Esq5dFeCS7JKSgP64MiIKIG3LL8C4J6w/view?usp=sharing | H94: https://drive.google.com/file/d/1dQXYVIyzzU6rXU8Zt6muQrI2el1hK1mh/view?usp=sharing | I94: https://drive.google.com/file/d/1MvV4nbuEYXwo65ked7PmVkmUGe5rl7V9/view?usp=sharing | L94: Her eyes are so beautiful. | M94: https://drive.google.com/file/d/1s1y77UpA3g5jRWN_IUcYG1TQzi0klTGC/view?usp=sharing | N94: https://drive.google.com/file/d/1XDRTJ6qLeCYY79uoIIi-fdYssMv-cCo4/view | P94: Close your eyes and sleep well! | Q94: https://drive.google.com/file/d/1pXZQSsncqkWCLVrgh1-VUClfQiITrTMl/view?usp=sharing | R94: https://drive.google.com/file/d/1HZEmDEfXWp1TJj4_JkEBzcW8Aqphxicy/view
A95: 4 | B95: 1 | C95: Body Parts 1 | D95: ear | E95: https://drive.google.com/file/d/1_tBTzxNYoJA2Ap-pZOWcq0mksyERxynu/view?usp=sharing | F95: https://drive.google.com/file/d/1jK4fzI_TGUHGz4YYnqX_OCyawEC-8R2b/view?usp=sharing | G95: https://drive.google.com/file/d/1O76RtcaRyU43zk5qzk2g9UV5t98RMItq/view?usp=sharing | H95: https://drive.google.com/file/d/1aTV-HJzBtL0JBQUIWYBVaVwVxMKSCGX9/view?usp=sharing | I95: https://drive.google.com/file/d/1CU2XVWH-JBi9140pb-qCIC3P86dFUTzE/view?usp=sharing | L95: Jane uses her ears to listen to the violin. | M95: https://drive.google.com/file/d/1lUXDFbP3siO5339msVxnmOeJxOBN4PaD/view?usp=sharing | N95: https://drive.google.com/file/d/1H-0xmlM6mnc1CuJgkwjFlY8qPOV9TIbX/view | P95: The man is covering his ears. | Q95: https://drive.google.com/file/d/1p3fokS-O47DU6DLgVLET6s5TWDGGrsqF/view?usp=sharing | R95: https://drive.google.com/file/d/1uRX5xle5lzdPS2lKe9Xi9UDDr8MLLQUw/view
A96: 4 | B96: 1 | C96: Body Parts 1 | D96: arm | E96: https://drive.google.com/file/d/1n0psXKgDocdcZ4EmyVeZaXQRlTEL2uRk/view?usp=sharing | F96: https://drive.google.com/file/d/1krmr9gYiRV-W-hXHY2zvMA3QgncnQq5O/view?usp=sharing | G96: https://drive.google.com/file/d/1vDcJfUfeq8KgrSUTh_DGbm-kuBxPj7e0/view?usp=sharing | H96: https://drive.google.com/file/d/1lfxhdbAEvaiMFlGtRiqdtnGXEREAwh3O/view?usp=sharing | I96: https://drive.google.com/file/d/1t_0Yp02XQAahJ4pG_e1uCQ3Si7HzEYIA/view?usp=sharing | L96: She is spreading her arms. | M96: https://drive.google.com/file/d/1CYq3lvwyeV5wELsgJUyhHJ4D2nZTEdeC/view?usp=sharing | N96: https://drive.google.com/file/d/1Sff7CfpQyfNpDeadQG8TpWey2IIPIpYn/view | P96: Can you lift your arms up? | Q96: https://drive.google.com/file/d/1nNzopsIRJVDRoy3gJ01fpzSI7TP6QaBE/view?usp=sharing | R96: https://drive.google.com/file/d/1IRe1Em57j7WYPfWwsJUCmrYsZFchxCM0/view
A97: 4 | B97: 1 | C97: Body Parts 1 | D97: leg | E97: https://drive.google.com/file/d/14T_Cqm4X4sz0k-XaJvywshYyDS4gxlpW/view?usp=sharing | F97: https://drive.google.com/file/d/1mpfgWJpTJbztwrP39tkoxrALka1lGHNs/view?usp=sharing | G97: https://drive.google.com/file/d/1Uh9uHxaSJ2YaIS0zOZWtY2q35l63Oxgp/view?usp=sharing | H97: https://drive.google.com/file/d/1J2LLNfSEPSWVuqNMzfxPMvPIwH65nIij/view?usp=sharing | I97: https://drive.google.com/file/d/1QSfLoVd9uLeLJ0rP8xy2dO8-jl2A_fBv/view?usp=sharing | L97: Running makes our legs stronger. | M97: https://drive.google.com/file/d/1a_Z4t1DJaEwUG7nRMW5pSh_-ocEtr4kc/view?usp=sharing | N97: https://drive.google.com/file/d/11pxWisbndpSfPpXIbpoQ5t4dAeaUSf9x/view?usp=sharing | P97: These are my legs. | Q97: https://drive.google.com/file/d/1Ia-1Ydfrj-yY8H9yHRbxLa3ndL6Go0J8/view?usp=sharing | R97: https://drive.google.com/file/d/1pxfkuKw70hIfoIxQ4z2goZ-fAx1tcJUe/view
... A101: 4 | B101: 1 | C101: Body Parts 3 | D101: mouth | E101: https://drive.google.com/file/d/1Ydw7rVWnJTFm4mZLWZPNk4fdtGKcU1Ip/view?usp=drive_link | F101: https://drive.google.com/file/d/1Dwm9vfHDSco3NX0z8Mm3qqwhI0i2zXPE/view?usp=sharing | G101: https://drive.google.com/file/d/1_akeiP6TQV0AYXR_kE5i0pilNe1XmhuO/view?usp=sharing | H101: https://drive.google.com/file/d/1IwlGLRMtcuNV3o8FD-4Dqw2FwELZmYKJ/view?usp=sharing | I101: https://drive.google.com/file/d/1SBTgqttbumysD9_1K4OCfFfsAZ21Z6jV/view?usp=sharing | L101: Open your mouth wide! | M101: https://drive.google.com/file/d/1AT4nx5nYJmgTN_Ajf4Zu9zWz2rJI_bAd/view?usp=sharing | N101: https://drive.google.com/file/d/1rUUv23dXO_EDiUOd-cjR_JMBs1uEOWOD/view?usp=sharing | P101: The baby's finger is in her mouth. | Q101: https://drive.google.com/file/d/1zh0ycj0T-DzORM8gx4_33JuhznCOAy4z/view?usp=sharing | R101: https://drive.google.com/file/d/1MC0zLMnGgPyy-UX-36bKI-xumJZNwe9J/view?usp=sharing
A102: 4 | B102: 1 | C102: SW 37 | D102: two | E102: https://drive.google.com/file/d/1sv7fMCvZ3ZLGyyFu9pQtmfHuVI1fIDu_/view?usp=sharing | F102: https://drive.google.com/file/d/1oqdzfZHomoFX09Cyvqjmdk2IuYKJcKmt/view?usp=sharing
A103: 4 | B103: 1 | C103: SW 38 | D103: use | E103: https://drive.google.com/file/d/10VQ-8YTwKXKbVAWkg_1lXBcillFd2aXy/view?usp=sharing | F103: https://drive.google.com/file/d/1NIH72p6nppqU9Hc5j8Kgwn_6HAGOmV7y/view?usp=sharing
...

Sheet MJ 5.0_Level 0_Topic Audio
A1: Topic | B1: Text | C1: Audio 1 | D1: Audio 2 | E1: Audio 3
A2: Animals 1 | B2: Animals | C2: https://drive.google.com/file/d/1RtyIIg7dglAgxPfAmR5f0w0_1kMfJYaA/view?usp=drive_link | D2: https://drive.google.com/file/d/1-TmLju5q-VniPljEDQlxQgOWewDfilX4/view?usp=drive_link | E2: https://drive.google.com/file/d/1u6jRY6OJq7fGryXYeqfGbBdYeBBSRZQ2/view?usp=drive_link
A3: Animals 3 | B3: Animals | C3: https://drive.google.com/file/d/1RtyIIg7dglAgxPfAmR5f0w0_1kMfJYaA/view?usp=drive_link | D3: https://drive.google.com/file/d/1-TmLju5q-VniPljEDQlxQgOWewDfilX4/view?usp=drive_link | E3: https://drive.google.com/file/d/1u6jRY6OJq7fGryXYeqfGbBdYeBBSRZQ2/view?usp=drive_link
A4: Actions 3 | B4: Actions | C4: https://drive.google.com/file/d/15o6UYhAyF-vNV4k92-TI12GO4o-9Q5Ag/view?usp=drive_link | D4: https://drive.google.com/file/d/1muEvlDHj4d0FCJeffbw10_zhubEJZsce/view?usp=drive_link | E4: https://drive.google.com/file/d/1zhs9xIAsAn9JkkfB4Wrt3jzSCsbkx-O9/view?usp=drive_link
A5: Actions 5 | B5: Actions | C5: https://drive.google.com/file/d/15o6UYhAyF-vNV4k92-TI12GO4o-9Q5Ag/view?usp=drive_link | D5: https://drive.google.com/file/d/1muEvlDHj4d0FCJeffbw10_zhubEJZsce/view?usp=drive_link | E5: https://drive.google.com/file/d/1zhs9xIAsAn9JkkfB4Wrt3jzSCsbkx-O9/view?usp=drive_link
A6: Transportation 1 | B6: Transportation | C6: https://drive.google.com/file/d/1p2W-YZIGwyhAP5mrtcPsNs0vP_34SpaC/view?usp=drive_link | D6: https://drive.google.com/file/d/1ID5lpvcuvlB0XnvpRHX-OCVKfjdWzWSZ/view?usp=drive_link | E6: https://drive.google.com/file/d/1D_3nJ30-18qMcbaIzmSN0EzkEziz0-Gd/view?usp=drive_link
A7: Transportation 2 | B7: Transportation | C7: https://drive.google.com/file/d/1p2W-YZIGwyhAP5mrtcPsNs0vP_34SpaC/view?usp=drive_link | D7: https://drive.google.com/file/d/1ID5lpvcuvlB0XnvpRHX-OCVKfjdWzWSZ/view?usp=drive_link | E7: https://drive.google.com/file/d/1D_3nJ30-18qMcbaIzmSN0EzkEziz0-Gd/view?usp=drive_link
A8: Toys 1 | B8: Toys | C8: https://drive.google.com/file/d/1dWUzaDDXRsirS-peTuQbIUf_NNbAifR8/view?usp=drive_link | D8: https://drive.google.com/file/d/1pUbX-CZhcGze__iIk9Mrh_VE-efA8SOr/view?usp=drive_link | E8: https://drive.google.com/file/d/1z_79yb0DXOd8OaKoDDpDluSy3CaCjCJ4/view?usp=drive_link
A9: Toys 2 | B9: Toys | C9: https://drive.google.com/file/d/1dWUzaDDXRsirS-peTuQbIUf_NNbAifR8/view?usp=drive_link | D9: https://drive.google.com/file/d/1pUbX-CZhcGze__iIk9Mrh_VE-efA8SOr/view?usp=drive_link | E9: https://drive.google.com/file/d/1z_79yb0DXOd8OaKoDDpDluSy3CaCjCJ4/view?usp=drive_link
A10: Actions 1 | B10: Actions | C10: https://drive.google.com/file/d/1dWUzaDDXRsirS-peTuQbIUf_NNbAifR8/view?usp=drive_link | D10: https://drive.google.com/file/d/1pUbX-CZhcGze__iIk9Mrh_VE-efA8SOr/view?usp=drive_link | E10: https://drive.google.com/file/d/1z_79yb0DXOd8OaKoDDpDluSy3CaCjCJ4/view?usp=drive_link
A11: Actions 2 | B11: Actions | C11: https://drive.google.com/file/d/15o6UYhAyF-vNV4k92-TI12GO4o-9Q5Ag/view?usp=drive_link | D11: https://drive.google.com/file/d/1muEvlDHj4d0FCJeffbw10_zhubEJZsce/view?usp=drive_link | E11: https://drive.google.com/file/d/1zhs9xIAsAn9JkkfB4Wrt3jzSCsbkx-O9/view?usp=drive_link
A12: Colors 1 | B12: Colors | C12: https://drive.google.com/file/d/1vs1DAO0zon9peHXj2wiicfZ2EOgv1gAz/view?usp=drive_link | D12: https://drive.google.com/file/d/1Y7nHfhqIUit0eRM9Jh89nQyQ0ST6Ram4/view?usp=drive_link | E12: https://drive.google.com/file/d/18f-bIUQ1qopGBuokBx2wPdKxUfD_hktr/view?usp=drive_link
... A165: Technology 2 | B165: Technology | C165: https://drive.google.com/file/d/1b76F7Z9KqYEzu-ZGbPil-n1wCQ1icWDP/view?usp=drive_link | D165: https://drive.google.com/file/d/1qJsMXNDsgNUSyHuxy7oLTQ0vX3cib_rx/view?usp=drive_link | E165: https://drive.google.com/file/d/19PovqeZqQ19296P4ohGLzp5FeqX9o-Ou/view?usp=drive_link

Sheet Sheet17
A1: Text | B1: Link | J1: cat | K1: https://vnmedia2.monkeyuni.net/upload/cms_platform/audio/1f798884bb67c1552f4a6e609e9730ba.mp3
A2: cat | B2: https://vnmedia2.monkeyuni.net/upload/cms_platform/audio/1f798884bb67c1552f4a6e609e9730ba.mp3 | J2: cow | K2: https://vnmedia2.monkeyuni.net/upload/cms_platform/audio/b61bfdf8556d097b67e720893fdd0992.mp3
A3: cat | B3: https://vnmedia2.monkeyuni.net/upload/cms_platform/audio/966399a85ef74cd20b21c3834c99d587.mp3 | J3: dog | K3: https://vnmedia2.monkeyuni.net/upload/cms_platform/audio/a562b4096ece55b8f6496dd73499e028.mp3
A4: cat | B4: https://vnmedia2.monkeyuni.net/upload/cms_platform/audio/ctuKjk85z7lyA8PjeC8Qz7U0aadSfegF.mp3 | J4: pig | K4: https://vnmedia2.monkeyuni.net/upload/cms_platform/audio/899658152eefc8ec0628b964ff472833.mp3
A5: cat | B5: https://vnmedia2.monkeyuni.net/upload/cms_platform/audio/dVLQZ3bahYosT3efqihjA0i7cFo0zpRD.mp3 | J5: bird | K5: https://vnmedia2.monkeyuni.net/upload/cms_platform/audio/1d8d983899b8999c837ecb16d7a71bca.mp3
A6: cat | B6: https://vnmedia2.monkeyuni.net/upload/cms_platform/audio/ | J6: duck | K6: https://vnmedia2.monkeyuni.net/upload/cms_platform/audio/9dfac0c99e662a02abed90d90d63e641.mp3
A7: cat | B7: https://vnmedia2.monkeyuni.net/upload/cms_platform/audio/248dcbe6a1574e3b29564935898ec774.mp3 | J7: frog | K7: https://vnmedia2.monkeyuni.net/upload/cms_platform/audio/f9416eaf1ec03dc8eea7104954117352.mp3
A8: cat | B8: https://vnmedia2.monkeyuni.net/upload/cms_platform/audio/f0ecdf9610b1b90a193ee715a575d42a.mp3 | J8: bus | K8: https://vnmedia2.monkeyuni.net/upload/cms_platform/audio/76040ad3d753a2187c216538efc82461.mp3
A9: cat | B9: https://vnmedia2.monkeyuni.net/upload/cms_platform/audio/ecea70bb9a5a8cb09a39bfc572bbac06.mp3 | J9: car | K9: https://vnmedia2.monkeyuni.net/upload/cms_platform/audio/c60db4ed8ef63e162ddc06c935167bfe.mp3
A10: cat | B10: https://vnmedia2.monkeyuni.net/upload/cms_platform/audio/d04559ef00e1dc70adb9152fb0fa2d6e.mp3 | J10: truck | K10: https://vnmedia2.monkeyuni.net/upload/cms_platform/audio/3a5c93f0d1326a6286c969c2b89903f4.mp3
A11: cat | B11: https://vnmedia2.monkeyuni.net/upload/cms_platform/audio/421545776bb02d8af4d03e413a1eb6dd.mp3 | J11: van | K11: https://vnmedia2.monkeyuni.net/upload/cms_platform/audio/6e48a9d614f00717aaf3a4bd19d3d825.mp3
A12: cat | B12: https://vnmedia2.monkeyuni.net/upload/cms_platform/audio/1c312d465f390faaba77436208540a22.mp3 | J12: train | K12: https://vnmedia2.monkeyuni.net/upload/cms_platform/audio/7e48ffafe52e39ae602152ff19c10e9e.mp3
... A78: car | B78: https://vnmedia2.monkeyuni.net/upload/cms_platform/audio/ed8d656682cc4e04a8de25493308a68b.mp3 | J78: goat | K78: https://vnmedia2.monkeyuni.net/upload/cms_platform/audio/4aadf21797b6863a7d287a2f5d1e5aae.mp3
A79: car | B79: https://vnmedia2.monkeyuni.net/upload/cms_platform/audio/1c733560642de73b39f13d9f9d07078d.mp3
A80: car | B80: https://vnmedia2.monkeyuni.net/upload/cms_platform/audio/392f541456f5f87a582b1c7a6923c095.mp3
A81: car | B81: https://vnmedia2.monkeyuni.net/upload/cms_platform/audio/0b05d0701722aa87641ddc9df4659181.mp3
A82: car | B82: https://vnmedia2.monkeyuni.net/upload/cms_platform/audio/219a27feccc8fdb96591866a6d71b228.mp3
A83: car | B83: https://vnmedia2.monkeyuni.net/upload/cms_platform/audio/dc197befe43e23c0b8e5f3113936dd04.mp3
A84: car | B84: https://vnmedia2.monkeyuni.net/upload/cms_platform/audio/b9385441cf34a5f91e099d8c8c2a03fa.mp3
A85: truck | B85: https://vnmedia2.monkeyuni.net/upload/cms_platform/audio/3a5c93f0d1326a6286c969c2b89903f4.mp3
A86: truck | B86: https://vnmedia2.monkeyuni.net/upload/cms_platform/audio/9rJNAg7inASXQm3dvmCFV8u2VzXDEzCH.mp3
A87: truck | B87: https://vnmedia2.monkeyuni.net/upload/cms_platform/audio/d1e014962675682c35d4fcdb95bb45a7.mp3
A88: truck | B88: https://vnmedia2.monkeyuni.net/upload/cms_platform/audio/284c06468a3fd22a10ffb157e6fdd8c6.mp3
A89: van | B89: https://vnmedia2.monkeyuni.net/upload/cms_platform/audio/6dab791639ace7c2fc92ca2d58f45eaa.mp3
A90: van | B90: https://vnmedia2.monkeyuni.net/upload/cms_platform/audio/6e48a9d614f00717aaf3a4bd19d3d825.mp3
... A864: mouse | B864: https://vnmedia2.monkeyuni.net/upload/cms_platform/audio/18a14839a1db5e6a4cf91d8535d98238.mp3

Sheet Flow có truyện video
A1: Unit | B1: Material catagory | C1: Tên | D1: Video | E1: Thumb intro | F1: Audio tên truyện | G1: Text truyện | H1: Audio | I1: Image
A2: 1 | B2: Song | C2: Animals' Sounds | D2: https://drive.google.com/file/d/1rcFOFrk6vL6aTPD8ULzCM3AdHkU2pVsL/view?usp=sharing
A3: 2 | B3: Chant | C3: I Want to Play | D3: https://drive.google.com/file/d/1bw3h17-eYpiHeSV1iMwaifLc1Z-XeKV8/view?usp=drive_link
A4: 3 | B4: Song | C4: Rainbow Song | D4: https://drive.google.com/file/d/1soMm1wwKhbNM98UXyGu116CECuWVygPW/view?usp=drive_link
A5: 4 | B5: Song | C5: My Favorite Rooms | D5: https://drive.google.com/file/d/1KYsS9-zNXukSNMeAiIBDfIfyhEu9c-mb/view?usp=drive_link
A6: 5 | B6: Song | C6: Shapes Around Me | D6: https://drive.google.com/file/d/1HawdBMnSZ9QdU5-3BBZc6xctgGLTd3FP/view?usp=drive_link
A7: 6 | B7: Chant | C7: Go and Hide | D7: https://drive.google.com/file/d/1fN_vjB6u678H6LbBpALbVJtxE0Jggr46/view?usp=drive_link
A8: 7 | B8: Chant | C8: Fruit Salad | D8: https://drive.google.com/file/d/13dv1xwdYNy1Gl_u5IjesDJ0_9_sgnV7y/view?usp=drive_link
A9: 8 | B9: Song | C9: Shapes Around Me | D9: https://drive.google.com/file/d/1HawdBMnSZ9QdU5-3BBZc6xctgGLTd3FP/view?usp=drive_link
A10: 9 | B10: Song | C10: When I Grow Up | D10: https://drive.google.com/file/d/1Cwjv-xxGm16Pbp4_gF0cbrkIM67F16gl/view?usp=drive_link
A11: 10 | B11: Song | C11: Peek-A-Boo | D11: https://drive.google.com/file/d/1jHRr-uB_H-fUJtCAU5BoasbgUh-eTyKZ/view?usp=drive_link
A12: 11 | B12: Song | C12: What Room Is It? | D12: https://drive.google.com/file/d/1dHT8PlYKtjBEGmSSa-bl__VQE4Y_i2_z/view?usp=sharing
A13: 12 | B13: Chant | C13: Let's Go Outside! | D13: https://drive.google.com/file/d/1DPStwj6kGy0cxqxcn5g-A4_o-PtLI3T_/view?usp=drive_link
A14: 13 | B14: Chant | C14: I Have No Fruits! | D14: https://drive.google.com/file/d/134lQ3cpoSGZPstB-35HCyEOCEzJEK57d/view?usp=sharing
A15: 14 | B15: Story | C15: The drinks | E15: https://drive.google.com/file/d/1xT9b6_6km31L--OkVM2O-dO45EyULFv9/view?usp=drive_link | F15: https://drive.google.com/file/d/132ZJfgEN2eg74Rf8eJnxmckzuU-gHgC_/view?usp=drive_link | G15: The juice. | H15: https://drive.google.com/file/d/1LUCftvQ7zIOgurN8tE0QjD9PVkhrkj4j/view?usp=drive_link | I15: https://drive.google.com/file/d/1xhatsdHFO5ThiEroWrJDpjlXUlqoPPHL/view?usp=drive_link
G16: The tea. | H16: https://drive.google.com/file/d/1RADFhm8Dws2GcYRPlT71Qgz4tkkL5-24/view?usp=drive_link | I16: https://drive.google.com/file/d/1Fw50nKqFKIir6uwGzwFeP0LmA19LaDoF/view?usp=drive_link
G17: The milk. | H17: https://drive.google.com/file/d/11rN4BFx7xQ9n55JFwDm175p4E2ZDKzGS/view?usp=drive_link | I17: https://drive.google.com/file/d/1smG7jyUB6KHEPbuSDA3kqMqWjOGMwFIB/view?usp=drive_link
G18: The hot chocolate. | H18: https://drive.google.com/file/d/13jwsBJWfR0ChYqocFTXmX4vYcAa5Q_NS/view?usp=drive_link | I18: https://drive.google.com/file/d/1bqK4V-7R2b1Ih0pdhQg61hzJqoWysVpg/view?usp=drive_link
G19: The water. | H19: https://drive.google.com/file/d/1d_fuBz-yUERJ_jtfqgQ4qjBqDnxa26Uw/view?usp=drive_link | I19: https://drive.google.com/file/d/1aP0zQ9Pjy2L5_yBcpGzThoaD3OpNj8Tr/view?usp=drive_link
G20: The coffee. | H20: https://drive.google.com/file/d/1snjVjy3Z98btQwPls3A6ZlK0L5QFMid3/view?usp=drive_link | I20: https://drive.google.com/file/d/1WhMHnZn695SR0DGb2uofOabpUTNA6yvX/view?usp=drive_link
G21: The beer. | H21: https://drive.google.com/file/d/1yBhhPIXJZSBvFG2Exk8xGlLaH4eUQxlL/view?usp=drive_link | I21: https://drive.google.com/file/d/1ZEAjaTkiXfzy5eQNNTxavajCuxYtYsTI/view?usp=drive_link
G22: The wine. | H22: https://drive.google.com/file/d/1Xl86TAHL_vo4lC3jNHRK8R9oD-qNofTb/view?usp=drive_link | I22: https://drive.google.com/file/d/1OH199ZEYEkHg1MNGDO82H7sBZegXeNuG/view?usp=drive_link
G23: The smoothie. | H23: https://drive.google.com/file/d/1S12_RGrmbm1ykuxTr5vR0o3C0DB3O-Wi/view?usp=drive_link | I23: https://drive.google.com/file/d/1g8xiwTBFrZ8jU7V6CKBycZg5mKOE4umN/view?usp=drive_link
G24: The bubble tea. | H24: https://drive.google.com/file/d/1tKALrZPZ0k_O2gd2ydf2zRy_nr_lp4yf/view?usp=drive_link | I24: https://drive.google.com/file/d/1hczRk2UfmuHR8ALVd8CEjoTgIDcRN7qx/view?usp=drive_link
A25: 15 | B25: Story | C25: Beans | E25: https://drive.google.com/file/d/1Srl338ewEUuXhF3MyH3BeOQk6EzZuQq9/view?usp=drive_link | F25: https://drive.google.com/file/d/1cPnLfisZ45hKSlMjm_usUpLvO3fqKy9l/view?usp=drive_link | G25: Beans, beans! | H25: https://drive.google.com/file/d/1l4tw2bjHKxYg0nI9LqE-ASG38qk3fowq/view?usp=drive_link | I25: https://drive.google.com/file/d/15Oq5q2g0XfwLI29tuKe2F4vyBa5tRThh/view?usp=drive_link
G26: They're good for your heart. | H26: https://drive.google.com/file/d/1oJf4HDtcX6jWb4g5AoBKTdfXGP_ipsjn/view?usp=drive_link | I26: https://drive.google.com/file/d/1K9J4u6eigPfM2lZxEScCFz1545tDZJN9/view?usp=drive_link
G27: The more you eat, the stronger you are. | H27: https://drive.google.com/file/d/110MXKeoQWhe0Lm4CVNVG49PFC7Mz7Q7J/view?usp=drive_link | I27: https://drive.google.com/file/d/1VaTLDnwBV86qk2zfzryY8nLoazH9TDjG/view?usp=drive_link
G28: Beans, beans! | H28: https://drive.google.com/file/d/1l4tw2bjHKxYg0nI9LqE-ASG38qk3fowq/view?usp=drive_link | I28: https://drive.google.com/file/d/1n5tohJe_EZjKFP_-sX5j_3NkhLp-WMjm/view?usp=drive_link
G29: They're good for your tummy. | H29: https://drive.google.com/file/d/1flaoXvsRagOHLQgWgnpTjYr2baGIAyW1/view?usp=drive_link | I29: https://drive.google.com/file/d/1zDDS4IpxWsZAf692hUFgOng-J0htMMcv/view?usp=drive_link
G30: I ate too much. My tummy feels funny. | H30: https://drive.google.com/file/d/1_rP5XNQR_vXdg0VN336YCjaWAz4sYUAP/view?usp=drive_link | I30: https://drive.google.com/file/d/1VvpvzKXBbYvJBfcfSEV-D9WCEAK4yLBU/view?usp=drive_link
G31: Beans, beans! | H31: https://drive.google.com/file/d/1l4tw2bjHKxYg0nI9LqE-ASG38qk3fowq/view?usp=drive_link | I31: https://drive.google.com/file/d/1-N_OJW_sUCOzUFr8wd3_f3QOottxeDIe/view?usp=drive_link
G32: The magical fruit. | H32: https://drive.google.com/file/d/1IfJUDaedO4-RyRaKykMrsegPapD1ompY/view?usp=drive_link | I32: https://drive.google.com/file/d/19552KM_aSn6nveiPqEpwWFIS_y3gBIRa/view?usp=drive_link
G33: The more you eat, | H33: https://drive.google.com/file/d/1LqUfMS0Qu4164CYjqdIYZZ0NWkaAwiHu/view?usp=drive_link | I33: https://drive.google.com/file/d/1BWpVFqCLtn5Pz_uXCzNX1eSrLjEkP8gK/view?usp=drive_link
G34: The more you TOOT! | H34: https://drive.google.com/file/d/1fGWy9-TKNkGNqGe_jUatOAmbMRxfMhGg/view?usp=drive_link | I34: https://drive.google.com/file/d/1s_Z2_y2yggce2Ik6NR5QQdUafrId-0li/view?usp=drive_link
A35: 16 | B35: Song | C35: My Messy Room | D35: https://drive.google.com/file/d/1xmwOdOFDthibRMxEtE1IVac4GCn_GX7y/view?usp=drive_link
A36: 17 | B36: Chant | C36: On the farm | D36: https://drive.google.com/file/d/18HtCQT26QKcSFz4OWHiXHSSYXEEvT9zK/view?usp=sharing
A37: 18 | B37: Song | C37: On the Road | D37: https://drive.google.com/file/d/18E18a5EE5PwVJi9LC0c-9m-catU6O1u6/view?usp=drive_link
A38: 19 | B38: Chant | C38: How Are You? | D38: https://drive.google.com/file/d/1oQKHDWC4XASj2aXlAmr12Sh9SG8XjUVK/view?usp=sharing
A39: 20 | B39: Story | C39: Touch Your Body | E39: https://drive.google.com/file/d/1AKreLHulK00RJDBMnknqZ7z7p7go_GLg/view?usp=drive_link | F39: https://drive.google.com/file/d/1o7Jxohw6Yoz7MgzePC9PovgJ2UZcAlQT/view?usp=drive_link | G39: Touch your eyes. | H39: https://drive.google.com/file/d/1MzRyvn_wUOlrn9-TguG_8jhKE1zVldIO/view?usp=drive_link | I39: https://drive.google.com/file/d/1qImT4FIuw_Y-moEjq_1C4df9WQzRNipV/view?usp=drive_link
G40: Touch your ears. | H40: https://drive.google.com/file/d/1JepkWXWM8ctNizRWUN39tVvmFN6B2g86/view?usp=drive_link | I40: https://drive.google.com/file/d/1HmKAdjxMcyFBOWWWFrO5w7PgkKerCb3j/view?usp=drive_link
G41: Touch your nose. | H41: https://drive.google.com/file/d/1kd8--Z0HaJNWrZW7Lhpl4pDLMkJ_Pmok/view?usp=drive_link | I41: https://drive.google.com/file/d/1xIaz2Zor1GPSukhPw8cNHi7yDVrH9Ycj/view?usp=drive_link
G42: Touch your cheeks. | H42: https://drive.google.com/file/d/10d6Bt_AOu8OqUzvjSPIteJ-7Uw2JBGJo/view?usp=drive_link | I42: https://drive.google.com/file/d/1LSxqU5-kzIGRzh1oD9lArK7PDKpqILGF/view?usp=drive_link
G43: Touch your mouth. | H43: https://drive.google.com/file/d/1A8n6FbQCIsNmAvI2wz36zgC7mY8Wkhdm/view?usp=drive_link | I43: https://drive.google.com/file/d/1hNwJZKzXXOlUbmv74zFSeK4EVH-EJTjU/view?usp=drive_link
G44: Touch your chin. | H44: https://drive.google.com/file/d/1Hy3uIEr_xRcHXIl3wr_dGO8a0TqqG4Fk/view?usp=drive_link | I44: https://drive.google.com/file/d/1_KvACiZJUJ4Il3Sk7OyhjNmGTWEaGMbN/view?usp=drive_link
A45: 21 | B45: Song | C45: My Little Friends | D45: https://drive.google.com/file/d/1wDTuXMLANSTL79whMRHUMZbewK6tX79u/view?usp=drive_link
A46: 22 | B46: Song | C46: Let’s Go Camping | D46: https://drive.google.com/file/d/1AOUr6O6josE8UCIzwGumLc_JJKYOTW1R/view?usp=sharing
A47: 23 | B47: Song | C47: Where’s Your Picture? | D47: https://drive.google.com/file/d/1WJxKa5z3XD0j7wiyXaJW9aNNPwc9e0Nl/view?usp=drive_link
A48: 24 | B48: Chant | C48: Animal Friends | D48: https://drive.google.com/file/d/1a5k3lZyA3fSIpltzihOt9kgknJp20Fb_/view?usp=sharing
A49: 25 | B49: Song | C49: I'm Hungry | D49: https://drive.google.com/file/d/1aN8FrU8_MOC_akP8olLzYT9lEWVPZGec/view?usp=drive_link
A50: 26 | B50: Song | C50: My Favorite Rooms | D50: https://drive.google.com/file/d/1KYsS9-zNXukSNMeAiIBDfIfyhEu9c-mb/view?usp=drive_link
A51: 27 | B51: Chant | C51: The Baker | D51: https://drive.google.com/file/d/1Z1DBvzmkmCP6UPlA_hXBAhDv50R62xMO/view?usp=drive_link
A52: 28 | B52: Song | C52: Family Harmony | D52: https://drive.google.com/file/d/1TAQJIGxyj5dnKyLvY80SunZKB3VSmaIm/view?usp=sharing
A53: 29 | B53: Song | C53: I Am a Young Firefighter | D53: https://drive.google.com/file/d/1sVQcnreRdA1UL-U4XdL7uizlIPmznyEb/view?usp=drive_link
A54: 30 | B54: Song | C54: I Love My Pets | D54: https://drive.google.com/file/d/1BsJ3KnX0Mp_Hc7Mnauzcx3a1wwNeSd5o/view?usp=sharing
A55: 31 | B55: Chant | C55: How Is the Weather? | D55: https://drive.google.com/file/d/1SxAlveyn7AyKkC6C2UifHpoBz4NTXK3g/view?usp=sharing
A56: 32 | B56: Chant | C56: What's That Sound? | D56: https://drive.google.com/file/d/1iP1Ify4WtY1mmxtwHJwbb_pRWoAz20vA/view?usp=sharing
A57: 33 | B57: Story | C57: Places in the city | E57: https://drive.google.com/file/d/1kBdHBJVNACy7l52_-bDPlREujfBqhlpr/view?usp=drive_link | F57: https://drive.google.com/file/d/1EC4WxStqy86wXuwqq9OX6W4RlJHZNgph/view?usp=drive_link | G57: The movie theater. | H57: https://drive.google.com/file/d/1ytizPWVK8wDFbqU9MiDqnhkpE24J0YO2/view?usp=drive_link | I57: https://drive.google.com/file/d/1iary8z3clYqEHpJJtITuLHKQ55rcoriP/view?usp=drive_link
G58: The fire station. | H58: https://drive.google.com/file/d/1SfMWZnb9K_Y5tyl9FDJN_A3Zz9pCE6kD/view?usp=drive_link | I58: https://drive.google.com/file/d/1ggEdNsNQQloSeFyWEivRVquSkgC0OdPl/view?usp=drive_link
G59: The police station. | H59: https://drive.google.com/file/d/15XoIuTFsB1yDmfp3E9KGmCwNDLePH1JS/view?usp=drive_link | I59: https://drive.google.com/file/d/1Upjha1dD4CcbkjKuzy0EwBV5p46-qVWW/view?usp=drive_linkk
G60: The museum. | H60: https://drive.google.com/file/d/1qcvYXfZX3x3HhCIUeuyaQkjwYSTJWNH9/view?usp=drive_link | I60: https://drive.google.com/file/d/1E4h02rYYsdGWiHGP7k03mN37viicEM7b/view?usp=drive_link
G61: The grocery store. | H61: https://drive.google.com/file/d/1jcGIii1wfUQJdNeMvxcVHMiVM5B4Okhx/view?usp=drive_link | I61: https://drive.google.com/file/d/1NcA01wIiFsYihRXaqFia1GHSbQ_YzanB/view?usp=drive_link
G62: The bakery. | H62: https://drive.google.com/file/d/1w7gwzjiT55QWnGhz6dIYmSgxff4dd8jt/view?usp=drive_link | I62: https://drive.google.com/file/d/1-ZWFPmAr9sXpQcHxOmyxYYjFEfRExGBL/view?usp=drive_link
G63: The book store. | H63: https://drive.google.com/file/d/1DeB1EKUFWSLCl6N9_dgNjCLwquWkPZmH/view?usp=drive_link | I63: https://drive.google.com/file/d/1294vHLyK8Er81eWJK-Kpb0SXuZ3E0xVR/view?usp=drive_link
G64: The barber shop. | H64: https://drive.google.com/file/d/1jXwya2h0DuJQQ45T_UK6hC3_2qg1Mwmr/view?usp=drive_link | I64: https://drive.google.com/file/d/1jp3Ou6-Pkt-qWBlFRrnFCgy8Y2cC_p41/view?usp=drive_link
A65: 34 | B65: Story | C65: Places I go | E65: https://drive.google.com/file/d/1ftkipLfo6nQ6Xaiw7s1jUC5Pivt7YFk4/view?usp=drive_link | F65: https://drive.google.com/file/d/1zVfPCLYI2rTZhAM0N4e_yBxw9OmUJMIB/view?usp=drive_link | G65: The bus goes to the city. | H65: https://drive.google.com/file/d/1QokWvGASBwnGClhu94W7SfuSN5U71QhP/view?usp=drive_link | I65: https://drive.google.com/file/d/1RnuyjeTSxrIFhKGBTuCASBOQQndz2Qj-/view?usp=drive_link
G66: The police car goes to the crash. | H66: https://drive.google.com/file/d/1mbRhCZVDYIf5ksJaNeZaDVFfLGfYBzMb/view?usp=drive_link | I66: https://drive.google.com/file/d/1pGbuXxgeyYpZp5oR6im3pv1_yo8tzNBU/view?usp=drive_link
G67: The fire truck goes to the fire. | H67: https://drive.google.com/file/d/1B2Jb8tPcR1CUkWj5tspVq6drFtOPp4zF/view?usp=drive_link | I67: https://drive.google.com/file/d/1fR7KC82Q4vvQCRNDC2Ffqzueg4IRC9Yn/view?usp=drive_link
G68: The ambulance goes to the hospital. | H68: https://drive.google.com/file/d/1ZPhmHAMQ-Q0Jdp085o4hvJiw4ykUOHiX/view?usp=drive_link | I68: https://drive.google.com/file/d/1l1yyn4M02_rBZEJYJghlSbV-83QCVbDq/view?usp=drive_link
G69: The train goes to the train station. | H69: https://drive.google.com/file/d/1zCTd8v2HgUBQYSswmC8Z6aAZDusBAzDj/view?usp=drive_link | I69: https://drive.google.com/file/d/1Kx1ztbRkU9Z_KbexP1ziJano9uV0LA6x/view?usp=drive_link
G70: The ship goes to the port. | H70: https://drive.google.com/file/d/1ImUasDcU7MNhdYi1EC52Zzt3_U9_UnQt/view?usp=drive_link | I70: https://drive.google.com/file/d/1WlPfX5S1Tyd6c0l92ybM47Ox-8J6ny46/view?usp=drive_link
G71: The plane goes to the airport. | H71: https://drive.google.com/file/d/1K0Pqc5rugVWSgrl6jaRt0UPlnfTVSrHa/view?usp=drive_link | I71: https://drive.google.com/file/d/11p2BwLOySa_-75METilS4YT78Vx11gP8/view?usp=drive_link
G72: The submarine goes underwater. | H72: https://drive.google.com/file/d/1eDYXOLyNJ0w0inPpbO1YSQYQZ77PcTzI/view?usp=drive_link | I72: https://drive.google.com/file/d/1TUv_Y9XfC6KjmdnjfK1Wm3Tb6MWCf2KL/view?usp=drive_link
G73: The rocketship goes to space! | H73: https://drive.google.com/file/d/19oF5c5nEOBrHB774nzc1y-eOIBisNiyx/view?usp=drive_link | I73: https://drive.google.com/file/d/1y4Y6NB_TFdc0BNxPQWUIarVXnp7wUjUM/view?usp=drive_link
G74: Oh! Hello! | H74: https://drive.google.com/file/d/14WoZOzN2Qp6uOabLimtOqPO7DIFPpMWA/view?usp=drive_link | I74: https://drive.google.com/file/d/1RzaXsfq2NMWZuOp9g9EEB5wRVoIFySmA/view?usp=drive_link
A75: 35 | B75: Story | C75: We love to play in the park | E75: https://drive.google.com/file/d/1quTaWut82s708Yda-ugdQ-g8hCFrPoUg/view?usp=drive_link | F75: https://drive.google.com/file/d/17GzoaVzLDYbkdHo1O35OEmO2okizPCnQ/view?usp=drive_link | G75: Monkey loves to hang and climb | H75: https://drive.google.com/file/d/198nH9OZ-6Mq2UgMd4g7kCbEUW9erSPua/view?usp=drive_link | I75: https://drive.google.com/file/d/1W8kyYXmdWgAQzyTlWfv2cZCFd9MR0f8B/view?usp=drive_link
G76: on the climbing frame. | H76: https://drive.google.com/file/d/1WKJi46PrIPXA6rm8LDmxqQXj7MPv3VKt/view?usp=drive_link | I76: https://drive.google.com/file/d/1Uh__RsI1WCQYtdyS-9Igvz_fXsoUsFIj/view?usp=drive_link
G77: Penguin loves to slip and slide | H77: https://drive.google.com/file/d/1fSzHNCoNrVx1gSaaKLZiO0E5Ya1KNUXr/view?usp=drive_link | I77: https://drive.google.com/file/d/1vt67Vq0lCfmdHL2p0EpK_914w7kaEkRB/view?usp=drive_link
G78: down the slide. | H78: https://drive.google.com/file/d/1Q1Mh9MTWrZGd8AUq5BPQxX9XAynM5blv/view?usp=drive_link | I78: https://drive.google.com/file/d/15Zas6MNVzqntstqvfS_k5my0P3s2zi-Z/view?usp=drive_link
G79: Sam loves to swing back and forth | H79: https://drive.google.com/file/d/13yZCrS7iZjU-A12w7lnUhQQynW6-OlIn/view?usp=drive_link | I79: https://drive.google.com/file/d/1dR4kRNhFZnD75pRrRgz0fVTQP_fgj4zL/view?usp=drive_link
G80: on the swing. | H80: https://drive.google.com/file/d/1FHaOqA2HcBZwFkwjNJ_F4lvMHYxcqKn9/view?usp=drive_link | I80: https://drive.google.com/file/d/1X3DqPj5RVvIlBjeoWwxbwoeMPfppTyu3/view?usp=drive_link
G81: Cheetah loves to twirl and spin | H81: https://drive.google.com/file/d/1kiZi8-sHb0IlJghdjdWZ7RBwdlKXpBmr/view?usp=drive_link | I81: https://drive.google.com/file/d/1aKJ-17Ju0x9yZk-OzLGfa3vhn2imIgBq/view?usp=drive_link
G82: on the merry-go-round. | H82: https://drive.google.com/file/d/1cX5P12cDTvxU1GELS8Z3fP3Niu9i-Su0/view?usp=drive_link | I82: https://drive.google.com/file/d/18N8Uz931KofNjHRaPmy1oxP5egzxyfNK/view?usp=drive_link
G83: Mouse loves to jump up and down | H83: https://drive.google.com/file/d/1AnVUD-yB3qBwBDMfTwNztB8Gy6hLF-N9/view?usp=drive_link | I83: https://drive.google.com/file/d/1Amx8Oy1CEhlO6C-htM5oSQ-g5LdzCIC2/view?usp=drive_link
G84: on the seesaw. | H84: https://drive.google.com/file/d/1I8xlgtZX50Pd_IxAd5foxymP0isxho5y/view?usp=drive_link | I84: https://drive.google.com/file/d/1Cl7qdhBMl9dgf6vURTElCUxNy66veJ-W/view?usp=drive_link
G85: Elephant loves to sit down. | H85: https://drive.google.com/file/d/1P47nHwcKAN6PzgiWrKpVh9WCFs7Y6tUI/view?usp=drive_link | I85: https://drive.google.com/file/d/1vqDcT2Aj7HtfmBrba2jB9kRsAo79iO2x/view?usp=drive_link
G86: Oh, no, Elephant! Not there! | H86: https://drive.google.com/file/d/1NDC5V88yMhYNTMUO4bEki20vWMfR7MQw/view?usp=drive_link | I86: https://drive.google.com/file/d/1wlVP0DDiiCYWN6DWa0PM-DGpH9szZwMS/view?usp=drive_link
A87: 36 | B87: Story | C87: Sea Animals | E87: https://drive.google.com/file/d/19PMChJSqJNXNIxVFGvifS60UshAfj8K2/view?usp=drive_link | F87: https://drive.google.com/file/d/1kSjcTmgr82_wMDdrxJ1Osg_4PhhwvrH7/view?usp=drive_link | G87: The shark. | H87: https://drive.google.com/file/d/1VMep11-Z2o16kofEEBDDlSs2nLizVAZi/view?usp=drive_link | I87: https://drive.google.com/file/d/1TFC_0iskuiptj9KrjIFBW6RtMkXcW_1f/view?usp=drive_link
G88: The whale. | H88: https://drive.google.com/file/d/1vEb8LgcHtX9Q0yD2ishhRn5-2PgEpMTO/view?usp=drive_link | I88: https://drive.google.com/file/d/1L5urlTVg3dFbSqw44utFFDPqY51UIP13/view?usp=drive_link
G89: The jellyfish. | H89: https://drive.google.com/file/d/1qXJJAZaGU9BK8UNjIFQ_2pMRbAc3HU5E/view?usp=drive_link | I89: https://drive.google.com/file/d/1RPni3Ia4GpV8SMR-zfwNZUl3jVj5Z2D8/view?usp=drive_link
G90: The stingray. | H90: https://drive.google.com/file/d/1MYTDCBmCm9m2WCgxYBBas5erGSRFW6hB/view?usp=drive_link | I90: https://drive.google.com/file/d/1cLdmpWNH7Jd7Q8BrFmW8TAx0OdZSXlB6/view?usp=drive_link
G91: The dolphin. | H91: https://drive.google.com/file/d/11HverXVKADi7lVNQGyg3Kw4o-w97sggL/view?usp=drive_link | I91: https://drive.google.com/file/d/11fxEsSqO9AdGGSpwMOFz1fxz-j-oijae/view?usp=drive_link
G92: The turtle. | H92: https://drive.google.com/file/d/16LCp66GeO3JfbxWHiCnbuYk-NH0Wz_GM/view?usp=drive_link | I92: https://drive.google.com/file/d/17xQa0c11WSFIRjg9FGJYlJD1o2tT0tUN/view?usp=drive_link
G93: The starfish. | H93: https://drive.google.com/file/d/1ueGEBpJLs03W5GioKdeEz6YRFXqnBcQZ/view?usp=drive_link | I93: https://drive.google.com/file/d/1EQQF7CxTsIQNSNpvBLmbIjCc-_rygzH4/view?usp=drive_link
G94: The seal. | H94: https://drive.google.com/file/d/13vdLwuSNUEvLBltjZL2uTMgBOitKc6ql/view?usp=drive_link | I94: https://drive.google.com/file/d/1Qh0QIKYkdqvo6OmBiXJA5Ofgvfy3G9zn/view?usp=drive_link
A95: 37 | B95: Song | C95: On the Road | D95: https://drive.google.com/file/d/18E18a5EE5PwVJi9LC0c-9m-catU6O1u6/view?usp=drive_link
A96: 38 | B96: Story | C96: The garden | E96: https://drive.google.com/file/d/1Va7MlgD92IrkMuH-7zexiPo3-xN42pKb/view?usp=drive_link | F96: https://drive.google.com/file/d/1tewhII6PllTG9SKe4EQKn9MTha_hGO3Z/view?usp=drive_link | G96: The flowers. | H96: https://drive.google.com/file/d/1kRVipG5rFox1pV9SV71q3R6Q7fDG4d1P/view?usp=drive_link | I96: https://drive.google.com/file/d/1Jw4yftc2O7IPhPpDy_UN9-KlJdbjyoui/view?usp=drive_link
G97: The trees. | H97: https://drive.google.com/file/d/18WfArFV-BPGKSOGcvUmx9j-x6ynuUUbn/view?usp=drive_link | I97: https://drive.google.com/file/d/1nbPWHxQKCQuzmsDGlwL2YC3p4IA_-PMG/view?usp=drive_link
G98: The birds. | H98: https://drive.google.com/file/d/1SQd1owSp4Po_Tszjp95DtAs_PinU91Su/view?usp=drive_link | I98: https://drive.google.com/file/d/1igHeIXuEnW-1p1LD2ef0L9w264N-gCwL/view?usp=drive_link
G99: The grass. | H99: https://drive.google.com/file/d/1qIpS-VNDYTKoqstEBkBR-AVZM6FRwYMk/view?usp=drive_link | I99: https://drive.google.com/file/d/1aozFakOYz61WvwajmXwz6s67TFuXIqre/view?usp=drive_link
G100: The fences. | H100: https://drive.google.com/file/d/1YJgUeXUl8gI1RZSEY7ORQvStjUThHlDX/view?usp=drive_link | I100: https://drive.google.com/file/d/1y6JIIC0-bH4jvt1I6BkRO1WYL_SC7t2L/view?usp=drive_link
...

Sheet MJ 5.0_Level 0_Logic lặp từ
A1: 1. Topic words
A2: Lesson | B2: Flow | C2: cat | D2: cow | E2: dog | F2: pig | G2: bird | H2: duck | I2: bat | J2: frog | K2: hug | L2: kiss | M2: give | N2: put | O2: smile | P2: cry | Q2: sleep | R2: take
A3: Lesson 1 | B3: 1 | C3: 1 | D3: 1 | E3: 1 | F3: 1 | K3: 1 | L3: 1 | M3: 1 | N3: 1
A4: Lesson 2 | B4: 1 | C4: 1 | D4: 1 | G4: 1 | H4: 1 | K4: 1 | L4: 1 | O4: 1 | P4: 1
A5: Lesson 3 | B5: 1 | E5: 1 | F5: 1 | I5: 1 | J5: 1 | M5: 1 | N5: 1 | Q5: 1 | R5: 1
A6: Lesson 4 | B6: 1 | G6: 1 | H6: 1 | I6: 1 | J6: 1 | O6: 1 | P6: 1 | Q6: 1 | R6: 1
A9: 2. Sight words
A10: Lesson | B10: Flow | C10: the | D10: of | E10: and | F10: a | G10: to | H10: in | I10: is | J10: you | K10: this | L10: it | M10: can | N10: he
A11: Lesson 1 | B11: 1 | C11: 1 | D11: 1 | E11: 1 | F11: 1 | G11: 1 | H11: 1
A12: Lesson 2 | B12: 1 | C12: 1 | D12: 1 | I12: 1 | J12: 1 | K12: 1 | L12: 1
A13: Lesson 3 | B13: 1 | E13: 1 | F13: 1 | K13: 1 | L13: 1 | M13: 1 | N13: 1
A14: Lesson 4 | B14: 1 | G14: 1 | H14: 1 | I14: 1 | J14: 1 | M14: 1 | N14: 1

Sheet Sheet9
A1: Material catagory | B1: Video kindy/ Truyện MS | C1: Link | D1: Link sản phẩm đã sửa | E1: pick | G1: Yêu cầu sửa: - Thay intro Kindy bằng intro Monkey Junior (cần ND duyệt) - Bỏ phần ôn từ vựng - Giữ phần song/ chant | J1: MJ trùng với Dolch | K1: MJ | L1: Dolch SW | M1: Dolch trùng MJ | P1: Tên truyện | Q1: link psd/ png | R1: yêu cầu (size 360x480) | S1: link thumb
A2: Song | B2: Animals' Sounds | C2: https://drive.google.com/drive/folders/1yc8eIfjzYZSQfeTw6C_vK2llrCdi4tWJ?usp=drive_link | D2: https://drive.google.com/file/d/1rcFOFrk6vL6aTPD8ULzCM3AdHkU2pVsL/view?usp=sharing | E2: hoang98 | J2: =COUNTIF(L:L,K2) -> 1 | K2: the | L2: a | M2: =COUNTIF(K:K,L2) -> 1 | O2: away | P2: The drinks | Q2: https://drive.google.com/drive/folders/1kdAy8lMfrely6_SfSiyVT6fPr1vMa7JT?usp=drive_link | R2: lấy 2 loại đồ uống xếp cạnh nhau
A3: Song | B3: On the Road | C3: https://drive.google.com/drive/folders/11P9zz_QriUqHfFf7rB5Fq9D-EBviPgE9?usp=drive_link | D3: https://drive.google.com/file/d/18E18a5EE5PwVJi9LC0c-9m-catU6O1u6/view?usp=drive_link | E3: hoang98 | J3: =COUNTIF(L:L,K3) -> 1 | K3: of | L3: and | M3: =COUNTIF(K:K,L3) -> 1 | O3: blue | P3: Beans | Q3: https://drive.google.com/drive/folders/1skYOU7MyjB7nzd-vutpHaYBvtmg3CQUq?usp=drive_link | R3: trang 5
A4: Chant | B4: I Want to Play | C4: https://drive.google.com/drive/folders/1IgMNHIN51BY0leSpxFegS_O2zYKCxaD7 | D4: https://drive.google.com/file/d/1bw3h17-eYpiHeSV1iMwaifLc1Z-XeKV8/view?usp=drive_link | E4: Tuyen | J4: =COUNTIF(L:L,K4) -> 1 | K4: and | L4: away | M4: =COUNTIF(K:K,L4) -> 0 | O4: funny | P4: Places in the city | Q4: https://drive.google.com/file/d/1-ZWFPmAr9sXpQcHxOmyxYYjFEfRExGBL/view?usp=drive_link | R4: trang 6
A5: Chant | B5: In the Jungle | C5: https://drive.google.com/drive/folders/1U_6siK2WIDYKicFw9bIadoI8Zv2l3Q-L | D5: https://drive.google.com/file/d/12S4GG0v0V1IHA1g-RRHiWcJ94DDlSX40/view?usp=sharing | E5: Tuyen | J5: =COUNTIF(L:L,K5) -> 1 | K5: a | L5: big | M5: =COUNTIF(K:K,L5) -> 1 | O5: jump | P5: Sea Animals | Q5: https://www.shutterstock.com/catalog/licenses?q=under%20the%20sea&page=4
A6: Song | B6: Rainbow Song | C6: https://drive.google.com/drive/folders/1m9top7gRCEv-8PCedr_jOYywirGCB2Kf?usp=drive_link | D6: https://drive.google.com/file/d/1soMm1wwKhbNM98UXyGu116CECuWVygPW/view?usp=drive_link | E6: hoang98 | J6: =COUNTIF(L:L,K6) -> 1 | K6: to | L6: blue | M6: =COUNTIF(K:K,L6) -> 0 | O6: red | P6: The garden | Q6: https://drive.google.com/file/d/1sQQME-7lYAfqXvxXk4nhgmDBlkgh4363/view?usp=drive_link | R6: trang 11
A7: Song | B7: My Favorite Rooms | C7: https://drive.google.com/drive/folders/1AWi59CFgisqyTVQvVbyDUjnoPP9GRd1H | D7: https://drive.google.com/file/d/1KYsS9-zNXukSNMeAiIBDfIfyhEu9c-mb/view?usp=drive_link | E7: Tuyen | J7: =COUNTIF(L:L,K7) -> 0 | K7: in | L7: can | M7: =COUNTIF(K:K,L7) -> 1 | O7: run
A8: Song | B8: Shapes Around Me | C8: https://drive.google.com/drive/folders/1Iw3Ek2c3hZWNuTZNeDSNaH6US1EL2HKo | D8: https://drive.google.com/file/d/1HawdBMnSZ9QdU5-3BBZc6xctgGLTd3FP/view?usp=drive_link | E8: Tuyen | J8: =COUNTIF(L:L,K8) -> 0 | K8: is | L8: come | M8: =COUNTIF(K:K,L8) -> 1 | O8: said
A9: Chant | B9: Go and Hide | C9: https://drive.google.com/drive/folders/1YjyhSra836hPFZfGSnFlqG-STqm9CmWE | D9: https://drive.google.com/file/d/1fN_vjB6u678H6LbBpALbVJtxE0Jggr46/view?usp=drive_link | E9: TUyen | J9: =COUNTIF(L:L,K9) -> 1 | K9: you | L9: down | M9: =COUNTIF(K:K,L9) -> 1 | O9: yellow
A10: Chant | B10: Fruit Salad | C10: https://drive.google.com/drive/folders/1ahy7XjufTQoWJzN0zR3ckreH33eUwOrC?usp=sharing | D10: https://drive.google.com/file/d/13dv1xwdYNy1Gl_u5IjesDJ0_9_sgnV7y/view?usp=drive_link | E10: Hoang 90 | J10: =COUNTIF(L:L,K10) -> 1 | K10: this | L10: find | M10: =COUNTIF(K:K,L10) -> 1 | O10: am
A11: Song | B11: Shapes Around Me | C11: https://drive.google.com/drive/folders/1Iw3Ek2c3hZWNuTZNeDSNaH6US1EL2HKo | D11: https://drive.google.com/file/d/1HawdBMnSZ9QdU5-3BBZc6xctgGLTd3FP/view?usp=drive_link
A12: Song | B12: When I Grow Up | C12: https://drive.google.com/drive/folders/1TSrbd7NuyrWT6KJgV41EERlSw3xwSatT | D12: https://drive.google.com/file/d/1Cwjv-xxGm16Pbp4_gF0cbrkIM67F16gl/view?usp=drive_link | E12: Tuyen | J12: =COUNTIF(L:L,K12) -> 1 | K12: can | L12: funny | M12: =COUNTIF(K:K,L12) -> 0 | O12: black
A13: Song | B13: Peek-A-Boo | C13: https://drive.google.com/drive/folders/12ejnSY3CJo4mzOyYFQt86mqCvApU04jG?usp=sharing | D13: https://drive.google.com/file/d/1jHRr-uB_H-fUJtCAU5BoasbgUh-eTyKZ/view?usp=drive_link | E13: Hoang90 | J13: =COUNTIF(L:L,K13) -> 1 | K13: he | L13: go | M13: =COUNTIF(K:K,L13) -> 1 | O13: brown
A14: Song | B14: What Room Is It? | C14: https://drive.google.com/drive/folders/1Or04Iz51mqsVQeA5K8QGTDJvvTj9nFZA | D14: https://drive.google.com/file/d/1dHT8PlYKtjBEGmSSa-bl__VQE4Y_i2_z/view?usp=sharing | E14: Tuyen | J14: =COUNTIF(L:L,K14) -> 1 | K14: one | L14: help | M14: =COUNTIF(K:K,L14) -> 1 | O14: came
A15: Chant | B15: Let's Go Outside! | C15: https://drive.google.com/drive/folders/1awna3v4qycK1rBTeNYLMuLNmfv80DnZ9?usp=drive_link | D15: https://drive.google.com/file/d/1DPStwj6kGy0cxqxcn5g-A4_o-PtLI3T_/view?usp=drive_link | E15: HOang98 | J15: =COUNTIF(L:L,K15) -> 0 | K15: for | L15: here | M15: =COUNTIF(K:K,L15) -> 1 | O15: did
A16: Chant | B16: I Have No Fruits! | C16: https://drive.google.com/drive/folders/1IaxyeH-xaRwOQtFsgVD6HGVviDtIfMbb?usp=sharing | D16: https://drive.google.com/file/d/134lQ3cpoSGZPstB-35HCyEOCEzJEK57d/view?usp=sharing | E16: Dung | J16: =COUNTIF(L:L,K16) -> 1 | K16: on | L16: I | M16: =COUNTIF(K:K,L16) -> 1 | O16: eat
A17: Song | B17: My Favorite Rooms | C17: https://drive.google.com/drive/folders/1AWi59CFgisqyTVQvVbyDUjnoPP9GRd1H | D17: https://drive.google.com/file/d/1KYsS9-zNXukSNMeAiIBDfIfyhEu9c-mb/view?usp=drive_link
A18: Chant | B18: Wear Your Boots! | C18: https://drive.google.com/drive/folders/1-RpCS-Arh3SL7AZ5Nqqja98zD8c3Bc6g?usp=sharing | D18: https://drive.google.com/file/d/1KvsL5Qe2I3Gaqq_3Gg_-ZDijjqRcGDQD/view?usp=drive_link | E18: Hoang90 | J18: =COUNTIF(L:L,K18) -> 1 | K18: they | L18: it | M18: =COUNTIF(K:K,L18) -> 0 | O18: pretty
A19: Song | B19: My Messy Room | C19: https://drive.google.com/drive/folders/1bL3jmIOWNOWG5VEiZeMLduOYZ80vt12C?usp=drive_link | D19: https://drive.google.com/file/d/1xmwOdOFDthibRMxEtE1IVac4GCn_GX7y/view?usp=drive_link | E19: hoang98 | J19: =COUNTIF(L:L,K19) -> 1 | K19: three | L19: jump | M19: =COUNTIF(K:K,L19) -> 0 | O19: ran
A20: Song | B20: On the Road | C20: https://drive.google.com/drive/folders/11P9zz_QriUqHfFf7rB5Fq9D-EBviPgE9?usp=drive_link | D20: https://drive.google.com/file/d/18E18a5EE5PwVJi9LC0c-9m-catU6O1u6/view?usp=drive_link | E20: Hoang98 | J20: =COUNTIF(L:L,K20) -> 1 | K20: at | L20: little | M20: =COUNTIF(K:K,L20) -> 1 | O20: ride
A21: Song | B21: My Little Friends | C21: https://drive.google.com/drive/folders/15j06lLJPwdFWEgeDg4V60O5zuFV8kr8e | D21: https://drive.google.com/file/d/1wDTuXMLANSTL79whMRHUMZbewK6tX79u/view?usp=drive_link | E21: Tuyen | J21: =COUNTIF(L:L,K21) -> 1 | K21: be | L21: look | M21: =COUNTIF(K:K,L21) -> 1 | O21: saw
A22: Song | B22: Where’s Your Picture? | C22: https://drive.google.com/drive/folders/11VN7ZXTiCAr2Yx_YWGu1PCPdK2IybfnC?usp=sharing | D22: https://drive.google.com/file/d/1WJxKa5z3XD0j7wiyXaJW9aNNPwc9e0Nl/view?usp=drive_link | E22: Hoang90 | J22: =COUNTIF(L:L,K22) -> 1 | K22: that | L22: make | M22: =COUNTIF(K:K,L22) -> 1 | O22: soon
A23: Chant | B23: Animal Friends | C23: https://drive.google.com/drive/folders/1yXLebn3IS-06K64TpMdMx3ykJkq6BrV4 | D23: https://drive.google.com/file/d/1a5k3lZyA3fSIpltzihOt9kgknJp20Fb_/view?usp=sharing | E23: Tuyen | J23: =COUNTIF(L:L,K23) -> 1 | K23: have | L23: me | M23: =COUNTIF(K:K,L23) -> 1 | O23: was
A24: Song | B24: I'm Hungry | C24: https://drive.google.com/file/d/1CYF9-QBK9NtbjtPiq0T9TTLJ1LmpeWv7/view?usp=drive_link | D24: https://drive.google.com/file/d/1aN8FrU8_MOC_akP8olLzYT9lEWVPZGec/view?usp=drive_link | E24: Hoang98 | J24: =COUNTIF(L:L,K24) -> 1 | K24: from | L24: my | M24: =COUNTIF(K:K,L24) -> 1 | O24: went
A25: Song | B25: Family Harmony | C25: https://drive.google.com/drive/folders/1NlggoKvtOSxeHCG2KQjqbmCgKIHsg3Le | D25: https://drive.google.com/file/d/1TAQJIGxyj5dnKyLvY80SunZKB3VSmaIm/view?usp=sharing | E25: Tuyen | J25: =COUNTIF(L:L,K25) -> 1 | K25: or | L25: not | M25: =COUNTIF(K:K,L25) -> 1 | O25: white
A26: Song | B26: I Am a Young Firefighter | C26: https://drive.google.com/drive/folders/1mdmMED6lxus9GTSAP1_kLBYfaeO2Se1o | D26: https://drive.google.com/file/d/1sVQcnreRdA1UL-U4XdL7uizlIPmznyEb/view?usp=drive_link | E26: Tuyen | J26: =COUNTIF(L:L,K26) -> 1 | K26: way | L26: one | M26: =COUNTIF(K:K,L26) -> 1 | O26: could
A27: Chant | B27: On the farm | C27: https://drive.google.com/drive/folders/1WEgf8Ax8SNlnnNg5fDtcxB44-u3ognJ4?usp=sharing | D27: https://drive.google.com/file/d/18HtCQT26QKcSFz4OWHiXHSSYXEEvT9zK/view?usp=sharing | E27: Hoàng 90 | J27: =COUNTIF(L:L,K27) -> 1 | K27: but | L27: red | M27: =COUNTIF(K:K,L27) -> 0 | O27: going
A28: Chant | B28: How Are You? | C28: https://drive.google.com/drive/folders/1Zh2096MWkraOCh2F09K_OeiXMlnIDHqH?usp=sharing | D28: https://drive.google.com/file/d/1oQKHDWC4XASj2aXlAmr12Sh9SG8XjUVK/view?usp=sharing | E28: Hoàng 90 | J28: =COUNTIF(L:L,K28) -> 1 | K28: not | L28: run | M28: =COUNTIF(K:K,L28) -> 0 | O28: had
A29: Song | B29: Let’s Go Camping | C29: https://drive.google.com/drive/folders/15VII11O0SYjIa8ssRy8STGO2q1l7grXa?usp=sharing | D29: https://drive.google.com/file/d/1AOUr6O6josE8UCIzwGumLc_JJKYOTW1R/view?usp=sharing | J29: =COUNTIF(L:L,K29) -> 1 | K29: what | L29: said | M29: =COUNTIF(K:K,L29) -> 0 | O29: let
A30: Chant | B30: The Baker | C30: https://drive.google.com/drive/folders/1OljrDcCRMgaBpjBhQ_OA3Jd60wvGLnJX?usp=drive_link | D30: https://drive.google.com/file/d/1Z1DBvzmkmCP6UPlA_hXBAhDv50R62xMO/view?usp=drive_link | E30: Hoàng98 | J30: =COUNTIF(L:L,K30) -> 1 | K30: all | L30: see | M30: =COUNTIF(K:K,L30) -> 1 | O30: once
A31: Song | B31: I Love My Pets | C31: https://drive.google.com/drive/folders/1_OhceIzPcnjcvlcoEwcVeTMX_EUD26IF | D31: https://drive.google.com/file/d/1BsJ3KnX0Mp_Hc7Mnauzcx3a1wwNeSd5o/view?usp=sharing | E31: Tuyên | J31: =COUNTIF(L:L,K31) -> 1 | K31: I | L31: the | M31: =COUNTIF(K:K,L31) -> 1 | O31: round
A32: Chant | B32: How Is the Weather? | C32: https://drive.google.com/drive/folders/1zqG2j61xjiW8EoVAMiRzEgWGy3jDDBUZ?usp=sharing | D32: https://drive.google.com/file/d/1SxAlveyn7AyKkC6C2UifHpoBz4NTXK3g/view?usp=sharing | E32: Hoàng 90 | J32: =COUNTIF(L:L,K32) -> 1 | K32: his | L32: three | M32: =COUNTIF(K:K,L32) -> 1 | O32: stop
A33: Chant | B33: What's That Sound? | C33: https://drive.google.com/drive/folders/1ssLx4s0Fdfegm7acmVwNSwMY2FDxUDeS | D33: https://drive.google.com/file/d/1iP1Ify4WtY1mmxtwHJwbb_pRWoAz20vA/view?usp=sharing | E33: Tuyên | J33: =COUNTIF(L:L,K33) -> 1 | K33: we | L33: to | M33: =COUNTIF(K:K,L33) -> 1 | O33: thank
A34: Song | B34: Come Back Home! | C34: https://drive.google.com/drive/folders/1KZxHK0CZC3P1yUzNt0E_ugwakIBpesQ6?usp=sharing | D34: https://drive.google.com/file/d/1p9eJlpfPx7wiCYhpAZK0oY19C_Hq6oPj/view?usp=sharing | E34: Hoàng 90 | J34: =COUNTIF(L:L,K34) -> 1 | K34: when | L34: two | M34: =COUNTIF(K:K,L34) -> 1 | O34: walk
A35: Song | B35: In the Forest | C35: https://drive.google.com/drive/folders/13miywBHHg5zmyU_2bQbtVXqd7tKDE-Zk | D35: https://drive.google.com/file/d/1EJnb9F4MopCoU6N7sw6tMNei6ujFfyNj/view?usp=drive_link | E35: Tuyên | J35: =COUNTIF(L:L,K35) -> 1 | K35: your | L35: up | M35: =COUNTIF(K:K,L35) -> 1 | O35: were
J36: =COUNTIF(L:L,K36) -> 1 | K36: there | L36: we | M36: =COUNTIF(K:K,L36) -> 1 | O36: always
J37: =COUNTIF(L:L,K37) -> 1 | K37: two | L37: where | M37: =COUNTIF(K:K,L37) -> 1 | O37: before
J38: =COUNTIF(L:L,K38) -> 1 | K38: use | L38: yellow | M38: =COUNTIF(K:K,L38) -> 0 | O38: best
J39: =COUNTIF(L:L,K39) -> 1 | K39: an | L39: you | M39: =COUNTIF(K:K,L39) -> 1 | O39: buy
J40: =COUNTIF(L:L,K40) -> 0 | K40: each | L40: all | M40: =COUNTIF(K:K,L40) -> 1 | O40: don't
J41: =COUNTIF(L:L,K41) -> 1 | K41: top | L41: am | M41: =COUNTIF(K:K,L41) -> 0 | O41: fast
J42: =COUNTIF(L:L,K42) -> 1 | K42: she | L42: are | M42: =COUNTIF(K:K,L42) -> 0 | O42: five
J43: =COUNTIF(L:L,K43) -> 1 | K43: do | L43: at | M43: =COUNTIF(K:K,L43) -> 1 | O43: found
J44: =COUNTIF(L:L,K44) -> 1 | K44: how | L44: ate | M44: =COUNTIF(K:K,L44) -> 0 | O44: gave
J45: =COUNTIF(L:L,K45) -> 1 | K45: their | L45: be | M45: =COUNTIF(K:K,L45) -> 1 | O45: goes
J46: =COUNTIF(L:L,K46) -> 1 | K46: yes | L46: black | M46: =COUNTIF(K:K,L46) -> 0 | O46: green
J47: =COUNTIF(L:L,K47) -> 1 | K47: will | L47: brown | M47: =COUNTIF(K:K,L47) -> 0 | O47: its
... J149: =COUNTIF(L:L,K149) -> 1 | K149: every | L149: gave | M149: =COUNTIF(K:K,L149) -> 0 | O149: night
J150: =COUNTIF(L:L,K150) -> 0 | L150: goes | M150: =COUNTIF(K:K,L150) -> 0 | O150: paper
J151: =COUNTIF(L:L,K151) -> 1 | K151: over | L151: green | M151: =COUNTIF(K:K,L151) -> 0 | O151: party
J152: =COUNTIF(L:L,K152) -> 1 | K152: carry | L152: its | M152: =COUNTIF(K:K,L152) -> 0 | O152: picture
J153: =COUNTIF(L:L,K153) -> 1 | K153: together | L153: made | M153: =COUNTIF(K:K,L153) -> 0 | O153: pig
J154: =COUNTIF(L:L,K154) -> 1 | K154: myself | L154: many | M154: =COUNTIF(K:K,L154) -> 1 | O154: rabbit
J155: =COUNTIF(L:L,K155) -> 1 | K155: wash | L155: off | M155: =COUNTIF(K:K,L155) -> 1 | O155: rain
J156: =COUNTIF(L:L,K156) -> 1 | K156: both | L156: or | M156: =COUNTIF(K:K,L156) -> 1 | O156: ring
J157: =COUNTIF(L:L,K157) -> 1 | K157: children | L157: pull | M157: =COUNTIF(K:K,L157) -> 0 | O157: robin
J158: =COUNTIF(L:L,K158) -> 1 | K158: under | L158: read | M158: =COUNTIF(K:K,L158) -> 1 | O158: Santa Claus
J159: =COUNTIF(L:L,K159) -> 0 | L159: right | M159: =COUNTIF(K:K,L159) -> 1 | O159: school
J160: =COUNTIF(L:L,K160) -> 0 | K160: behind | L160: sing | M160: =COUNTIF(K:K,L160) -> 0 | O160: seed
J161: =COUNTIF(L:L,K161) -> 0 | K161: between | L161: sit | M161: =COUNTIF(K:K,L161) -> 0 | O161: sheep
J162: =COUNTIF(L:L,K162) -> 0 | K162: in front of | L162: sleep | M162: =COUNTIF(K:K,L162) -> 0 | O162: shoe
J163: =COUNTIF(L:L,K163) -> 1 | K163: under | L163: tell | M163: =COUNTIF(K:K,L163) -> 1 | O163: sister
J164: =COUNTIF(L:L,K164) -> 0 | K164: above | L164: their | M164: =COUNTIF(K:K,L164) -> 1 | O164: snow
J165: =COUNTIF(L:L,K165) -> 0 | K165: opposite | L165: these | M165: =COUNTIF(K:K,L165) -> 1 | O165: song
J166: =COUNTIF(L:L,K166) -> 0 | K166: next to | L166: those | M166: =COUNTIF(K:K,L166) -> 0 | O166: squirrel
J167: =COUNTIF(L:L,K167) -> 0 | K167: left | L167: upon | M167: =COUNTIF(K:K,L167) -> 0 | O167: stick
J168: =COUNTIF(L:L,K168) -> 1 | K168: right | L168: us | M168: =COUNTIF(K:K,L168) -> 1 | O168: street
L169: use | M169: =COUNTIF(K:K,L169) -> 1 | O169: sun
L170: very | M170: =COUNTIF(K:K,L170) -> 1 | O170: table
L171: wash | M171: =COUNTIF(K:K,L171) -> 1 | O171: thing
L172: which | M172: =COUNTIF(K:K,L172) -> 0 | O172: time
L173: why | M173: =COUNTIF(K:K,L173) -> 1 | O173: toy
L174: wish | M174: =COUNTIF(K:K,L174) -> 0 | O174: tree
L175: work | M175: =COUNTIF(K:K,L175) -> 0 | O175: watch
L176: would | M176: =COUNTIF(K:K,L176) -> 1 | O176: water
L177: write | M177: =COUNTIF(K:K,L177) -> 0 | O177: wind
L178: your | M178: =COUNTIF(K:K,L178) -> 1 | O178: window
L179: about | M179: =COUNTIF(K:K,L179) -> 1 | O179: wood
L180: better | M180: =COUNTIF(K:K,L180) -> 0
L181: bring | M181: =COUNTIF(K:K,L181) -> 0
L182: carry | M182: =COUNTIF(K:K,L182) -> 1
L183: clean | M183: =COUNTIF(K:K,L183) -> 0
L184: cut | M184: =COUNTIF(K:K,L184) -> 0
L185: done | M185: =COUNTIF(K:K,L185) -> 0
L186: draw | M186: =COUNTIF(K:K,L186) -> 0
L187: drink | M187: =COUNTIF(K:K,L187) -> 0
L188: eight | M188: =COUNTIF(K:K,L188) -> 0
L189: fall | M189: =COUNTIF(K:K,L189) -> 0
L190: far | M190: =COUNTIF(K:K,L190) -> 0
L191: full | M191: =COUNTIF(K:K,L191) -> 0
... L314: wood | M314: =COUNTIF(K:K,L314) -> 0

Sheet MG - Thống kê list game
B2: STT | C2: Round | D2: Khâu | E2: Done | F2: Doing | G2: To do | H2: error | I2: Total | J2: 35
B3: 1 | C3: Round 0 - PO chuẩn bị tài liệu | D3: Done + bàn giao docs 2 | E3: =countif('MG - Update tiến độ game'!J4:J40,"Done doc 2") -> 35 | F3: =countif('MG - Update tiến độ game'!J4:J40,"Doing") -> 0 | G3: =countif('MG - Update tiến độ game'!J4:J40,"Todo") -> 0 | H3: =35-sum(E3:G3) -> 0
B4: 2 | C4: Round 1.1 - Dev | D4: Dev (Unity) | E4: =countif('MG - Update tiến độ game'!T4:T40,"Done dev") -> 31 | F4: =countif('MG - Update tiến độ game'!T4:T40,"Doing") -> 4 | G4: =countif('MG - Update tiến độ game'!T4:T40,"Todo") -> 2 | H4: =35-sum(E4:G4) -> -2
B5: 3 | D5: BE config data | H5: =35-sum(E5:G5) -> 35
B6: 4 | D6: QA test | E6: =countif('MG - Update tiến độ game'!AL4:AL40,"Done") -> 11 | F6: =countif('MG - Update tiến độ game'!AL4:AL40,"Fix bug") -> 14 | G6: =countif('MG - Update tiến độ game'!AL4:AL40,"Todo") -> 10 | H6: =35-sum(E6:G6) -> 0
B7: 5 | C7: R1.2 - Nghiệm thu | D7: PO + GD + Artist nghiệm thu | F7: =countif('MG - Update tiến độ game'!F4:F40,"ND + GD nghiệm thu") -> 17 | H7: =35-sum(E7:G7) -> 18
B8: 6 | C8: Round 2.1 - Done fix bug | H8: =35-sum(E8:G8) -> 35
B9: 7 | C9: Round 2.2 Product Team nghiệm thu | F9: =countif('MG - Update tiến độ game'!F4:F40,"Product nghiệm thu") -> 0 | H9: =35-sum(E9:G9) -> 35
B10: 8 | C10: Round 3 - CR | F10: =countif('MG - Update tiến độ game'!F4:F40,"CR") -> 6
B11: 9 | C11: Game done | F11: =countif('MG - Update tiến độ game'!F4:F40,"Done - Release") -> 0

Sheet Testing data game
A1: - iOS: bản 410000215 - Android: Link
A2: STT | B2: ID game | C2: Game name | D2: Duration (s) | E2: Capacity (h) | F2: Deadline | G2: PiC Testing | H2: Status | I2: Note
A3: 1 | C3: Video interactive | F3: 45484 | G3: Thiên Anh | H3: Done 70 unit
A4: 2 | B4: MG.VD02 | C4: Video thường | F4: 45489 | G4: Thiên Anh | H4: Done 70 unit
A5: 3 | B5: BE.IP02 | C5: Egg cracking | D5: 45 | E5: =D5*60/3600+1 -> 1.75 | F5: 45492 | G5: Thiên Anh | H5: Done 70 unit | I5: chờ sửa highlight rồi test tiếp lỗi từ U9, U10
A6: 4 | B6: BE.GP06 | C6: Sound vocab matching | D6: 40 | E6: =D6*60/3600+1 -> 1.6666667 | F6: 45492 | G6: Hương | H6: Done 70 unit
A7: 5 | B7: BE.RST02 | C7: Multiple choice story 1 (chọn ảnh) | D7: 20 | E7: =D7*60/3600+0.5 -> 0.83333333 | F7: 45488 | G7: Thiên Anh | H7: Done 70 unit
C8: Multiple choice story 2 (chọn ảnh) | D8: 30 | E8: =D8*60/3600+1 -> 1.5 | F8: 45492 | G8: Nguyệt | H8: Done 70 unit | I8: đã test xong tất cả 35 act
A9: 6 | B9: BE.RP05 | C9: Multiple choice (cho audio chọn ảnh) | D9: 40 | E9: =D9*60/3600+0.5 -> 1.1666667 | F9: 45489 | G9: Thiên Anh | H9: Done 70 unit
A10: 7 | B10: EE.GS01 | C10: Letter Fishing | D10: 50 | E10: =D10*60/3600+0.5 -> 1.3333333 | F10: 45485 | G10: Linh | H10: Done 70 unit
A11: 8 | B11: BE.GP05 | C11: Trace the letter (Tracing) | D11: 110 | E11: =D11*60/3600+1 -> 2.8333333 | G11: Thiên Anh | I11: đang lỗi, chờ check lại
A12: 9 | B12: BE.GP01 | C12: Xe oto phonic | D12: 80 | E12: =D12*60/3600+1 -> 2.3333333 | F12: 45489 | G12: Linh | H12: Done 70 unit
A13: 10 | B13: BE.PP01 | C13: Blending sound | D13: 40 | E13: =D13*60/3600+1 -> 1.6666667 | F13: 45492 | G13: Thiên Anh | H13: Done 70 unit
A14: 11 | B14: BE.PV02 | C14: Cat teaching AI | D14: 80 | E14: =D14*60/3600+1 -> 2.3333333 | F14: 45492 | G14: Trang | I14: xong 20 Unit từ 1-20
A15: 12 | B15: BE.PV03 | C15: Robot teaching AI | D15: 80 | E15: =D15*60/3600+1 -> 2.3333333 | F15: 45488 | G15: Linh | H15: Done 70 unit
A16: 13 | B16: BE.GV05 | C16: Match the cards | D16: 40 | E16: =D16*60/3600+1 -> 1.6666667 | F16: 45492 | G16: Nguyệt | H16: Done 70 unit
A17: 14 | B17: BE.GV03 | C17: Puzzle | D17: 30 | E17: =D17*60/3600+0.5 -> 1 | F17: 45484 | G17: chị Thủy | H17: Done 60 unit
A18: 15 | B18: EE.GS03 | C18: Drag letters to build word M-ABC | D18: 30 | E18: =D18*60/3600+1 -> 1.5 | F18: 45492 | G18: Duyên | H18: Done 70 unit
A19: 16 | B19: BE.PV04 | C19: Drag letters to build word | D19: 40 | E19: =D19*60/3600+1 -> 1.6666667 | F19: 45492 | G19: Nguyệt | I19: đang lỗi, chờ check lại
A20: 17 | B20: MSP | C20: Word Fishing | D20: 60 | E20: =D20*60/3600+1 -> 2 | F20: 45492 | G20: Thiên Anh | H20: Đang test
A21: 18 | B21: BE.RP04 | C21: Listen and choose (cho audio chọn text) | D21: 30 | E21: =D21*60/3600+0.5 -> 1 | F21: 45489 | G21: Duyên | H21: Done 70 unit
A22: 19 | B22: MG.MC02 | C22: Multiple choice (ảnh) | F22: 45488 | G22: Thiên Anh | H22: Done 70 unit
A23: 20 | B23: BE.RV03 | C23: Listen and choose picture | D23: 40 | E23: =D23*60/3600+1 -> 1.6666667 | F23: 45492 | G23: Linh | H23: Done 70 unit
A24: 21 | B24: BE.RV06 | C24: Multiple choice (cho audio chọn text) | D24: 30 | E24: =D24*60/3600+1 -> 1.5 | F24: 45492 | G24: Hương | H24: Done 70 unit
A25: 22 | B25: BE.RV08 | C25: Catching fireflies | D25: 40 | E25: =D25*60/3600+0.5 -> 1.1666667 | F25: 45484 | G25: Duyên | H25: Done 70 unit
A26: 23 | B26: BE.IV01 | C26: Dinosaur chasing | D26: 60 | E26: =D26*60/3600+0.5 -> 1.5 | F26: 45489 | G26: Linh | H26: Done 70 unit
A27: 24 | B27: MG.TB02 | C27: Tap the bubbles | D27: 60 | E27: =D27*60/3600+1 -> 2 | F27: 45492 | G27: Thiên Anh | H27: Done 70 unit
A28: 25 | B28: BE.PS04 | C28: Speaking competition | D28: 100 | E28: =D28*60/3600+1 -> 2.6666667 | F28: 45492 | G28: Thiên Anh | H28: Đang test
A29: 26 | B29: BE.FS01 | C29: Điền thế - Intro sentence | D29: 40 | E29: =D29*60/3600+1 -> 1.6666667 | F29: 45492 | G29: Linh | H29: Done 70 unit
A30: 27 | B30: EE.PS01 | C30: Speaking sentence (AI) | D30: 110 | E30: =D30*60/3600+1 -> 2.8333333 | F30: 45492 | G30: Thiên Anh | I30: game thiếu sync text, cần sửa rồi mới test
A31: 28 | B31: BE.PS01 | C31: Brick layer | D31: 80 | E31: =D31*60/3600+1 -> 2.3333333 | F31: 45492 | G31: Thủy | H31: Done 70 unit
A32: 29 | B32: BE.RS02 | C32: Word machine | D32: 60 | E32: =D32*60/3600+0.5 -> 1.5 | F32: 45484 | G32: Linh | H32: Done 70 unit
A33: 30 | B33: BE.RVS02 | C33: Jumbled pages | D33: 70 | E33: =D33*32/3600+0.5 -> 1.1222222 | F33: 45484 | G33: Linh | H33: Done 70 unit | I33: Có 34 bài thui, mà e done nhé
A34: 31 | B34: BE.ID01 | C34: Intro dialog | F34: 45484 | G34: Thiên Anh | H34: Done 70 unit
A35: 32 | B35: MSP | C35: Chunking speaking | D35: 90 | E35: =D35*60/3600+1 -> 2.5 | F35: 45488 | G35: Thủy | H35: Done 70 unit
A36: 33 | B36: BE.PD01 | C36: Dialog 1 | D36: 90 | E36: =D36*60/3600+1 -> 2.5 | G36: Thiên Anh | H36: Done 70 unit
A37: 34 | B37: MSP | C37: Read the story | D37: 90 | E37: =D37*50/3600+0.5 -> 1.75 | F37: 45485 | G37: Duyên | H37: Done 70 unit | I37: 50 units
A38: 35 | B38: EE.IW01 | C38: Multisensory | D38: 60 | E38: =D38*2*4*41/3600+1 -> 6.4666667 | H38: Đang test
A39: 36 | B39: EE.IV01 | C39: Flashcard | D39: 20 | E39: =D39*2*4*41/3600+1 -> 2.8222222 | G39: Linh
A40: 37 | B40: EE.IW04 | C40: Tap the balloon | D40: 30 | E40: =D40*4*4*41/3600+1 -> 6.4666667 | G40: Duyên
A41: 38 | B41: EE.RW08 | C41: Multi-bubble | D41: 20 | E41: =D41*4*4*41/3600+1 -> 4.6444444 | G41: Duyên
A42: 39 | B42: EE.RV01 | C42: Multiple choice - Image | D42: 20 | E42: =D42*4*4*41/3600+1 -> 4.6444444 | G42: Duyên
A43: 40 | B43: EE.RW02 | C43: Listen and Choose 2 | D43: 15 | E43: =D43*4*41/3600+1 -> 1.6833333 | G43: Duyên | H43: Done 41 unit
A44: 41 | B44: EE.IV04 | C44: Tap 3 options + Flashcard | D44: 30 | E44: =D44*4*41/3600+1 -> 2.3666667 | G44: Linh | I44: Duyên đã test 10 bài đầu
A45: 42 | B45: MJ.ST01 | C45: Đọc truyện | G45: Duyên | H45: Done 41 unit
A46: 43 | B46: MJ.VD03 | C46: Video thường | D46: 60 | E46: =D46*33/3600+0.5 -> 1.05

Sheet MG - Update tiến độ game
H1: Round 0 - GD + PO chuẩn bị tài liệu | R1: Round 1.1 - Dev (Unity) | AA1: Round 1.1 - BE config data | AH1: Round 1.1 QA test | AR1: R1.2 - PO + GD + Artist nghiệm thu | AW1: Round 2.1 - Done fix bug | AZ1: Round 2.2 Product Team nghiệm thu
K2: Dự kiến | L2: Thực tế | V2: Timeline dự kiến | X2: Timeline thực tế | AE2: Dự kiến | AF2: Thực tế | AK2: Dự kiến | AN2: Thực tế | AT2: Dự kiến | AU2: Thực tế | AW2: Dự kiến | AX2: Thực tế | AZ2: Dự kiến | BA2: Thực tế
A3: STT | B3: ID game | C3: Game name | E3: Status game | F3: Nghiệm thu | H3: Link tham khảo | I3: Doc 2 | J3: Trạng thái doc | K3: Ngày trả docs | L3: Ngày trả docs | M3: Data game | N3: Note | O3: Thời gian chuyển dev | P3: Thời gian cần done data | R3: huongbt_note CR game | S3: PIC dev | T3: STT dev | U3: ETA (days) | V3: Start dev | W3: End dev | X3: Start dev | Y3: End dev | AA3: BE Config (1h/ 1 game) | AB3: BE 2 Activity Test | AC3: PO full data | AD3: BE Full Data | AE3: UN Ghép data | AF3: UN Ghép data | AH3: PIC QA | AI3: Start Testcase | AJ3: ETA test game (giờ) | AK3: Start QA | AL3: Done QA | AM3: Ngày chuyển PO nghiệm thu - R1 | AN3: Start QA | AO3: Done QA | AP3: Ngày chuyển PO nghiệm thu - R1 | AR3: PO_Nghiệm thu game play | AS3: PO_Nghiệm thu game 1 - 2 unit | AT3: PO chuyển Dev | AU3: PO chuyển Dev | AW3: Dev chuyển PO | AX3: Dev chuyển PO | AZ3: Product Team nghiệm thu | BA3: Product Team nghiệm thu | BE3: STT QA_Done game play | BF3: Start QA - testing game 1-2 unit | BG3: Done QA - testing game 1-2 unit | BH3: PO_Nghiệm thu flow
A4: 1 | C4: Video interactive | E4: Mới | F4: ND + GD nghiệm thu | I4: Link | J4: Done doc 2 | K4: 45425 | L4: 45425 | M4: các line bôi xanh | N4: cần check lại với dev để làm doc | O4: 45425 | P4: 45439 | S4: Tài | T4: Done dev | V4: 45425 | AA4: Done | AB4: Done | AE4: 30/5 | AH4: Linh Phạm | AI4: Done | AJ4: 4 | AL4: Todo | BE4: =IF(AND(AK4>0,AL4>0),"Done dev",IF(AND(AK4>0,AL4=""),"Doing","Todo")) -> Todo
A5: 2 | B5: MG.VD02 | C5: Video thường | E5: Done dev | F5: ND + GD nghiệm thu | I5: Link | J5: Done doc 2 | L5: 14/6 | N5: Hương check lại game này | P5: 45436 | S5: Nam | T5: Done dev | AA5: Done | AB5: Done | AE5: 30/5 | AH5: Linh Phạm | AI5: Done | AJ5: 1 | AL5: Todo | BE5: =IF(AND(AK5>0,AL5>0),"Done dev",IF(AND(AK5>0,AL5=""),"Doing","Todo")) -> Todo
A6: 3 | B6: BE.IP02 | C6: Egg cracking | E6: Cần sửa | F6: Cần sửa | H6: Link | I6: Link | J6: Done doc 2 | K6: 45429 | L6: 45429 | M6: Âm ở cột E & F Dùng text + ảnh từ | N6: sửa art | O6: 45429 | P6: 45435 | S6: Thuận | T6: =IF(AND(V6>0,W6>0),"Done dev",IF(AND(V6>0,W6=""),"Doing","Todo")) -> Done dev | U6: 2 days - sáng 22/5 | V6: 17/5 | W6: 45434 | AA6: Done | AB6: Done | AC6: Done | AE6: 30/5 | AH6: Linh Phạm | AI6: Done | AJ6: 4 | AK6: 45445 | AL6: Done | AM6: 45448 | AO6: 45388 | AP6: 45448 | BE6: =IF(AND(AK6>0,AL6>0),"Done dev",IF(AND(AK6>0,AL6=""),"Doing","Todo")) -> Done dev
A7: 4 | B7: BE.GP06 | C7: Sound vocab matching | D7: 50 | E7: Done dev | F7: ND + GD nghiệm thu | H7: Link | I7: Link | J7: Done doc 2 | M7: Âm ở cột E & F Dùng text + ảnh từ | N7: cần check lại xem âm sẽ hiện dạng ảnh hay tự generate từ text | P7: 45435 | S7: Tuấn Anh | T7: Done dev | AA7: Done | AB7: Done | AC7: Done | AE7: 30/5 | AH7: Linh Phạm | AI7: Done | AJ7: 2 | AK7: 45446 | AL7: Fix bug | BE7: Doing
A8: 5 | B8: BE.RST02 | C8: Multiple choice story (chọn ảnh) | E8: Cần sửa | F8: ND + GD nghiệm thu | H8: Link | I8: Link | J8: Done doc 2 | K8: 45432 | L8: 20/5 - thiếu UI, 22/5 mới trả | M8: Lesson 1 (phonics): chọn tất cả 4 đáp án (ảnh từ phonics) Lesson 3 (truyện): chọn các hình ảnh xuất hiện trong bài (có thể 1-4 đáp án) Lesson 5 (truyện): CHTT đọc hiểu truyện | N8: check lại dạng 4 đáp án, có thể chọn nhiều đáp án đúng cần bổ sung CTA | O8: 45432 | P8: D2 | R8: - CR: Chuyển từ 3 đáp án thành 4 đáp án - Flexible giữa 3 vs 4 đáp án, và có câu đc chọn nhiều đáp án đúng | S8: Tài | T8: =IF(AND(V8>0,W8>0),"Done dev",IF(AND(V8>0,W8=""),"Doing","Todo")) -> Done dev | U8: 2 days | V8: 45433 | W8: 24/5 | AA8: Done | AB8: Done | AE8: 30/5 | AH8: Linh Phạm | AI8: Done | AJ8: 2 | AK8: 45445 | AL8: Done | AM8: 45448 | AO8: 45388 | AP8: 45448 | BE8: =IF(AND(AK8>0,AL8>0),"Done dev",IF(AND(AK8>0,AL8=""),"Doing","Todo")) -> Done dev
A9: 6 | B9: BE.RP05 | C9: Multiple choice (cho audio chọn ảnh) | E9: Done dev | F9: CR | H9: Link | I9: Link | J9: Done doc 2 | K9: 45447 | L9: 45447 | M9: Dùng text + ảnh từ | N9: voi Ellie cân nhắc thay đổi game play cho đỡ tĩnh + object nên có stroke trắng ko có đáp án nhiễu | P9: D2 | S9: Tài | T9: Done dev | AA9: Done | AB9: Done | AC9: Done | AE9: 30/5 | AH9: Linh Phạm | AI9: Done | AJ9: 2 | AK9: 45444 | AL9: Fix bug | AM9: 45448 | AP9: 45448 | BE9: =IF(AND(AK9>0,AL9>0),"Done dev",IF(AND(AK9>0,AL9=""),"Doing","Todo")) -> Done dev
A10: 7 | B10: EE.GS01 | C10: Letter Fishing | D10: 50 | E10: Mới | H10: Link | I10: Link | J10: Done doc 2 | M10: chơi âm chính trong lesson (cột E & F) | N10: game M-ABC cần dev mới | O10: 45425 | P10: D2 | R10: thay CTA game | S10: Tài | T10: Done dev | AA10: Done | AB10: Done | AC10: Done | AE10: 30/5 | AH10: Linh Phạm | AI10: Done | AJ10: 4 | AK10: 31/5 | AL10: Fix bug | AM10: 45448 | AP10: 45448 | BE10: =IF(AND(AK10>0,AL10>0),"Done dev",IF(AND(AK10>0,AL10=""),"Doing","Todo")) -> Done dev
A11: 8 | B11: BE.GP05 | C11: Trace the letter (Tracing) | E11: Dev mới | F11: CR | I11: Link | J11: Done doc 2 | K11: 45447 | L11: 45357 | M11: chơi âm chính trong lesson (cột E & F) Hệ thống cần tự generate ra letter name + letter sound tương ứng | N11: cần có dạng vẽ 2-3 chữ cái cạnh nhau xem xét sửa CTA auto config check lại nét vẽ chuẩn của các chữ cái r, m, n,... | O11: NO | S11: Tùng | T11: Done dev | AA11: Done | AB11: Done | AC11: Done | AE11: 30/5 | AH11: Linh Phạm | AJ11: 2 | AK11: 45446 | AL11: Done | AR11: Chuyển round cũ | BE11: Done_Game play
A12: 9 | B12: BE.GP01 | C12: Xe oto phonic | E12: Cần sửa | F12: ND + GD nghiệm thu | H12: Link | I12: Link | J12: Done doc 2 | K12: 45434 | L12: 27/5 | M12: nếu ko chơi đc 2 lượt thì sẽ chơi 1 lượt random từ | N12: cần check xem chơi đc 2 lượt ko Huong note: làm game mới | O12: 23/5 | P12: 45435 | R12: Đổi nhiều | S12: Nam | T12: =IF(AND(V12>0,W12>0),"Done dev",IF(AND(V12>0,W12=""),"Doing","Todo")) -> Doing | U12: 4 days -3/6 | V12: 27/5 | AA12: Done | AB12: Done | AC12: Done | AE12: 45357 | AH12: Linh Phạm | AI12: Done | AJ12: 2 | AL12: Todo | BE12: =IF(AND(AK12>0,AL12>0),"Done dev",IF(AND(AK12>0,AL12=""),"Doing","Todo")) -> Todo
A13: 10 | B13: BE.PP01 | C13: Blending sound | E13: Dev mới | F13: CR | H13: Link | I13: Link | J13: Done doc 2 | K13: 45448 | L13: 45388 | M13: nếu ko chơi đc 2 lượt thì sẽ chơi 1 lượt random từ | N13: chỉ để đúng số lượng letter, mỗi lần chọn thì mất 1 cái cần check xem chơi đc 2 lượt ko | P13: 45435 | S13: Tuấn Anh | T13: Done dev | AA13: Done | AB13: Done | AC13: Done | AE13: 30/5 | AH13: Linh Phạm | AJ13: 4 | AL13: Todo | BE13: =IF(AND(AK13>0,AL13>0),"Done dev",IF(AND(AK13>0,AL13=""),"Doing","Todo")) -> Todo
A14: 11 | B14: BE.PV02 | C14: Cat teaching AI | E14: Cần sửa | F14: ND + GD nghiệm thu | I14: Link | J14: Done doc 2 | K14: 45427 | L14: 45427 | M14: 4 từ | N14: sửa mic chơi số lượt theo data được config | O14: 45432 | P14: D2 | R14: - CR: thay UI mic + chơi số lượt theo data config + UI nhân vật + SFX trả điểm, logic đúng sai | S14: Nam | T14: =IF(AND(V14>0,W14>0),"Done dev",IF(AND(V14>0,W14=""),"Doing","Todo")) -> Done dev | U14: 1h Sáng 24/5 | V14: 45435 | W14: 24/5 | AA14: Done | AB14: Done | AC14: Done | AE14: 30/5 | AH14: Linh Phạm | AI14: Done | AJ14: 2 | AK14: 45444 | AL14: Fix bug | AM14: 45448 | AP14: 45448 | BE14: =IF(AND(AK14>0,AL14>0),"Done dev",IF(AND(AK14>0,AL14=""),"Doing","Todo")) -> Done dev
A15: 12 | B15: BE.PV03 | C15: Robot teaching AI | E15: Cần sửa | F15: ND + GD nghiệm thu | H15: Link | I15: Link | J15: Done doc 2 | K15: 45427 | L15: 45427 | M15: 4 từ | N15: sửa mic chơi số lượt theo data được config | O15: 45432 | P15: D2 | R15: - CR: thay UI mic + chơi số lượt theo data config + UI nhân vật + SFX trả điểm, logic đúng sai | S15: Nam | T15: =IF(AND(V15>0,W15>0),"Done dev",IF(AND(V15>0,W15=""),"Doing","Todo")) -> Done dev | U15: 1h Sáng 24/5 | V15: 45435 | W15: 24/5 | AA15: Done | AB15: Done | AC15: Done | AE15: 30/5 | AH15: Linh Phạm | AI15: Done | AJ15: 1 | AK15: 45444 | AL15: Fix bug | AM15: 45448 | AP15: 45448 | BE15: =IF(AND(AK15>0,AL15>0),"Done dev",IF(AND(AK15>0,AL15=""),"Doing","Todo")) -> Done dev
A16: 13 | B16: BE.GV05 | C16: Match the cards | E16: Cần sửa | F16: ND + GD nghiệm thu | H16: Link | I16: Link | J16: Done doc 2 | K16: 45429 | L16: 45432 | M16: Dùng text + ảnh từ | N16: sửa art thêm tính năng tự config background cho game + chọn màu thẻ | O16: 45432 | P16: D2 | R16: - thay đổi art - anim pháo hoa đổi thành spine mới | S16: Nam | T16: =IF(AND(V16>0,W16>0),"Done dev",IF(AND(V16>0,W16=""),"Doing","Todo")) -> Done dev | U16: 4h | V16: 20/5 | W16: 45434 | AA16: Done | AB16: Done | AC16: Done | AE16: 30/5 | AH16: Linh Phạm | AI16: Done | AJ16: 2 | AK16: 45297 | AL16: Done | AM16: 45448 | AO16: 45388 | AP16: 45448 | BE16: =IF(AND(AK16>0,AL16>0),"Done dev",IF(AND(AK16>0,AL16=""),"Doing","Todo")) -> Done dev
A17: 14 | B17: BE.GV03 | C17: Puzzle | E17: Đã nghiệm thu | F17: ND + GD nghiệm thu | I17: Link | J17: Done doc 2 | M17: Dùng text + ảnh từ | N17: chơi số lượt theo data config (hiện tại là 2 lượt) | P17: D2 | R17: chơi số lượt theo data config (hiện tại là 2 lượt) | S17: Tuấn Anh | T17: Done dev | AA17: Done | AB17: Done | AC17: Done | AE17: 30/5 | AI17: Done | AK17: 45446 | AL17: Done | BE17: Done
A18: 15 | B18: EE.GS03 | C18: Drag letters to build word M-ABC | E18: Mới | F18: ND + GD nghiệm thu | H18: Link | I18: Link | J18: Done doc 2 | K18: 45448 | L18: 45357 | M18: hệ thống tự random 1-3 chữ cái cần drag vào từ (tự động gắn audio của chữ cái) | N18: game M-ABC cần dev mới | O18: 45425 | P18: D2 | S18: Thuận | T18: Done dev | V18: 45425 | AA18: Done | AB18: Done | AC18: Done | AE18: 30/5 | AH18: Linh Phạm | AI18: Done | AJ18: 4 | AK18: 45444 | AL18: Fix bug | AM18: 45448 | AP18: 45448 | BE18: =IF(AND(AK18>0,AL18>0),"Done dev",IF(AND(AK18>0,AL18=""),"Doing","Todo")) -> Done dev
